package com.qq.e.comm.plugin.w.a;

import android.content.Context;
import android.util.Pair;
import com.qq.e.comm.plugin.ad.f;
import com.qq.e.comm.plugin.t.b.f;
import com.qq.e.comm.plugin.util.j;
import com.qq.e.comm.util.GDTLogger;
import java.util.Map;
import java.util.concurrent.Exchanger;
import java.util.concurrent.TimeUnit;
import java.util.concurrent.atomic.AtomicInteger;
import org.json.JSONObject;
import yaq.gdtadv;

public class d {
  private static final AtomicInteger a = new AtomicInteger();
  
  static Pair<Integer, JSONObject> a(String paramString, long paramLong, a parama, e parame, b paramb) {
    return (Pair<Integer, JSONObject>)gdtadv.getobjresult(62, 1, new Object[] { paramString, Long.valueOf(paramLong), parama, parame, paramb });
  }
  
  static String a(String paramString1, JSONObject paramJSONObject, int paramInt1, String paramString2, int paramInt2) {
    return (String)gdtadv.getobjresult(63, 1, new Object[] { paramString1, paramJSONObject, Integer.valueOf(paramInt1), paramString2, Integer.valueOf(paramInt2) });
  }
  
  static String a(String paramString1, JSONObject paramJSONObject, int paramInt1, String paramString2, int paramInt2, int paramInt3) {
    return (String)gdtadv.getobjresult(64, 1, new Object[] { paramString1, paramJSONObject, Integer.valueOf(paramInt1), paramString2, Integer.valueOf(paramInt2), Integer.valueOf(paramInt3) });
  }
  
  public static String a(String paramString1, JSONObject paramJSONObject, String paramString2, int paramInt) {
    return (String)gdtadv.getobjresult(65, 1, new Object[] { paramString1, paramJSONObject, paramString2, Integer.valueOf(paramInt) });
  }
  
  public static <T> void a(T paramT) {
    gdtadv.getVresult(67, 1, new Object[] { paramT });
  }
  
  public static <T> void a(T paramT, a parama, e parame, b paramb) {
    gdtadv.getVresult(68, 1, new Object[] { paramT, parama, parame, paramb });
  }
  
  public static void a(String paramString, com.qq.e.comm.plugin.s.a parama, j<Pair<Integer, JSONObject>> paramj) {
    gdtadv.getVresult(69, 1, new Object[] { paramString, parama, paramj });
  }
  
  public static void a(String paramString, JSONObject paramJSONObject, e parame, b paramb, Map<String, Object> paramMap) {
    gdtadv.getVresult(70, 1, new Object[] { paramString, paramJSONObject, parame, paramb, paramMap });
  }
  
  public static <T> void b(T paramT) {
    gdtadv.getVresult(73, 1, new Object[] { paramT });
  }
  
  private static boolean b(Context paramContext, a parama, b paramb, e parame) {
    return gdtadv.getZresult(74, 1, new Object[] { paramContext, parama, paramb, parame });
  }
  
  public static <T> void c(T paramT) {
    gdtadv.getVresult(76, 1, new Object[] { paramT });
  }
  
  private static boolean d(a parama, b paramb) {
    return gdtadv.getZresult(78, 1, new Object[] { parama, paramb });
  }
  
  private static boolean e(a parama, b paramb) {
    return gdtadv.getZresult(79, 1, new Object[] { parama, paramb });
  }
  
  private static boolean f(a parama, b paramb) {
    return gdtadv.getZresult(80, 1, new Object[] { parama, paramb });
  }
  
  public static class a {
    public final JSONObject a;
    
    public final String b;
    
    public final com.qq.e.comm.plugin.s.a c;
    
    public a(JSONObject param1JSONObject, String param1String) {
      this(param1JSONObject, param1String, null);
    }
    
    public a(JSONObject param1JSONObject, String param1String, com.qq.e.comm.plugin.s.a param1a) {
      this.a = param1JSONObject;
      this.b = param1String;
      this.c = param1a;
    }
    
    public String toString() {
      StringBuilder stringBuilder = new StringBuilder();
      stringBuilder.append("ADParam [adInfo=");
      stringBuilder.append(this.a);
      stringBuilder.append(", clickURL=");
      stringBuilder.append(this.b);
      stringBuilder.append("]");
      return stringBuilder.toString();
    }
  }
  
  public static class b {
    public int a;
    
    public int b;
    
    public d.c c;
    
    public String d;
    
    public boolean e;
    
    public boolean f;
    
    public boolean g;
    
    public f h;
    
    public int i;
    
    public int j;
    
    public boolean k = true;
    
    private boolean l;
    
    private boolean m = false;
    
    public b(int param1Int, d.c param1c) {
      this.b = param1Int;
      this.c = param1c;
      this.a = 0;
      this.j = 0;
    }
    
    public b a(int param1Int) {
      this.a = param1Int;
      return this;
    }
    
    public b a(f param1f) {
      this.h = param1f;
      return this;
    }
    
    public b a(String param1String) {
      this.d = param1String;
      return this;
    }
    
    public b a(boolean param1Boolean) {
      this.l = param1Boolean;
      return this;
    }
    
    public boolean a() {
      return this.l;
    }
    
    public b b(int param1Int) {
      if (param1Int != 1) {
        this.e = false;
        this.f = false;
        if (param1Int == 2) {
          this.g = false;
          return this;
        } 
        this.g = true;
        return this;
      } 
      this.e = true;
      this.f = true;
      this.g = true;
      return this;
    }
    
    public b b(boolean param1Boolean) {
      this.m = param1Boolean;
      return this;
    }
    
    public boolean b() {
      return this.m;
    }
    
    public b c(int param1Int) {
      this.j = param1Int;
      return this;
    }
  }
  
  public enum c {
    a, b;
  }
  
  static class d<T> implements Runnable {
    private final T a;
    
    private final d.a b;
    
    private final d.b c;
    
    private final d.e d;
    
    private com.qq.e.comm.plugin.y.c e = new com.qq.e.comm.plugin.y.c();
    
    public d(T param1T, d.a param1a, d.b param1b, d.e param1e) {
      this.a = param1T;
      this.b = param1a;
      this.c = param1b;
      this.d = param1e;
      this.e.a(param1e.c);
      if (param1a.a != null) {
        this.e.b(param1a.a.optString("cl"));
        this.e.c(param1a.a.optString("traceid"));
      } 
    }
    
    public void run() {
      // Byte code:
      //   0: invokestatic a : ()Ljava/util/concurrent/atomic/AtomicInteger;
      //   3: invokevirtual incrementAndGet : ()I
      //   6: pop
      //   7: aload_0
      //   8: getfield a : Ljava/lang/Object;
      //   11: instanceof android/view/View
      //   14: istore_2
      //   15: iload_2
      //   16: ifeq -> 90
      //   19: aload_0
      //   20: getfield a : Ljava/lang/Object;
      //   23: checkcast android/view/View
      //   26: invokevirtual getRootView : ()Landroid/view/View;
      //   29: invokevirtual getContext : ()Landroid/content/Context;
      //   32: astore_3
      //   33: aload_0
      //   34: getfield c : Lcom/qq/e/comm/plugin/w/a/d$b;
      //   37: getfield i : I
      //   40: ifgt -> 63
      //   43: aload_0
      //   44: getfield c : Lcom/qq/e/comm/plugin/w/a/d$b;
      //   47: invokestatic a : ()Lcom/qq/e/comm/plugin/ad/a;
      //   50: aload_0
      //   51: getfield a : Ljava/lang/Object;
      //   54: checkcast android/view/View
      //   57: invokevirtual b : (Landroid/view/View;)I
      //   60: putfield i : I
      //   63: ldc 'gdt_tag_p'
      //   65: ldc 'DoClickRunable : viewIdentifier = %d'
      //   67: iconst_1
      //   68: anewarray java/lang/Object
      //   71: dup
      //   72: iconst_0
      //   73: aload_0
      //   74: getfield c : Lcom/qq/e/comm/plugin/w/a/d$b;
      //   77: getfield i : I
      //   80: invokestatic valueOf : (I)Ljava/lang/Integer;
      //   83: aastore
      //   84: invokestatic b : (Ljava/lang/String;Ljava/lang/String;[Ljava/lang/Object;)V
      //   87: goto -> 181
      //   90: aload_0
      //   91: getfield a : Ljava/lang/Object;
      //   94: instanceof com/qq/e/comm/plugin/ab/h
      //   97: ifeq -> 799
      //   100: aload_0
      //   101: getfield a : Ljava/lang/Object;
      //   104: checkcast com/qq/e/comm/plugin/ab/h
      //   107: invokeinterface a : ()Landroid/view/View;
      //   112: invokevirtual getRootView : ()Landroid/view/View;
      //   115: invokevirtual getContext : ()Landroid/content/Context;
      //   118: astore_3
      //   119: aload_0
      //   120: getfield c : Lcom/qq/e/comm/plugin/w/a/d$b;
      //   123: getfield i : I
      //   126: ifgt -> 154
      //   129: aload_0
      //   130: getfield c : Lcom/qq/e/comm/plugin/w/a/d$b;
      //   133: invokestatic a : ()Lcom/qq/e/comm/plugin/ad/a;
      //   136: aload_0
      //   137: getfield a : Ljava/lang/Object;
      //   140: checkcast com/qq/e/comm/plugin/ab/h
      //   143: invokeinterface a : ()Landroid/view/View;
      //   148: invokevirtual b : (Landroid/view/View;)I
      //   151: putfield i : I
      //   154: ldc 'gdt_tag_p'
      //   156: ldc 'DoClickRunable(IWebView) : viewIdentifier = %d'
      //   158: iconst_1
      //   159: anewarray java/lang/Object
      //   162: dup
      //   163: iconst_0
      //   164: aload_0
      //   165: getfield c : Lcom/qq/e/comm/plugin/w/a/d$b;
      //   168: getfield i : I
      //   171: invokestatic valueOf : (I)Ljava/lang/Integer;
      //   174: aastore
      //   175: invokestatic b : (Ljava/lang/String;Ljava/lang/String;[Ljava/lang/Object;)V
      //   178: goto -> 181
      //   181: aload_0
      //   182: getfield b : Lcom/qq/e/comm/plugin/w/a/d$a;
      //   185: getfield c : Lcom/qq/e/comm/plugin/s/a;
      //   188: instanceof com/qq/e/comm/plugin/s/f
      //   191: ifeq -> 804
      //   194: aload_0
      //   195: getfield b : Lcom/qq/e/comm/plugin/w/a/d$a;
      //   198: getfield c : Lcom/qq/e/comm/plugin/s/a;
      //   201: checkcast com/qq/e/comm/plugin/s/f
      //   204: invokevirtual ap : ()Ljava/lang/Boolean;
      //   207: invokevirtual booleanValue : ()Z
      //   210: ifeq -> 804
      //   213: iconst_1
      //   214: istore_1
      //   215: goto -> 218
      //   218: iload_1
      //   219: ifne -> 547
      //   222: aload_0
      //   223: getfield b : Lcom/qq/e/comm/plugin/w/a/d$a;
      //   226: getfield a : Lorg/json/JSONObject;
      //   229: invokestatic c : (Lorg/json/JSONObject;)Z
      //   232: ifeq -> 238
      //   235: goto -> 547
      //   238: aload_0
      //   239: getfield c : Lcom/qq/e/comm/plugin/w/a/d$b;
      //   242: getfield b : I
      //   245: bipush #18
      //   247: if_icmpne -> 265
      //   250: aload_0
      //   251: getfield b : Lcom/qq/e/comm/plugin/w/a/d$a;
      //   254: aload_0
      //   255: getfield c : Lcom/qq/e/comm/plugin/w/a/d$b;
      //   258: invokestatic a : (Lcom/qq/e/comm/plugin/w/a/d$a;Lcom/qq/e/comm/plugin/w/a/d$b;)Z
      //   261: pop
      //   262: goto -> 610
      //   265: aload_0
      //   266: getfield c : Lcom/qq/e/comm/plugin/w/a/d$b;
      //   269: getfield b : I
      //   272: iconst_1
      //   273: if_icmpne -> 313
      //   276: aload_0
      //   277: getfield b : Lcom/qq/e/comm/plugin/w/a/d$a;
      //   280: getfield a : Lorg/json/JSONObject;
      //   283: invokestatic a : (Lorg/json/JSONObject;)Z
      //   286: ifeq -> 313
      //   289: aload_0
      //   290: getfield a : Ljava/lang/Object;
      //   293: aload_3
      //   294: aload_0
      //   295: getfield b : Lcom/qq/e/comm/plugin/w/a/d$a;
      //   298: aload_0
      //   299: getfield c : Lcom/qq/e/comm/plugin/w/a/d$b;
      //   302: aload_0
      //   303: getfield d : Lcom/qq/e/comm/plugin/w/a/d$e;
      //   306: invokestatic a : (Ljava/lang/Object;Landroid/content/Context;Lcom/qq/e/comm/plugin/w/a/d$a;Lcom/qq/e/comm/plugin/w/a/d$b;Lcom/qq/e/comm/plugin/w/a/d$e;)Z
      //   309: pop
      //   310: goto -> 610
      //   313: aload_0
      //   314: getfield c : Lcom/qq/e/comm/plugin/w/a/d$b;
      //   317: getfield b : I
      //   320: ifne -> 363
      //   323: aload_0
      //   324: getfield a : Ljava/lang/Object;
      //   327: astore #4
      //   329: aload_0
      //   330: getfield b : Lcom/qq/e/comm/plugin/w/a/d$a;
      //   333: astore #5
      //   335: aload_0
      //   336: getfield c : Lcom/qq/e/comm/plugin/w/a/d$b;
      //   339: astore #6
      //   341: aload_0
      //   342: getfield d : Lcom/qq/e/comm/plugin/w/a/d$e;
      //   345: astore #7
      //   347: aload #4
      //   349: aload_3
      //   350: aload #5
      //   352: aload #6
      //   354: aload #7
      //   356: invokestatic a : (Ljava/lang/Object;Landroid/content/Context;Lcom/qq/e/comm/plugin/w/a/d$a;Lcom/qq/e/comm/plugin/w/a/d$b;Lcom/qq/e/comm/plugin/w/a/d$e;)Z
      //   359: pop
      //   360: goto -> 610
      //   363: bipush #36
      //   365: aload_0
      //   366: getfield c : Lcom/qq/e/comm/plugin/w/a/d$b;
      //   369: getfield b : I
      //   372: if_icmpne -> 395
      //   375: aload_3
      //   376: aload_0
      //   377: getfield b : Lcom/qq/e/comm/plugin/w/a/d$a;
      //   380: aload_0
      //   381: getfield c : Lcom/qq/e/comm/plugin/w/a/d$b;
      //   384: aload_0
      //   385: getfield d : Lcom/qq/e/comm/plugin/w/a/d$e;
      //   388: invokestatic a : (Landroid/content/Context;Lcom/qq/e/comm/plugin/w/a/d$a;Lcom/qq/e/comm/plugin/w/a/d$b;Lcom/qq/e/comm/plugin/w/a/d$e;)Z
      //   391: pop
      //   392: goto -> 610
      //   395: bipush #45
      //   397: aload_0
      //   398: getfield c : Lcom/qq/e/comm/plugin/w/a/d$b;
      //   401: getfield b : I
      //   404: if_icmpne -> 422
      //   407: aload_0
      //   408: getfield b : Lcom/qq/e/comm/plugin/w/a/d$a;
      //   411: aload_0
      //   412: getfield c : Lcom/qq/e/comm/plugin/w/a/d$b;
      //   415: invokestatic b : (Lcom/qq/e/comm/plugin/w/a/d$a;Lcom/qq/e/comm/plugin/w/a/d$b;)Z
      //   418: pop
      //   419: goto -> 610
      //   422: aload_0
      //   423: getfield c : Lcom/qq/e/comm/plugin/w/a/d$b;
      //   426: getfield b : I
      //   429: sipush #9001
      //   432: if_icmpne -> 459
      //   435: aload_0
      //   436: getfield a : Ljava/lang/Object;
      //   439: aload_3
      //   440: aload_0
      //   441: getfield b : Lcom/qq/e/comm/plugin/w/a/d$a;
      //   444: aload_0
      //   445: getfield c : Lcom/qq/e/comm/plugin/w/a/d$b;
      //   448: aload_0
      //   449: getfield d : Lcom/qq/e/comm/plugin/w/a/d$e;
      //   452: invokestatic a : (Ljava/lang/Object;Landroid/content/Context;Lcom/qq/e/comm/plugin/w/a/d$a;Lcom/qq/e/comm/plugin/w/a/d$b;Lcom/qq/e/comm/plugin/w/a/d$e;)Z
      //   455: pop
      //   456: goto -> 610
      //   459: aload_0
      //   460: getfield c : Lcom/qq/e/comm/plugin/w/a/d$b;
      //   463: getfield b : I
      //   466: sipush #9000
      //   469: if_icmpne -> 495
      //   472: aload_0
      //   473: getfield a : Ljava/lang/Object;
      //   476: aload_0
      //   477: getfield b : Lcom/qq/e/comm/plugin/w/a/d$a;
      //   480: aload_0
      //   481: getfield c : Lcom/qq/e/comm/plugin/w/a/d$b;
      //   484: aload_0
      //   485: getfield d : Lcom/qq/e/comm/plugin/w/a/d$e;
      //   488: invokestatic a : (Ljava/lang/Object;Lcom/qq/e/comm/plugin/w/a/d$a;Lcom/qq/e/comm/plugin/w/a/d$b;Lcom/qq/e/comm/plugin/w/a/d$e;)Z
      //   491: pop
      //   492: goto -> 610
      //   495: aload_0
      //   496: getfield c : Lcom/qq/e/comm/plugin/w/a/d$b;
      //   499: getfield b : I
      //   502: sipush #9002
      //   505: if_icmpne -> 532
      //   508: aload_0
      //   509: getfield a : Ljava/lang/Object;
      //   512: aload_3
      //   513: aload_0
      //   514: getfield b : Lcom/qq/e/comm/plugin/w/a/d$a;
      //   517: aload_0
      //   518: getfield c : Lcom/qq/e/comm/plugin/w/a/d$b;
      //   521: aload_0
      //   522: getfield d : Lcom/qq/e/comm/plugin/w/a/d$e;
      //   525: invokestatic b : (Ljava/lang/Object;Landroid/content/Context;Lcom/qq/e/comm/plugin/w/a/d$a;Lcom/qq/e/comm/plugin/w/a/d$b;Lcom/qq/e/comm/plugin/w/a/d$e;)Z
      //   528: pop
      //   529: goto -> 610
      //   532: aload_0
      //   533: getfield b : Lcom/qq/e/comm/plugin/w/a/d$a;
      //   536: aload_0
      //   537: getfield c : Lcom/qq/e/comm/plugin/w/a/d$b;
      //   540: invokestatic c : (Lcom/qq/e/comm/plugin/w/a/d$a;Lcom/qq/e/comm/plugin/w/a/d$b;)Z
      //   543: pop
      //   544: goto -> 610
      //   547: aload_0
      //   548: getfield a : Ljava/lang/Object;
      //   551: aload_0
      //   552: getfield b : Lcom/qq/e/comm/plugin/w/a/d$a;
      //   555: aload_0
      //   556: getfield c : Lcom/qq/e/comm/plugin/w/a/d$b;
      //   559: aload_0
      //   560: getfield d : Lcom/qq/e/comm/plugin/w/a/d$e;
      //   563: aconst_null
      //   564: invokestatic a : (Ljava/lang/Object;Lcom/qq/e/comm/plugin/w/a/d$a;Lcom/qq/e/comm/plugin/w/a/d$b;Lcom/qq/e/comm/plugin/w/a/d$e;Lcom/qq/e/comm/plugin/w/a/i$a;)Landroid/util/Pair;
      //   567: getfield second : Ljava/lang/Object;
      //   570: checkcast java/lang/Boolean
      //   573: invokevirtual booleanValue : ()Z
      //   576: ifne -> 610
      //   579: iload_1
      //   580: ifeq -> 610
      //   583: aload_0
      //   584: getfield a : Ljava/lang/Object;
      //   587: astore #4
      //   589: aload_0
      //   590: getfield b : Lcom/qq/e/comm/plugin/w/a/d$a;
      //   593: astore #5
      //   595: aload_0
      //   596: getfield c : Lcom/qq/e/comm/plugin/w/a/d$b;
      //   599: astore #6
      //   601: aload_0
      //   602: getfield d : Lcom/qq/e/comm/plugin/w/a/d$e;
      //   605: astore #7
      //   607: goto -> 347
      //   610: invokestatic a : ()Ljava/util/concurrent/atomic/AtomicInteger;
      //   613: invokevirtual decrementAndGet : ()I
      //   616: pop
      //   617: invokestatic a : ()Ljava/util/Stack;
      //   620: astore_3
      //   621: aload_3
      //   622: ifnull -> 721
      //   625: aload_3
      //   626: invokevirtual isEmpty : ()Z
      //   629: ifne -> 721
      //   632: new com/qq/e/comm/plugin/y/d
      //   635: dup
      //   636: invokespecial <init> : ()V
      //   639: astore #4
      //   641: goto -> 682
      //   644: astore_3
      //   645: ldc 'UnknowExceptinWhileProcessingClick'
      //   647: aload_3
      //   648: invokestatic e : (Ljava/lang/String;Ljava/lang/Throwable;)V
      //   651: invokestatic a : ()Ljava/util/concurrent/atomic/AtomicInteger;
      //   654: invokevirtual decrementAndGet : ()I
      //   657: pop
      //   658: invokestatic a : ()Ljava/util/Stack;
      //   661: astore_3
      //   662: aload_3
      //   663: ifnull -> 721
      //   666: aload_3
      //   667: invokevirtual isEmpty : ()Z
      //   670: ifne -> 721
      //   673: new com/qq/e/comm/plugin/y/d
      //   676: dup
      //   677: invokespecial <init> : ()V
      //   680: astore #4
      //   682: aload #4
      //   684: ldc 'adParam'
      //   686: aload_0
      //   687: getfield b : Lcom/qq/e/comm/plugin/w/a/d$a;
      //   690: invokevirtual toString : ()Ljava/lang/String;
      //   693: invokevirtual a : (Ljava/lang/String;Ljava/lang/Object;)Lcom/qq/e/comm/plugin/y/d;
      //   696: pop
      //   697: aload #4
      //   699: ldc 'stack'
      //   701: aload_3
      //   702: invokevirtual toString : ()Ljava/lang/String;
      //   705: invokevirtual a : (Ljava/lang/String;Ljava/lang/Object;)Lcom/qq/e/comm/plugin/y/d;
      //   708: pop
      //   709: ldc 90012
      //   711: iconst_0
      //   712: aload_0
      //   713: getfield e : Lcom/qq/e/comm/plugin/y/c;
      //   716: aload #4
      //   718: invokestatic a : (IILcom/qq/e/comm/plugin/y/c;Lcom/qq/e/comm/plugin/y/d;)V
      //   721: return
      //   722: astore_3
      //   723: invokestatic a : ()Ljava/util/concurrent/atomic/AtomicInteger;
      //   726: invokevirtual decrementAndGet : ()I
      //   729: pop
      //   730: invokestatic a : ()Ljava/util/Stack;
      //   733: astore #4
      //   735: aload #4
      //   737: ifnull -> 797
      //   740: aload #4
      //   742: invokevirtual isEmpty : ()Z
      //   745: ifne -> 797
      //   748: new com/qq/e/comm/plugin/y/d
      //   751: dup
      //   752: invokespecial <init> : ()V
      //   755: astore #5
      //   757: aload #5
      //   759: ldc 'adParam'
      //   761: aload_0
      //   762: getfield b : Lcom/qq/e/comm/plugin/w/a/d$a;
      //   765: invokevirtual toString : ()Ljava/lang/String;
      //   768: invokevirtual a : (Ljava/lang/String;Ljava/lang/Object;)Lcom/qq/e/comm/plugin/y/d;
      //   771: pop
      //   772: aload #5
      //   774: ldc 'stack'
      //   776: aload #4
      //   778: invokevirtual toString : ()Ljava/lang/String;
      //   781: invokevirtual a : (Ljava/lang/String;Ljava/lang/Object;)Lcom/qq/e/comm/plugin/y/d;
      //   784: pop
      //   785: ldc 90012
      //   787: iconst_0
      //   788: aload_0
      //   789: getfield e : Lcom/qq/e/comm/plugin/y/c;
      //   792: aload #5
      //   794: invokestatic a : (IILcom/qq/e/comm/plugin/y/c;Lcom/qq/e/comm/plugin/y/d;)V
      //   797: aload_3
      //   798: athrow
      //   799: aconst_null
      //   800: astore_3
      //   801: goto -> 181
      //   804: iconst_0
      //   805: istore_1
      //   806: goto -> 218
      // Exception table:
      //   from	to	target	type
      //   0	15	644	finally
      //   19	63	644	finally
      //   63	87	644	finally
      //   90	154	644	finally
      //   154	178	644	finally
      //   181	213	644	finally
      //   222	235	644	finally
      //   238	262	644	finally
      //   265	310	644	finally
      //   313	347	644	finally
      //   347	360	644	finally
      //   363	392	644	finally
      //   395	419	644	finally
      //   422	456	644	finally
      //   459	492	644	finally
      //   495	529	644	finally
      //   532	544	644	finally
      //   547	579	644	finally
      //   583	607	644	finally
      //   645	651	722	finally
    }
  }
  
  public static class e {
    public final String a;
    
    public final com.qq.e.comm.plugin.ad.e b;
    
    public final String c;
    
    public e(String param1String1, com.qq.e.comm.plugin.ad.e param1e, String param1String2) {
      this.a = param1String1;
      this.b = param1e;
      this.c = param1String2;
    }
  }
}


/* Location:              D:\code\BluedHook\classes.dex\com.soft.blued9136188-dex2jar.jar!\com\qq\e\comm\plugin\w\a\d.class
 * Java compiler version: 6 (50.0)
 * JD-Core Version:       1.1.3
 */