package com.alibaba.mtl.appmonitor.a;

import java.util.Map;
import org.json.JSONObject;

public class a extends d {
  public Map<String, String> d;
  
  public Map<String, Integer> e;
  
  public int f = 0;
  
  public int g = 0;
  
  public JSONObject a() {
    // Byte code:
    //   0: aload_0
    //   1: monitorenter
    //   2: aload_0
    //   3: invokespecial a : ()Lorg/json/JSONObject;
    //   6: astore_1
    //   7: aload_1
    //   8: ldc 'successCount'
    //   10: aload_0
    //   11: getfield f : I
    //   14: invokevirtual put : (Ljava/lang/String;I)Lorg/json/JSONObject;
    //   17: pop
    //   18: aload_1
    //   19: ldc 'failCount'
    //   21: aload_0
    //   22: getfield g : I
    //   25: invokevirtual put : (Ljava/lang/String;I)Lorg/json/JSONObject;
    //   28: pop
    //   29: aload_0
    //   30: getfield e : Ljava/util/Map;
    //   33: ifnull -> 192
    //   36: invokestatic a : ()Lcom/alibaba/mtl/appmonitor/c/a;
    //   39: ldc com/alibaba/mtl/appmonitor/c/d
    //   41: iconst_0
    //   42: anewarray java/lang/Object
    //   45: invokevirtual a : (Ljava/lang/Class;[Ljava/lang/Object;)Lcom/alibaba/mtl/appmonitor/c/b;
    //   48: checkcast org/json/JSONArray
    //   51: astore_2
    //   52: aload_0
    //   53: getfield e : Ljava/util/Map;
    //   56: invokeinterface entrySet : ()Ljava/util/Set;
    //   61: invokeinterface iterator : ()Ljava/util/Iterator;
    //   66: astore_3
    //   67: aload_3
    //   68: invokeinterface hasNext : ()Z
    //   73: ifeq -> 184
    //   76: aload_3
    //   77: invokeinterface next : ()Ljava/lang/Object;
    //   82: checkcast java/util/Map$Entry
    //   85: astore #4
    //   87: invokestatic a : ()Lcom/alibaba/mtl/appmonitor/c/a;
    //   90: ldc com/alibaba/mtl/appmonitor/c/e
    //   92: iconst_0
    //   93: anewarray java/lang/Object
    //   96: invokevirtual a : (Ljava/lang/Class;[Ljava/lang/Object;)Lcom/alibaba/mtl/appmonitor/c/b;
    //   99: checkcast org/json/JSONObject
    //   102: astore #5
    //   104: aload #4
    //   106: invokeinterface getKey : ()Ljava/lang/Object;
    //   111: checkcast java/lang/String
    //   114: astore #6
    //   116: aload #5
    //   118: ldc 'errorCode'
    //   120: aload #6
    //   122: invokevirtual put : (Ljava/lang/String;Ljava/lang/Object;)Lorg/json/JSONObject;
    //   125: pop
    //   126: aload #5
    //   128: ldc 'errorCount'
    //   130: aload #4
    //   132: invokeinterface getValue : ()Ljava/lang/Object;
    //   137: invokevirtual put : (Ljava/lang/String;Ljava/lang/Object;)Lorg/json/JSONObject;
    //   140: pop
    //   141: aload_0
    //   142: getfield d : Ljava/util/Map;
    //   145: aload #6
    //   147: invokeinterface containsKey : (Ljava/lang/Object;)Z
    //   152: ifeq -> 174
    //   155: aload #5
    //   157: ldc 'errorMsg'
    //   159: aload_0
    //   160: getfield d : Ljava/util/Map;
    //   163: aload #6
    //   165: invokeinterface get : (Ljava/lang/Object;)Ljava/lang/Object;
    //   170: invokevirtual put : (Ljava/lang/String;Ljava/lang/Object;)Lorg/json/JSONObject;
    //   173: pop
    //   174: aload_2
    //   175: aload #5
    //   177: invokevirtual put : (Ljava/lang/Object;)Lorg/json/JSONArray;
    //   180: pop
    //   181: goto -> 67
    //   184: aload_1
    //   185: ldc 'errors'
    //   187: aload_2
    //   188: invokevirtual put : (Ljava/lang/String;Ljava/lang/Object;)Lorg/json/JSONObject;
    //   191: pop
    //   192: aload_0
    //   193: monitorexit
    //   194: aload_1
    //   195: areturn
    //   196: astore_1
    //   197: aload_0
    //   198: monitorexit
    //   199: aload_1
    //   200: athrow
    //   201: astore_2
    //   202: goto -> 192
    // Exception table:
    //   from	to	target	type
    //   2	7	196	finally
    //   7	67	201	java/lang/Exception
    //   7	67	196	finally
    //   67	174	201	java/lang/Exception
    //   67	174	196	finally
    //   174	181	201	java/lang/Exception
    //   174	181	196	finally
    //   184	192	201	java/lang/Exception
    //   184	192	196	finally
  }
  
  public void a(String paramString1, String paramString2) {
    // Byte code:
    //   0: aload_0
    //   1: monitorenter
    //   2: aload_1
    //   3: invokestatic isBlank : (Ljava/lang/String;)Z
    //   6: istore #5
    //   8: iload #5
    //   10: ifeq -> 16
    //   13: aload_0
    //   14: monitorexit
    //   15: return
    //   16: aload_0
    //   17: getfield d : Ljava/util/Map;
    //   20: ifnonnull -> 34
    //   23: aload_0
    //   24: new java/util/HashMap
    //   27: dup
    //   28: invokespecial <init> : ()V
    //   31: putfield d : Ljava/util/Map;
    //   34: aload_0
    //   35: getfield e : Ljava/util/Map;
    //   38: ifnonnull -> 52
    //   41: aload_0
    //   42: new java/util/HashMap
    //   45: dup
    //   46: invokespecial <init> : ()V
    //   49: putfield e : Ljava/util/Map;
    //   52: aload_2
    //   53: invokestatic c : (Ljava/lang/String;)Z
    //   56: ifeq -> 102
    //   59: aload_2
    //   60: invokevirtual length : ()I
    //   63: istore #4
    //   65: bipush #100
    //   67: istore_3
    //   68: iload #4
    //   70: bipush #100
    //   72: if_icmple -> 78
    //   75: goto -> 83
    //   78: aload_2
    //   79: invokevirtual length : ()I
    //   82: istore_3
    //   83: aload_2
    //   84: iconst_0
    //   85: iload_3
    //   86: invokevirtual substring : (II)Ljava/lang/String;
    //   89: astore_2
    //   90: aload_0
    //   91: getfield d : Ljava/util/Map;
    //   94: aload_1
    //   95: aload_2
    //   96: invokeinterface put : (Ljava/lang/Object;Ljava/lang/Object;)Ljava/lang/Object;
    //   101: pop
    //   102: aload_0
    //   103: getfield e : Ljava/util/Map;
    //   106: aload_1
    //   107: invokeinterface containsKey : (Ljava/lang/Object;)Z
    //   112: ifne -> 133
    //   115: aload_0
    //   116: getfield e : Ljava/util/Map;
    //   119: aload_1
    //   120: iconst_1
    //   121: invokestatic valueOf : (I)Ljava/lang/Integer;
    //   124: invokeinterface put : (Ljava/lang/Object;Ljava/lang/Object;)Ljava/lang/Object;
    //   129: pop
    //   130: goto -> 165
    //   133: aload_0
    //   134: getfield e : Ljava/util/Map;
    //   137: aload_1
    //   138: aload_0
    //   139: getfield e : Ljava/util/Map;
    //   142: aload_1
    //   143: invokeinterface get : (Ljava/lang/Object;)Ljava/lang/Object;
    //   148: checkcast java/lang/Integer
    //   151: invokevirtual intValue : ()I
    //   154: iconst_1
    //   155: iadd
    //   156: invokestatic valueOf : (I)Ljava/lang/Integer;
    //   159: invokeinterface put : (Ljava/lang/Object;Ljava/lang/Object;)Ljava/lang/Object;
    //   164: pop
    //   165: aload_0
    //   166: monitorexit
    //   167: return
    //   168: astore_1
    //   169: aload_0
    //   170: monitorexit
    //   171: aload_1
    //   172: athrow
    // Exception table:
    //   from	to	target	type
    //   2	8	168	finally
    //   16	34	168	finally
    //   34	52	168	finally
    //   52	65	168	finally
    //   78	83	168	finally
    //   83	102	168	finally
    //   102	130	168	finally
    //   133	165	168	finally
  }
  
  public void clean() {
    // Byte code:
    //   0: aload_0
    //   1: monitorenter
    //   2: aload_0
    //   3: invokespecial clean : ()V
    //   6: aload_0
    //   7: iconst_0
    //   8: putfield f : I
    //   11: aload_0
    //   12: iconst_0
    //   13: putfield g : I
    //   16: aload_0
    //   17: getfield d : Ljava/util/Map;
    //   20: ifnull -> 32
    //   23: aload_0
    //   24: getfield d : Ljava/util/Map;
    //   27: invokeinterface clear : ()V
    //   32: aload_0
    //   33: getfield e : Ljava/util/Map;
    //   36: ifnull -> 48
    //   39: aload_0
    //   40: getfield e : Ljava/util/Map;
    //   43: invokeinterface clear : ()V
    //   48: aload_0
    //   49: monitorexit
    //   50: return
    //   51: astore_1
    //   52: aload_0
    //   53: monitorexit
    //   54: aload_1
    //   55: athrow
    // Exception table:
    //   from	to	target	type
    //   2	32	51	finally
    //   32	48	51	finally
  }
  
  public void f() {
    // Byte code:
    //   0: aload_0
    //   1: monitorenter
    //   2: aload_0
    //   3: aload_0
    //   4: getfield f : I
    //   7: iconst_1
    //   8: iadd
    //   9: putfield f : I
    //   12: aload_0
    //   13: monitorexit
    //   14: return
    //   15: astore_1
    //   16: aload_0
    //   17: monitorexit
    //   18: aload_1
    //   19: athrow
    // Exception table:
    //   from	to	target	type
    //   2	12	15	finally
  }
  
  public void g() {
    // Byte code:
    //   0: aload_0
    //   1: monitorenter
    //   2: aload_0
    //   3: aload_0
    //   4: getfield g : I
    //   7: iconst_1
    //   8: iadd
    //   9: putfield g : I
    //   12: aload_0
    //   13: monitorexit
    //   14: return
    //   15: astore_1
    //   16: aload_0
    //   17: monitorexit
    //   18: aload_1
    //   19: athrow
    // Exception table:
    //   from	to	target	type
    //   2	12	15	finally
  }
}


/* Location:              D:\code\BluedHook\classes.dex\com.soft.blued7646532-dex2jar.jar!\com\alibaba\mtl\appmonitor\a\a.class
 * Java compiler version: 6 (50.0)
 * JD-Core Version:       1.1.3
 */