package c.t.maploc.lite.tsa;

import android.content.Context;
import android.telephony.TelephonyManager;

public final class o {
  public static int a;
  
  public final s b;
  
  private final m c;
  
  private final n d;
  
  public o(s params, m paramm, n paramn) {
    this.b = params;
    this.c = paramm;
    this.d = paramn;
  }
  
  private static int a(Context paramContext) {
    // Byte code:
    //   0: aload_0
    //   1: ifnonnull -> 6
    //   4: iconst_m1
    //   5: ireturn
    //   6: aload_0
    //   7: invokestatic b : (Landroid/content/Context;)Z
    //   10: istore #10
    //   12: aload_0
    //   13: ldc 'wifi'
    //   15: invokevirtual getSystemService : (Ljava/lang/String;)Ljava/lang/Object;
    //   18: checkcast android/net/wifi/WifiManager
    //   21: astore #11
    //   23: aload #11
    //   25: ifnull -> 72
    //   28: aload #11
    //   30: invokevirtual isWifiEnabled : ()Z
    //   33: istore #7
    //   35: getstatic android/os/Build$VERSION.SDK_INT : I
    //   38: bipush #18
    //   40: if_icmplt -> 67
    //   43: aload #11
    //   45: invokevirtual isScanAlwaysAvailable : ()Z
    //   48: istore #8
    //   50: iload #8
    //   52: ifeq -> 67
    //   55: iconst_1
    //   56: istore #5
    //   58: iconst_1
    //   59: istore_2
    //   60: iload #7
    //   62: istore #8
    //   64: goto -> 94
    //   67: iconst_1
    //   68: istore_1
    //   69: goto -> 85
    //   72: iconst_0
    //   73: istore_1
    //   74: iconst_0
    //   75: istore #7
    //   77: goto -> 85
    //   80: iconst_0
    //   81: istore #7
    //   83: iconst_0
    //   84: istore_1
    //   85: iconst_0
    //   86: istore_2
    //   87: iload #7
    //   89: istore #8
    //   91: iload_1
    //   92: istore #5
    //   94: aload_0
    //   95: ldc 'location'
    //   97: invokevirtual getSystemService : (Ljava/lang/String;)Ljava/lang/Object;
    //   100: checkcast android/location/LocationManager
    //   103: astore #11
    //   105: aload #11
    //   107: ifnull -> 167
    //   110: aload_0
    //   111: invokevirtual getContentResolver : ()Landroid/content/ContentResolver;
    //   114: ldc 'location_mode'
    //   116: invokestatic getInt : (Landroid/content/ContentResolver;Ljava/lang/String;)I
    //   119: istore_1
    //   120: goto -> 125
    //   123: iconst_0
    //   124: istore_1
    //   125: aload #11
    //   127: ldc 'gps'
    //   129: invokevirtual isProviderEnabled : (Ljava/lang/String;)Z
    //   132: istore #9
    //   134: aload #11
    //   136: invokevirtual getAllProviders : ()Ljava/util/List;
    //   139: astore_0
    //   140: aload_0
    //   141: ifnonnull -> 152
    //   144: iconst_0
    //   145: istore #7
    //   147: iload_1
    //   148: istore_3
    //   149: goto -> 177
    //   152: aload_0
    //   153: ldc 'gps'
    //   155: invokeinterface contains : (Ljava/lang/Object;)Z
    //   160: istore #7
    //   162: iload_1
    //   163: istore_3
    //   164: goto -> 177
    //   167: iconst_0
    //   168: istore_1
    //   169: iconst_0
    //   170: istore #7
    //   172: iconst_0
    //   173: istore #9
    //   175: iload_1
    //   176: istore_3
    //   177: iload #8
    //   179: ifne -> 187
    //   182: iconst_2
    //   183: istore_1
    //   184: goto -> 189
    //   187: iconst_0
    //   188: istore_1
    //   189: iload #9
    //   191: ifne -> 200
    //   194: iconst_4
    //   195: istore #4
    //   197: goto -> 203
    //   200: iconst_0
    //   201: istore #4
    //   203: iload #5
    //   205: ifne -> 215
    //   208: bipush #8
    //   210: istore #5
    //   212: goto -> 218
    //   215: iconst_0
    //   216: istore #5
    //   218: iload #7
    //   220: ifne -> 230
    //   223: bipush #16
    //   225: istore #6
    //   227: goto -> 233
    //   230: iconst_0
    //   231: istore #6
    //   233: iload_2
    //   234: ifne -> 243
    //   237: bipush #32
    //   239: istore_2
    //   240: goto -> 245
    //   243: iconst_0
    //   244: istore_2
    //   245: iload_3
    //   246: iflt -> 264
    //   249: iload_3
    //   250: iconst_3
    //   251: if_icmpgt -> 264
    //   254: iconst_1
    //   255: iload_3
    //   256: bipush #6
    //   258: iadd
    //   259: ishl
    //   260: istore_3
    //   261: goto -> 266
    //   264: iconst_0
    //   265: istore_3
    //   266: iload_3
    //   267: iload_2
    //   268: iload #10
    //   270: iconst_1
    //   271: ixor
    //   272: iconst_0
    //   273: iadd
    //   274: iload_1
    //   275: iadd
    //   276: iload #4
    //   278: iadd
    //   279: iload #5
    //   281: iadd
    //   282: iload #6
    //   284: iadd
    //   285: iadd
    //   286: iadd
    //   287: ireturn
    //   288: astore #11
    //   290: goto -> 80
    //   293: astore #11
    //   295: goto -> 83
    //   298: astore_0
    //   299: goto -> 167
    //   302: astore_0
    //   303: goto -> 123
    //   306: astore_0
    //   307: goto -> 169
    // Exception table:
    //   from	to	target	type
    //   12	23	288	finally
    //   28	35	288	finally
    //   35	50	293	finally
    //   94	105	298	finally
    //   110	120	302	finally
    //   125	140	306	finally
    //   152	162	306	finally
  }
  
  private static boolean b(Context paramContext) {
    boolean bool = false;
    try {
      TelephonyManager telephonyManager = (TelephonyManager)paramContext.getSystemService("phone");
      if (telephonyManager == null)
        return false; 
      int i = telephonyManager.getSimState();
      if (i == 5)
        bool = true; 
      return bool;
    } catch (Exception exception) {
      return false;
    } 
  }
  
  public final String a(j paramj, boolean paramBoolean) {
    // Byte code:
    //   0: aload_1
    //   1: ifnonnull -> 7
    //   4: ldc ''
    //   6: areturn
    //   7: aload_0
    //   8: getfield c : Lc/t/maploc/lite/tsa/m;
    //   11: astore #6
    //   13: iconst_0
    //   14: istore #4
    //   16: aload #6
    //   18: ifnonnull -> 24
    //   21: goto -> 1242
    //   24: getstatic c/t/maploc/lite/tsa/o.a : I
    //   27: aload_0
    //   28: getfield c : Lc/t/maploc/lite/tsa/m;
    //   31: getfield e : I
    //   34: if_icmpeq -> 1248
    //   37: goto -> 1242
    //   40: aload_0
    //   41: getfield c : Lc/t/maploc/lite/tsa/m;
    //   44: ifnonnull -> 54
    //   47: getstatic c/t/maploc/lite/tsa/o.a : I
    //   50: istore_3
    //   51: goto -> 62
    //   54: aload_0
    //   55: getfield c : Lc/t/maploc/lite/tsa/m;
    //   58: getfield e : I
    //   61: istore_3
    //   62: iload_3
    //   63: putstatic c/t/maploc/lite/tsa/o.a : I
    //   66: aload_0
    //   67: getfield b : Lc/t/maploc/lite/tsa/s;
    //   70: astore #6
    //   72: aload #6
    //   74: ifnonnull -> 84
    //   77: ldc '[]'
    //   79: astore #6
    //   81: goto -> 234
    //   84: aload_0
    //   85: getfield b : Lc/t/maploc/lite/tsa/s;
    //   88: astore #7
    //   90: aload #7
    //   92: getfield b : Ljava/util/List;
    //   95: invokeinterface size : ()I
    //   100: ifgt -> 106
    //   103: goto -> 77
    //   106: new java/lang/StringBuilder
    //   109: dup
    //   110: ldc '['
    //   112: invokespecial <init> : (Ljava/lang/String;)V
    //   115: astore #6
    //   117: aload #7
    //   119: getfield b : Ljava/util/List;
    //   122: invokeinterface iterator : ()Ljava/util/Iterator;
    //   127: astore #7
    //   129: iload #4
    //   131: istore_3
    //   132: aload #7
    //   134: invokeinterface hasNext : ()Z
    //   139: ifeq -> 219
    //   142: aload #7
    //   144: invokeinterface next : ()Ljava/lang/Object;
    //   149: checkcast android/net/wifi/ScanResult
    //   152: astore #8
    //   154: iload_3
    //   155: ifle -> 166
    //   158: aload #6
    //   160: ldc ','
    //   162: invokevirtual append : (Ljava/lang/String;)Ljava/lang/StringBuilder;
    //   165: pop
    //   166: aload #6
    //   168: ldc '{"mac":"'
    //   170: invokevirtual append : (Ljava/lang/String;)Ljava/lang/StringBuilder;
    //   173: pop
    //   174: aload #6
    //   176: aload #8
    //   178: getfield BSSID : Ljava/lang/String;
    //   181: invokevirtual append : (Ljava/lang/String;)Ljava/lang/StringBuilder;
    //   184: pop
    //   185: aload #6
    //   187: ldc '","rssi":'
    //   189: invokevirtual append : (Ljava/lang/String;)Ljava/lang/StringBuilder;
    //   192: pop
    //   193: aload #6
    //   195: aload #8
    //   197: getfield level : I
    //   200: invokevirtual append : (I)Ljava/lang/StringBuilder;
    //   203: pop
    //   204: aload #6
    //   206: ldc '}'
    //   208: invokevirtual append : (Ljava/lang/String;)Ljava/lang/StringBuilder;
    //   211: pop
    //   212: iload_3
    //   213: iconst_1
    //   214: iadd
    //   215: istore_3
    //   216: goto -> 132
    //   219: aload #6
    //   221: ldc ']'
    //   223: invokevirtual append : (Ljava/lang/String;)Ljava/lang/StringBuilder;
    //   226: pop
    //   227: aload #6
    //   229: invokevirtual toString : ()Ljava/lang/String;
    //   232: astore #6
    //   234: aload_0
    //   235: getfield c : Lc/t/maploc/lite/tsa/m;
    //   238: ifnonnull -> 248
    //   241: ldc '[]'
    //   243: astore #7
    //   245: goto -> 259
    //   248: aload_0
    //   249: getfield c : Lc/t/maploc/lite/tsa/m;
    //   252: iload #5
    //   254: invokevirtual a : (Z)Ljava/lang/String;
    //   257: astore #7
    //   259: aload_0
    //   260: getfield d : Lc/t/maploc/lite/tsa/n;
    //   263: astore #9
    //   265: ldc '{}'
    //   267: astore #8
    //   269: aload #9
    //   271: ifnonnull -> 277
    //   274: goto -> 538
    //   277: aload_0
    //   278: getfield d : Lc/t/maploc/lite/tsa/n;
    //   281: astore #8
    //   283: aload #8
    //   285: getfield b : Landroid/location/Location;
    //   288: astore #15
    //   290: new java/lang/StringBuilder
    //   293: dup
    //   294: invokespecial <init> : ()V
    //   297: astore #9
    //   299: aload #15
    //   301: invokevirtual getLatitude : ()D
    //   304: bipush #6
    //   306: invokestatic a : (DI)Ljava/lang/String;
    //   309: astore #13
    //   311: aload #15
    //   313: invokevirtual getLongitude : ()D
    //   316: bipush #6
    //   318: invokestatic a : (DI)Ljava/lang/String;
    //   321: astore #14
    //   323: aload #15
    //   325: invokevirtual getAltitude : ()D
    //   328: iconst_1
    //   329: invokestatic a : (DI)Ljava/lang/String;
    //   332: astore #10
    //   334: aload #15
    //   336: invokevirtual getAccuracy : ()F
    //   339: f2d
    //   340: iconst_1
    //   341: invokestatic a : (DI)Ljava/lang/String;
    //   344: astore #11
    //   346: aload #15
    //   348: invokevirtual getBearing : ()F
    //   351: f2d
    //   352: iconst_1
    //   353: invokestatic a : (DI)Ljava/lang/String;
    //   356: astore #12
    //   358: aload #15
    //   360: invokevirtual getSpeed : ()F
    //   363: f2d
    //   364: iconst_1
    //   365: invokestatic a : (DI)Ljava/lang/String;
    //   368: astore #15
    //   370: aload #9
    //   372: ldc '{'
    //   374: invokevirtual append : (Ljava/lang/String;)Ljava/lang/StringBuilder;
    //   377: pop
    //   378: aload #9
    //   380: ldc '"latitude":'
    //   382: invokevirtual append : (Ljava/lang/String;)Ljava/lang/StringBuilder;
    //   385: pop
    //   386: aload #9
    //   388: aload #13
    //   390: invokevirtual append : (Ljava/lang/String;)Ljava/lang/StringBuilder;
    //   393: pop
    //   394: aload #9
    //   396: ldc ',"longitude":'
    //   398: invokevirtual append : (Ljava/lang/String;)Ljava/lang/StringBuilder;
    //   401: pop
    //   402: aload #9
    //   404: aload #14
    //   406: invokevirtual append : (Ljava/lang/String;)Ljava/lang/StringBuilder;
    //   409: pop
    //   410: aload #9
    //   412: ldc ',"additional":'
    //   414: invokevirtual append : (Ljava/lang/String;)Ljava/lang/StringBuilder;
    //   417: pop
    //   418: new java/lang/StringBuilder
    //   421: dup
    //   422: ldc '"'
    //   424: invokespecial <init> : (Ljava/lang/String;)V
    //   427: astore #13
    //   429: aload #13
    //   431: aload #10
    //   433: invokevirtual append : (Ljava/lang/String;)Ljava/lang/StringBuilder;
    //   436: pop
    //   437: aload #13
    //   439: ldc ','
    //   441: invokevirtual append : (Ljava/lang/String;)Ljava/lang/StringBuilder;
    //   444: pop
    //   445: aload #13
    //   447: aload #11
    //   449: invokevirtual append : (Ljava/lang/String;)Ljava/lang/StringBuilder;
    //   452: pop
    //   453: aload #13
    //   455: ldc ','
    //   457: invokevirtual append : (Ljava/lang/String;)Ljava/lang/StringBuilder;
    //   460: pop
    //   461: aload #13
    //   463: aload #12
    //   465: invokevirtual append : (Ljava/lang/String;)Ljava/lang/StringBuilder;
    //   468: pop
    //   469: aload #13
    //   471: ldc ','
    //   473: invokevirtual append : (Ljava/lang/String;)Ljava/lang/StringBuilder;
    //   476: pop
    //   477: aload #13
    //   479: aload #15
    //   481: invokevirtual append : (Ljava/lang/String;)Ljava/lang/StringBuilder;
    //   484: pop
    //   485: aload #13
    //   487: ldc ','
    //   489: invokevirtual append : (Ljava/lang/String;)Ljava/lang/StringBuilder;
    //   492: pop
    //   493: aload #13
    //   495: aload #8
    //   497: getfield c : J
    //   500: invokevirtual append : (J)Ljava/lang/StringBuilder;
    //   503: pop
    //   504: aload #13
    //   506: ldc '"'
    //   508: invokevirtual append : (Ljava/lang/String;)Ljava/lang/StringBuilder;
    //   511: pop
    //   512: aload #9
    //   514: aload #13
    //   516: invokevirtual toString : ()Ljava/lang/String;
    //   519: invokevirtual append : (Ljava/lang/String;)Ljava/lang/StringBuilder;
    //   522: pop
    //   523: aload #9
    //   525: ldc '}'
    //   527: invokevirtual append : (Ljava/lang/String;)Ljava/lang/StringBuilder;
    //   530: pop
    //   531: aload #9
    //   533: invokevirtual toString : ()Ljava/lang/String;
    //   536: astore #8
    //   538: aload_1
    //   539: getfield b : Lc/t/maploc/lite/tsa/k;
    //   542: astore #13
    //   544: new java/util/HashMap
    //   547: dup
    //   548: invokespecial <init> : ()V
    //   551: astore #9
    //   553: aload #9
    //   555: ldc 'imei'
    //   557: aload #13
    //   559: invokevirtual g : ()Ljava/lang/String;
    //   562: invokevirtual put : (Ljava/lang/Object;Ljava/lang/Object;)Ljava/lang/Object;
    //   565: pop
    //   566: aload #9
    //   568: ldc 'imsi'
    //   570: aload #13
    //   572: invokevirtual h : ()Ljava/lang/String;
    //   575: invokevirtual put : (Ljava/lang/Object;Ljava/lang/Object;)Ljava/lang/Object;
    //   578: pop
    //   579: aload #9
    //   581: ldc 'phonenum'
    //   583: ldc ''
    //   585: invokevirtual put : (Ljava/lang/Object;Ljava/lang/Object;)Ljava/lang/Object;
    //   588: pop
    //   589: aload #9
    //   591: ldc 'qq'
    //   593: ldc ''
    //   595: invokevirtual put : (Ljava/lang/Object;Ljava/lang/Object;)Ljava/lang/Object;
    //   598: pop
    //   599: aload #9
    //   601: ldc 'mac'
    //   603: aload #13
    //   605: invokevirtual f : ()Ljava/lang/String;
    //   608: getstatic java/util/Locale.ENGLISH : Ljava/util/Locale;
    //   611: invokevirtual toLowerCase : (Ljava/util/Locale;)Ljava/lang/String;
    //   614: invokevirtual put : (Ljava/lang/Object;Ljava/lang/Object;)Ljava/lang/Object;
    //   617: pop
    //   618: new org/json/JSONObject
    //   621: dup
    //   622: aload #9
    //   624: invokespecial <init> : (Ljava/util/Map;)V
    //   627: invokevirtual toString : ()Ljava/lang/String;
    //   630: astore #10
    //   632: aload #13
    //   634: invokevirtual i : ()Ljava/lang/String;
    //   637: astore #12
    //   639: aload_1
    //   640: getfield a : Landroid/content/Context;
    //   643: invokestatic a : (Landroid/content/Context;)I
    //   646: istore_3
    //   647: aload_1
    //   648: getfield a : Landroid/content/Context;
    //   651: invokestatic a : (Landroid/content/Context;)Ljava/lang/String;
    //   654: astore #11
    //   656: aload #6
    //   658: astore_1
    //   659: aload #6
    //   661: ldc '[]'
    //   663: invokevirtual equals : (Ljava/lang/Object;)Z
    //   666: ifeq -> 735
    //   669: aload #6
    //   671: astore_1
    //   672: aload #11
    //   674: ldc '{}'
    //   676: invokevirtual equals : (Ljava/lang/Object;)Z
    //   679: ifne -> 735
    //   682: new org/json/JSONObject
    //   685: dup
    //   686: aload #11
    //   688: invokespecial <init> : (Ljava/lang/String;)V
    //   691: astore_1
    //   692: aload_1
    //   693: ldc_w 'ssid'
    //   696: invokevirtual remove : (Ljava/lang/String;)Ljava/lang/Object;
    //   699: pop
    //   700: new java/lang/StringBuilder
    //   703: dup
    //   704: ldc '['
    //   706: invokespecial <init> : (Ljava/lang/String;)V
    //   709: astore #9
    //   711: aload #9
    //   713: aload_1
    //   714: invokevirtual toString : ()Ljava/lang/String;
    //   717: invokevirtual append : (Ljava/lang/String;)Ljava/lang/StringBuilder;
    //   720: pop
    //   721: aload #9
    //   723: ldc ']'
    //   725: invokevirtual append : (Ljava/lang/String;)Ljava/lang/StringBuilder;
    //   728: pop
    //   729: aload #9
    //   731: invokevirtual toString : ()Ljava/lang/String;
    //   734: astore_1
    //   735: aload #13
    //   737: getfield c : Ljava/lang/String;
    //   740: astore #9
    //   742: aload #9
    //   744: astore #6
    //   746: aload #9
    //   748: ifnull -> 763
    //   751: aload #9
    //   753: ldc_w '["|_]'
    //   756: ldc ''
    //   758: invokevirtual replaceAll : (Ljava/lang/String;Ljava/lang/String;)Ljava/lang/String;
    //   761: astore #6
    //   763: new java/lang/StringBuilder
    //   766: dup
    //   767: invokespecial <init> : ()V
    //   770: astore #9
    //   772: aload #9
    //   774: aload #6
    //   776: invokevirtual append : (Ljava/lang/String;)Ljava/lang/StringBuilder;
    //   779: pop
    //   780: aload #9
    //   782: ldc_w '_'
    //   785: invokevirtual append : (Ljava/lang/String;)Ljava/lang/StringBuilder;
    //   788: pop
    //   789: aload #9
    //   791: aload #13
    //   793: getfield a : Ljava/lang/String;
    //   796: invokevirtual append : (Ljava/lang/String;)Ljava/lang/StringBuilder;
    //   799: pop
    //   800: aload #9
    //   802: invokevirtual toString : ()Ljava/lang/String;
    //   805: astore #6
    //   807: new java/lang/StringBuilder
    //   810: dup
    //   811: ldc_w '{"version":"'
    //   814: invokespecial <init> : (Ljava/lang/String;)V
    //   817: astore #9
    //   819: aload #9
    //   821: invokestatic a : ()Ljava/lang/String;
    //   824: invokevirtual append : (Ljava/lang/String;)Ljava/lang/StringBuilder;
    //   827: pop
    //   828: aload #9
    //   830: ldc_w '","address":0'
    //   833: invokevirtual append : (Ljava/lang/String;)Ljava/lang/StringBuilder;
    //   836: pop
    //   837: aload #9
    //   839: invokevirtual toString : ()Ljava/lang/String;
    //   842: astore #9
    //   844: new java/lang/StringBuilder
    //   847: dup
    //   848: invokespecial <init> : ()V
    //   851: astore #13
    //   853: aload #13
    //   855: aload #9
    //   857: invokevirtual append : (Ljava/lang/String;)Ljava/lang/StringBuilder;
    //   860: pop
    //   861: aload #13
    //   863: ldc_w ',"source":203,"access_token":"'
    //   866: invokevirtual append : (Ljava/lang/String;)Ljava/lang/StringBuilder;
    //   869: pop
    //   870: aload #13
    //   872: aload #12
    //   874: invokevirtual append : (Ljava/lang/String;)Ljava/lang/StringBuilder;
    //   877: pop
    //   878: aload #13
    //   880: ldc_w '","app_name":"'
    //   883: invokevirtual append : (Ljava/lang/String;)Ljava/lang/StringBuilder;
    //   886: pop
    //   887: aload #13
    //   889: invokestatic c : ()Ljava/lang/String;
    //   892: invokevirtual append : (Ljava/lang/String;)Ljava/lang/StringBuilder;
    //   895: pop
    //   896: aload #13
    //   898: ldc_w '","app_label":"'
    //   901: invokevirtual append : (Ljava/lang/String;)Ljava/lang/StringBuilder;
    //   904: pop
    //   905: aload #13
    //   907: aload #6
    //   909: invokevirtual append : (Ljava/lang/String;)Ljava/lang/StringBuilder;
    //   912: pop
    //   913: aload #13
    //   915: ldc_w '","bearing":1'
    //   918: invokevirtual append : (Ljava/lang/String;)Ljava/lang/StringBuilder;
    //   921: pop
    //   922: aload #13
    //   924: invokevirtual toString : ()Ljava/lang/String;
    //   927: astore #6
    //   929: new java/lang/StringBuilder
    //   932: dup
    //   933: invokespecial <init> : ()V
    //   936: astore #9
    //   938: aload #9
    //   940: aload #6
    //   942: invokevirtual append : (Ljava/lang/String;)Ljava/lang/StringBuilder;
    //   945: pop
    //   946: aload #9
    //   948: ldc_w ',"control":0'
    //   951: invokevirtual append : (Ljava/lang/String;)Ljava/lang/StringBuilder;
    //   954: pop
    //   955: aload #9
    //   957: invokevirtual toString : ()Ljava/lang/String;
    //   960: astore #6
    //   962: iload_2
    //   963: ifeq -> 1006
    //   966: new java/lang/StringBuilder
    //   969: dup
    //   970: invokespecial <init> : ()V
    //   973: astore #9
    //   975: aload #9
    //   977: aload #6
    //   979: invokevirtual append : (Ljava/lang/String;)Ljava/lang/StringBuilder;
    //   982: pop
    //   983: ldc_w ',"detectgps":1'
    //   986: astore #6
    //   988: aload #9
    //   990: aload #6
    //   992: invokevirtual append : (Ljava/lang/String;)Ljava/lang/StringBuilder;
    //   995: pop
    //   996: aload #9
    //   998: invokevirtual toString : ()Ljava/lang/String;
    //   1001: astore #6
    //   1003: goto -> 1031
    //   1006: new java/lang/StringBuilder
    //   1009: dup
    //   1010: invokespecial <init> : ()V
    //   1013: astore #9
    //   1015: aload #9
    //   1017: aload #6
    //   1019: invokevirtual append : (Ljava/lang/String;)Ljava/lang/StringBuilder;
    //   1022: pop
    //   1023: ldc_w ',"detectgps":0'
    //   1026: astore #6
    //   1028: goto -> 988
    //   1031: new java/lang/StringBuilder
    //   1034: dup
    //   1035: invokespecial <init> : ()V
    //   1038: astore #9
    //   1040: aload #9
    //   1042: aload #6
    //   1044: invokevirtual append : (Ljava/lang/String;)Ljava/lang/StringBuilder;
    //   1047: pop
    //   1048: aload #9
    //   1050: ldc_w ',"pstat":'
    //   1053: invokevirtual append : (Ljava/lang/String;)Ljava/lang/StringBuilder;
    //   1056: pop
    //   1057: aload #9
    //   1059: iload_3
    //   1060: invokevirtual append : (I)Ljava/lang/StringBuilder;
    //   1063: pop
    //   1064: aload #9
    //   1066: invokevirtual toString : ()Ljava/lang/String;
    //   1069: astore #6
    //   1071: new java/lang/StringBuilder
    //   1074: dup
    //   1075: invokespecial <init> : ()V
    //   1078: astore #9
    //   1080: aload #9
    //   1082: aload #6
    //   1084: invokevirtual append : (Ljava/lang/String;)Ljava/lang/StringBuilder;
    //   1087: pop
    //   1088: aload #9
    //   1090: ldc_w ',"wlan":'
    //   1093: invokevirtual append : (Ljava/lang/String;)Ljava/lang/StringBuilder;
    //   1096: pop
    //   1097: aload #9
    //   1099: aload #11
    //   1101: invokevirtual append : (Ljava/lang/String;)Ljava/lang/StringBuilder;
    //   1104: pop
    //   1105: aload #9
    //   1107: invokevirtual toString : ()Ljava/lang/String;
    //   1110: astore #6
    //   1112: new java/lang/StringBuilder
    //   1115: dup
    //   1116: invokespecial <init> : ()V
    //   1119: astore #9
    //   1121: aload #9
    //   1123: aload #6
    //   1125: invokevirtual append : (Ljava/lang/String;)Ljava/lang/StringBuilder;
    //   1128: pop
    //   1129: aload #9
    //   1131: ldc_w ',"attribute":'
    //   1134: invokevirtual append : (Ljava/lang/String;)Ljava/lang/StringBuilder;
    //   1137: pop
    //   1138: aload #9
    //   1140: aload #10
    //   1142: invokevirtual append : (Ljava/lang/String;)Ljava/lang/StringBuilder;
    //   1145: pop
    //   1146: aload #9
    //   1148: ldc_w ',"location":'
    //   1151: invokevirtual append : (Ljava/lang/String;)Ljava/lang/StringBuilder;
    //   1154: pop
    //   1155: aload #9
    //   1157: aload #8
    //   1159: invokevirtual append : (Ljava/lang/String;)Ljava/lang/StringBuilder;
    //   1162: pop
    //   1163: aload #9
    //   1165: ldc_w ',"cells":'
    //   1168: invokevirtual append : (Ljava/lang/String;)Ljava/lang/StringBuilder;
    //   1171: pop
    //   1172: aload #9
    //   1174: aload #7
    //   1176: invokevirtual append : (Ljava/lang/String;)Ljava/lang/StringBuilder;
    //   1179: pop
    //   1180: aload #9
    //   1182: ldc_w ',"wifis":'
    //   1185: invokevirtual append : (Ljava/lang/String;)Ljava/lang/StringBuilder;
    //   1188: pop
    //   1189: aload #9
    //   1191: aload_1
    //   1192: invokevirtual append : (Ljava/lang/String;)Ljava/lang/StringBuilder;
    //   1195: pop
    //   1196: aload #9
    //   1198: ldc_w ',"bles":'
    //   1201: invokevirtual append : (Ljava/lang/String;)Ljava/lang/StringBuilder;
    //   1204: pop
    //   1205: aload #9
    //   1207: ldc '[]'
    //   1209: invokevirtual append : (Ljava/lang/String;)Ljava/lang/StringBuilder;
    //   1212: pop
    //   1213: aload #9
    //   1215: ldc '}'
    //   1217: invokevirtual append : (Ljava/lang/String;)Ljava/lang/StringBuilder;
    //   1220: pop
    //   1221: aload #9
    //   1223: invokevirtual toString : ()Ljava/lang/String;
    //   1226: astore_1
    //   1227: aload_1
    //   1228: areturn
    //   1229: aconst_null
    //   1230: areturn
    //   1231: astore_1
    //   1232: goto -> 1229
    //   1235: astore_1
    //   1236: aload #6
    //   1238: astore_1
    //   1239: goto -> 735
    //   1242: iconst_1
    //   1243: istore #5
    //   1245: goto -> 40
    //   1248: iconst_0
    //   1249: istore #5
    //   1251: goto -> 40
    // Exception table:
    //   from	to	target	type
    //   7	13	1231	finally
    //   24	37	1231	finally
    //   40	51	1231	finally
    //   54	62	1231	finally
    //   62	72	1231	finally
    //   84	103	1231	finally
    //   106	129	1231	finally
    //   132	154	1231	finally
    //   158	166	1231	finally
    //   166	212	1231	finally
    //   219	234	1231	finally
    //   234	241	1231	finally
    //   248	259	1231	finally
    //   259	265	1231	finally
    //   277	538	1231	finally
    //   538	656	1231	finally
    //   659	669	1235	finally
    //   672	735	1235	finally
    //   735	742	1231	finally
    //   751	763	1231	finally
    //   763	962	1231	finally
    //   966	983	1231	finally
    //   988	1003	1231	finally
    //   1006	1023	1231	finally
    //   1031	1227	1231	finally
  }
  
  public final boolean a() {
    return (this.d != null);
  }
}


/* Location:              D:\code\BluedHook\classes.dex\com.soft.blued7646532-dex2jar.jar!\c\t\maploc\lite\tsa\o.class
 * Java compiler version: 6 (50.0)
 * JD-Core Version:       1.1.3
 */