package com.soft.blued.ui.feed.observer;

import com.soft.blued.ui.feed.model.FeedComment;
import java.util.ArrayList;

public class CommentListDataObserver {
  private static CommentListDataObserver a = new CommentListDataObserver();
  
  private ArrayList<ICommentDataObserver> b = new ArrayList<ICommentDataObserver>();
  
  public static CommentListDataObserver a() {
    return a;
  }
  
  public void a(FeedComment paramFeedComment, String paramString) {
    // Byte code:
    //   0: aload_0
    //   1: monitorenter
    //   2: aload_0
    //   3: getfield b : Ljava/util/ArrayList;
    //   6: invokevirtual iterator : ()Ljava/util/Iterator;
    //   9: astore_3
    //   10: aload_3
    //   11: invokeinterface hasNext : ()Z
    //   16: ifeq -> 47
    //   19: aload_3
    //   20: invokeinterface next : ()Ljava/lang/Object;
    //   25: checkcast com/soft/blued/ui/feed/observer/CommentListDataObserver$ICommentDataObserver
    //   28: astore #4
    //   30: aload #4
    //   32: ifnull -> 10
    //   35: aload #4
    //   37: aload_1
    //   38: aload_2
    //   39: invokeinterface a : (Lcom/soft/blued/ui/feed/model/FeedComment;Ljava/lang/String;)V
    //   44: goto -> 10
    //   47: aload_0
    //   48: monitorexit
    //   49: return
    //   50: astore_1
    //   51: aload_0
    //   52: monitorexit
    //   53: aload_1
    //   54: athrow
    // Exception table:
    //   from	to	target	type
    //   2	10	50	finally
    //   10	30	50	finally
    //   35	44	50	finally
  }
  
  public void a(ICommentDataObserver paramICommentDataObserver) {
    // Byte code:
    //   0: aload_0
    //   1: monitorenter
    //   2: aload_1
    //   3: ifnull -> 23
    //   6: aload_0
    //   7: getfield b : Ljava/util/ArrayList;
    //   10: aload_1
    //   11: invokevirtual add : (Ljava/lang/Object;)Z
    //   14: pop
    //   15: goto -> 23
    //   18: astore_1
    //   19: aload_0
    //   20: monitorexit
    //   21: aload_1
    //   22: athrow
    //   23: aload_0
    //   24: monitorexit
    //   25: return
    // Exception table:
    //   from	to	target	type
    //   6	15	18	finally
  }
  
  public void a(String paramString) {
    // Byte code:
    //   0: aload_0
    //   1: monitorenter
    //   2: aload_0
    //   3: getfield b : Ljava/util/ArrayList;
    //   6: invokevirtual iterator : ()Ljava/util/Iterator;
    //   9: astore_2
    //   10: aload_2
    //   11: invokeinterface hasNext : ()Z
    //   16: ifeq -> 43
    //   19: aload_2
    //   20: invokeinterface next : ()Ljava/lang/Object;
    //   25: checkcast com/soft/blued/ui/feed/observer/CommentListDataObserver$ICommentDataObserver
    //   28: astore_3
    //   29: aload_3
    //   30: ifnull -> 10
    //   33: aload_3
    //   34: aload_1
    //   35: invokeinterface a : (Ljava/lang/String;)V
    //   40: goto -> 10
    //   43: aload_0
    //   44: monitorexit
    //   45: return
    //   46: astore_1
    //   47: aload_0
    //   48: monitorexit
    //   49: aload_1
    //   50: athrow
    // Exception table:
    //   from	to	target	type
    //   2	10	46	finally
    //   10	29	46	finally
    //   33	40	46	finally
  }
  
  public void a(String paramString, int paramInt) {
    // Byte code:
    //   0: aload_0
    //   1: monitorenter
    //   2: aload_0
    //   3: getfield b : Ljava/util/ArrayList;
    //   6: invokevirtual iterator : ()Ljava/util/Iterator;
    //   9: astore_3
    //   10: aload_3
    //   11: invokeinterface hasNext : ()Z
    //   16: ifeq -> 47
    //   19: aload_3
    //   20: invokeinterface next : ()Ljava/lang/Object;
    //   25: checkcast com/soft/blued/ui/feed/observer/CommentListDataObserver$ICommentDataObserver
    //   28: astore #4
    //   30: aload #4
    //   32: ifnull -> 10
    //   35: aload #4
    //   37: aload_1
    //   38: iload_2
    //   39: invokeinterface a : (Ljava/lang/String;I)V
    //   44: goto -> 10
    //   47: aload_0
    //   48: monitorexit
    //   49: return
    //   50: astore_1
    //   51: aload_0
    //   52: monitorexit
    //   53: aload_1
    //   54: athrow
    // Exception table:
    //   from	to	target	type
    //   2	10	50	finally
    //   10	30	50	finally
    //   35	44	50	finally
  }
  
  public void b(ICommentDataObserver paramICommentDataObserver) {
    // Byte code:
    //   0: aload_0
    //   1: monitorenter
    //   2: aload_1
    //   3: ifnull -> 23
    //   6: aload_0
    //   7: getfield b : Ljava/util/ArrayList;
    //   10: aload_1
    //   11: invokevirtual remove : (Ljava/lang/Object;)Z
    //   14: pop
    //   15: goto -> 23
    //   18: astore_1
    //   19: aload_0
    //   20: monitorexit
    //   21: aload_1
    //   22: athrow
    //   23: aload_0
    //   24: monitorexit
    //   25: return
    // Exception table:
    //   from	to	target	type
    //   6	15	18	finally
  }
  
  public static interface ICommentDataObserver {
    void a(FeedComment param1FeedComment, String param1String);
    
    void a(String param1String);
    
    void a(String param1String, int param1Int);
  }
}


/* Location:              D:\code\BluedHook\classes.dex\com.soft.blued9136188-dex2jar.jar!\com\soft\blue\\ui\feed\observer\CommentListDataObserver.class
 * Java compiler version: 6 (50.0)
 * JD-Core Version:       1.1.3
 */