package com.alipay.apmobilesecuritysdk.d;

import android.content.Context;
import java.util.Map;

public final class d {
  public static Map<String, String> a() {
    // Byte code:
    //   0: ldc com/alipay/apmobilesecuritysdk/d/d
    //   2: monitorenter
    //   3: new java/util/HashMap
    //   6: dup
    //   7: invokespecial <init> : ()V
    //   10: astore_0
    //   11: new com/alipay/apmobilesecuritysdk/c/b
    //   14: dup
    //   15: invokespecial <init> : ()V
    //   18: pop
    //   19: aload_0
    //   20: ldc 'AE16'
    //   22: ldc ''
    //   24: invokeinterface put : (Ljava/lang/Object;Ljava/lang/Object;)Ljava/lang/Object;
    //   29: pop
    //   30: ldc com/alipay/apmobilesecuritysdk/d/d
    //   32: monitorexit
    //   33: aload_0
    //   34: areturn
    //   35: astore_0
    //   36: ldc com/alipay/apmobilesecuritysdk/d/d
    //   38: monitorexit
    //   39: aload_0
    //   40: athrow
    //   41: astore_1
    //   42: goto -> 30
    // Exception table:
    //   from	to	target	type
    //   3	11	35	finally
    //   11	30	41	finally
  }
  
  public static Map<String, String> a(Context paramContext) {
    // Byte code:
    //   0: ldc com/alipay/apmobilesecuritysdk/d/d
    //   2: monitorenter
    //   3: invokestatic a : ()Lcom/alipay/security/mobile/module/b/d;
    //   6: pop
    //   7: invokestatic a : ()Lcom/alipay/security/mobile/module/b/b;
    //   10: pop
    //   11: new java/util/HashMap
    //   14: dup
    //   15: invokespecial <init> : ()V
    //   18: astore_2
    //   19: aload_2
    //   20: ldc 'AE1'
    //   22: invokestatic b : ()Ljava/lang/String;
    //   25: invokeinterface put : (Ljava/lang/Object;Ljava/lang/Object;)Ljava/lang/Object;
    //   30: pop
    //   31: new java/lang/StringBuilder
    //   34: dup
    //   35: invokespecial <init> : ()V
    //   38: astore_3
    //   39: invokestatic c : ()Z
    //   42: ifeq -> 277
    //   45: ldc '1'
    //   47: astore_1
    //   48: goto -> 51
    //   51: aload_3
    //   52: aload_1
    //   53: invokevirtual append : (Ljava/lang/String;)Ljava/lang/StringBuilder;
    //   56: pop
    //   57: aload_2
    //   58: ldc 'AE2'
    //   60: aload_3
    //   61: invokevirtual toString : ()Ljava/lang/String;
    //   64: invokeinterface put : (Ljava/lang/Object;Ljava/lang/Object;)Ljava/lang/Object;
    //   69: pop
    //   70: new java/lang/StringBuilder
    //   73: dup
    //   74: invokespecial <init> : ()V
    //   77: astore_1
    //   78: aload_0
    //   79: invokestatic a : (Landroid/content/Context;)Z
    //   82: ifeq -> 283
    //   85: ldc '1'
    //   87: astore_0
    //   88: goto -> 91
    //   91: aload_1
    //   92: aload_0
    //   93: invokevirtual append : (Ljava/lang/String;)Ljava/lang/StringBuilder;
    //   96: pop
    //   97: aload_2
    //   98: ldc 'AE3'
    //   100: aload_1
    //   101: invokevirtual toString : ()Ljava/lang/String;
    //   104: invokeinterface put : (Ljava/lang/Object;Ljava/lang/Object;)Ljava/lang/Object;
    //   109: pop
    //   110: aload_2
    //   111: ldc 'AE4'
    //   113: invokestatic d : ()Ljava/lang/String;
    //   116: invokeinterface put : (Ljava/lang/Object;Ljava/lang/Object;)Ljava/lang/Object;
    //   121: pop
    //   122: aload_2
    //   123: ldc 'AE5'
    //   125: invokestatic e : ()Ljava/lang/String;
    //   128: invokeinterface put : (Ljava/lang/Object;Ljava/lang/Object;)Ljava/lang/Object;
    //   133: pop
    //   134: aload_2
    //   135: ldc 'AE6'
    //   137: invokestatic f : ()Ljava/lang/String;
    //   140: invokeinterface put : (Ljava/lang/Object;Ljava/lang/Object;)Ljava/lang/Object;
    //   145: pop
    //   146: aload_2
    //   147: ldc 'AE7'
    //   149: invokestatic g : ()Ljava/lang/String;
    //   152: invokeinterface put : (Ljava/lang/Object;Ljava/lang/Object;)Ljava/lang/Object;
    //   157: pop
    //   158: aload_2
    //   159: ldc 'AE8'
    //   161: invokestatic h : ()Ljava/lang/String;
    //   164: invokeinterface put : (Ljava/lang/Object;Ljava/lang/Object;)Ljava/lang/Object;
    //   169: pop
    //   170: aload_2
    //   171: ldc 'AE9'
    //   173: invokestatic i : ()Ljava/lang/String;
    //   176: invokeinterface put : (Ljava/lang/Object;Ljava/lang/Object;)Ljava/lang/Object;
    //   181: pop
    //   182: aload_2
    //   183: ldc 'AE10'
    //   185: invokestatic j : ()Ljava/lang/String;
    //   188: invokeinterface put : (Ljava/lang/Object;Ljava/lang/Object;)Ljava/lang/Object;
    //   193: pop
    //   194: aload_2
    //   195: ldc 'AE11'
    //   197: invokestatic k : ()Ljava/lang/String;
    //   200: invokeinterface put : (Ljava/lang/Object;Ljava/lang/Object;)Ljava/lang/Object;
    //   205: pop
    //   206: aload_2
    //   207: ldc 'AE12'
    //   209: invokestatic l : ()Ljava/lang/String;
    //   212: invokeinterface put : (Ljava/lang/Object;Ljava/lang/Object;)Ljava/lang/Object;
    //   217: pop
    //   218: aload_2
    //   219: ldc 'AE13'
    //   221: invokestatic m : ()Ljava/lang/String;
    //   224: invokeinterface put : (Ljava/lang/Object;Ljava/lang/Object;)Ljava/lang/Object;
    //   229: pop
    //   230: aload_2
    //   231: ldc 'AE14'
    //   233: invokestatic n : ()Ljava/lang/String;
    //   236: invokeinterface put : (Ljava/lang/Object;Ljava/lang/Object;)Ljava/lang/Object;
    //   241: pop
    //   242: aload_2
    //   243: ldc 'AE15'
    //   245: invokestatic o : ()Ljava/lang/String;
    //   248: invokeinterface put : (Ljava/lang/Object;Ljava/lang/Object;)Ljava/lang/Object;
    //   253: pop
    //   254: aload_2
    //   255: ldc 'AE21'
    //   257: invokestatic g : ()Ljava/lang/String;
    //   260: invokeinterface put : (Ljava/lang/Object;Ljava/lang/Object;)Ljava/lang/Object;
    //   265: pop
    //   266: ldc com/alipay/apmobilesecuritysdk/d/d
    //   268: monitorexit
    //   269: aload_2
    //   270: areturn
    //   271: astore_0
    //   272: ldc com/alipay/apmobilesecuritysdk/d/d
    //   274: monitorexit
    //   275: aload_0
    //   276: athrow
    //   277: ldc '0'
    //   279: astore_1
    //   280: goto -> 51
    //   283: ldc '0'
    //   285: astore_0
    //   286: goto -> 91
    // Exception table:
    //   from	to	target	type
    //   3	45	271	finally
    //   51	85	271	finally
    //   91	266	271	finally
  }
}


/* Location:              D:\code\BluedHook\classes.dex\com.soft.blued7646532-dex2jar.jar!\com\alipay\apmobilesecuritysdk\d\d.class
 * Java compiler version: 6 (50.0)
 * JD-Core Version:       1.1.3
 */