package com.blued.android.module.live_china.observer;

import android.widget.EditText;
import com.blued.android.chat.data.BadgeData;
import com.blued.android.chat.model.ChattingModel;
import com.blued.android.module.live_china.model.LiveGiftModel;
import com.blued.android.module.live_china.model.LiveHornModel;
import com.blued.android.module.live_china.model.LiveMakeLoverFansModel;
import com.blued.android.module.live_china.model.LiveRewardModel;
import com.blued.android.module.live_china.model.LiveRoomData;
import com.blued.android.module.live_china.model.LiveRoomUserModel;
import com.blued.android.module.live_china.model.LiveZanExtraModel;
import java.util.ArrayList;
import java.util.List;

public class LiveSetDataObserver {
  private static LiveSetDataObserver a = new LiveSetDataObserver();
  
  private ArrayList<ILiveSetDataObserver> b = new ArrayList<ILiveSetDataObserver>();
  
  public static LiveSetDataObserver a() {
    return a;
  }
  
  public void a(int paramInt) {
    // Byte code:
    //   0: aload_0
    //   1: monitorenter
    //   2: aload_0
    //   3: getfield b : Ljava/util/ArrayList;
    //   6: invokevirtual iterator : ()Ljava/util/Iterator;
    //   9: astore_2
    //   10: aload_2
    //   11: invokeinterface hasNext : ()Z
    //   16: ifeq -> 43
    //   19: aload_2
    //   20: invokeinterface next : ()Ljava/lang/Object;
    //   25: checkcast com/blued/android/module/live_china/observer/LiveSetDataObserver$ILiveSetDataObserver
    //   28: astore_3
    //   29: aload_3
    //   30: ifnull -> 10
    //   33: aload_3
    //   34: iload_1
    //   35: invokeinterface f : (I)V
    //   40: goto -> 10
    //   43: aload_0
    //   44: monitorexit
    //   45: return
    //   46: astore_2
    //   47: aload_0
    //   48: monitorexit
    //   49: aload_2
    //   50: athrow
    // Exception table:
    //   from	to	target	type
    //   2	10	46	finally
    //   10	29	46	finally
    //   33	40	46	finally
  }
  
  public void a(int paramInt1, int paramInt2, int paramInt3, float paramFloat) {
    // Byte code:
    //   0: aload_0
    //   1: monitorenter
    //   2: aload_0
    //   3: getfield b : Ljava/util/ArrayList;
    //   6: invokevirtual iterator : ()Ljava/util/Iterator;
    //   9: astore #5
    //   11: aload #5
    //   13: invokeinterface hasNext : ()Z
    //   18: ifeq -> 53
    //   21: aload #5
    //   23: invokeinterface next : ()Ljava/lang/Object;
    //   28: checkcast com/blued/android/module/live_china/observer/LiveSetDataObserver$ILiveSetDataObserver
    //   31: astore #6
    //   33: aload #6
    //   35: ifnull -> 11
    //   38: aload #6
    //   40: iload_1
    //   41: iload_2
    //   42: iload_3
    //   43: fload #4
    //   45: invokeinterface a : (IIIF)V
    //   50: goto -> 11
    //   53: aload_0
    //   54: monitorexit
    //   55: return
    //   56: astore #5
    //   58: aload_0
    //   59: monitorexit
    //   60: aload #5
    //   62: athrow
    // Exception table:
    //   from	to	target	type
    //   2	11	56	finally
    //   11	33	56	finally
    //   38	50	56	finally
  }
  
  public void a(int paramInt1, int paramInt2, int paramInt3, int paramInt4) {
    // Byte code:
    //   0: aload_0
    //   1: monitorenter
    //   2: aload_0
    //   3: getfield b : Ljava/util/ArrayList;
    //   6: invokevirtual iterator : ()Ljava/util/Iterator;
    //   9: astore #5
    //   11: aload #5
    //   13: invokeinterface hasNext : ()Z
    //   18: ifeq -> 53
    //   21: aload #5
    //   23: invokeinterface next : ()Ljava/lang/Object;
    //   28: checkcast com/blued/android/module/live_china/observer/LiveSetDataObserver$ILiveSetDataObserver
    //   31: astore #6
    //   33: aload #6
    //   35: ifnull -> 11
    //   38: aload #6
    //   40: iload_1
    //   41: iload_2
    //   42: iload_3
    //   43: iload #4
    //   45: invokeinterface a : (IIII)V
    //   50: goto -> 11
    //   53: aload_0
    //   54: monitorexit
    //   55: return
    //   56: astore #5
    //   58: aload_0
    //   59: monitorexit
    //   60: aload #5
    //   62: athrow
    // Exception table:
    //   from	to	target	type
    //   2	11	56	finally
    //   11	33	56	finally
    //   38	50	56	finally
  }
  
  public void a(long paramLong) {
    // Byte code:
    //   0: aload_0
    //   1: monitorenter
    //   2: aload_0
    //   3: getfield b : Ljava/util/ArrayList;
    //   6: invokevirtual iterator : ()Ljava/util/Iterator;
    //   9: astore_3
    //   10: aload_3
    //   11: invokeinterface hasNext : ()Z
    //   16: ifeq -> 46
    //   19: aload_3
    //   20: invokeinterface next : ()Ljava/lang/Object;
    //   25: checkcast com/blued/android/module/live_china/observer/LiveSetDataObserver$ILiveSetDataObserver
    //   28: astore #4
    //   30: aload #4
    //   32: ifnull -> 10
    //   35: aload #4
    //   37: lload_1
    //   38: invokeinterface b : (J)V
    //   43: goto -> 10
    //   46: aload_0
    //   47: monitorexit
    //   48: return
    //   49: astore_3
    //   50: aload_0
    //   51: monitorexit
    //   52: aload_3
    //   53: athrow
    // Exception table:
    //   from	to	target	type
    //   2	10	49	finally
    //   10	30	49	finally
    //   35	43	49	finally
  }
  
  public void a(EditText paramEditText) {
    // Byte code:
    //   0: aload_0
    //   1: monitorenter
    //   2: aload_0
    //   3: getfield b : Ljava/util/ArrayList;
    //   6: invokevirtual iterator : ()Ljava/util/Iterator;
    //   9: astore_2
    //   10: aload_2
    //   11: invokeinterface hasNext : ()Z
    //   16: ifeq -> 43
    //   19: aload_2
    //   20: invokeinterface next : ()Ljava/lang/Object;
    //   25: checkcast com/blued/android/module/live_china/observer/LiveSetDataObserver$ILiveSetDataObserver
    //   28: astore_3
    //   29: aload_3
    //   30: ifnull -> 10
    //   33: aload_3
    //   34: aload_1
    //   35: invokeinterface a : (Landroid/widget/EditText;)V
    //   40: goto -> 10
    //   43: aload_0
    //   44: monitorexit
    //   45: return
    //   46: astore_1
    //   47: aload_0
    //   48: monitorexit
    //   49: aload_1
    //   50: athrow
    // Exception table:
    //   from	to	target	type
    //   2	10	46	finally
    //   10	29	46	finally
    //   33	40	46	finally
  }
  
  public void a(ChattingModel paramChattingModel) {
    // Byte code:
    //   0: aload_0
    //   1: monitorenter
    //   2: aload_0
    //   3: getfield b : Ljava/util/ArrayList;
    //   6: invokevirtual iterator : ()Ljava/util/Iterator;
    //   9: astore_2
    //   10: aload_2
    //   11: invokeinterface hasNext : ()Z
    //   16: ifeq -> 43
    //   19: aload_2
    //   20: invokeinterface next : ()Ljava/lang/Object;
    //   25: checkcast com/blued/android/module/live_china/observer/LiveSetDataObserver$ILiveSetDataObserver
    //   28: astore_3
    //   29: aload_3
    //   30: ifnull -> 10
    //   33: aload_3
    //   34: aload_1
    //   35: invokeinterface c : (Lcom/blued/android/chat/model/ChattingModel;)V
    //   40: goto -> 10
    //   43: aload_0
    //   44: monitorexit
    //   45: return
    //   46: astore_1
    //   47: aload_0
    //   48: monitorexit
    //   49: aload_1
    //   50: athrow
    // Exception table:
    //   from	to	target	type
    //   2	10	46	finally
    //   10	29	46	finally
    //   33	40	46	finally
  }
  
  public void a(LiveGiftModel paramLiveGiftModel) {
    // Byte code:
    //   0: aload_0
    //   1: monitorenter
    //   2: aload_0
    //   3: getfield b : Ljava/util/ArrayList;
    //   6: invokevirtual iterator : ()Ljava/util/Iterator;
    //   9: astore_2
    //   10: aload_2
    //   11: invokeinterface hasNext : ()Z
    //   16: ifeq -> 43
    //   19: aload_2
    //   20: invokeinterface next : ()Ljava/lang/Object;
    //   25: checkcast com/blued/android/module/live_china/observer/LiveSetDataObserver$ILiveSetDataObserver
    //   28: astore_3
    //   29: aload_3
    //   30: ifnull -> 10
    //   33: aload_3
    //   34: aload_1
    //   35: invokeinterface b : (Lcom/blued/android/module/live_china/model/LiveGiftModel;)V
    //   40: goto -> 10
    //   43: aload_0
    //   44: monitorexit
    //   45: return
    //   46: astore_1
    //   47: aload_0
    //   48: monitorexit
    //   49: aload_1
    //   50: athrow
    // Exception table:
    //   from	to	target	type
    //   2	10	46	finally
    //   10	29	46	finally
    //   33	40	46	finally
  }
  
  public void a(LiveHornModel paramLiveHornModel, boolean paramBoolean) {
    // Byte code:
    //   0: aload_0
    //   1: monitorenter
    //   2: aload_0
    //   3: getfield b : Ljava/util/ArrayList;
    //   6: invokevirtual iterator : ()Ljava/util/Iterator;
    //   9: astore_3
    //   10: aload_3
    //   11: invokeinterface hasNext : ()Z
    //   16: ifeq -> 47
    //   19: aload_3
    //   20: invokeinterface next : ()Ljava/lang/Object;
    //   25: checkcast com/blued/android/module/live_china/observer/LiveSetDataObserver$ILiveSetDataObserver
    //   28: astore #4
    //   30: aload #4
    //   32: ifnull -> 10
    //   35: aload #4
    //   37: aload_1
    //   38: iload_2
    //   39: invokeinterface a : (Lcom/blued/android/module/live_china/model/LiveHornModel;Z)V
    //   44: goto -> 10
    //   47: aload_0
    //   48: monitorexit
    //   49: return
    //   50: astore_1
    //   51: aload_0
    //   52: monitorexit
    //   53: aload_1
    //   54: athrow
    // Exception table:
    //   from	to	target	type
    //   2	10	50	finally
    //   10	30	50	finally
    //   35	44	50	finally
  }
  
  public void a(LiveMakeLoverFansModel paramLiveMakeLoverFansModel) {
    // Byte code:
    //   0: aload_0
    //   1: monitorenter
    //   2: aload_0
    //   3: getfield b : Ljava/util/ArrayList;
    //   6: invokevirtual iterator : ()Ljava/util/Iterator;
    //   9: astore_2
    //   10: aload_2
    //   11: invokeinterface hasNext : ()Z
    //   16: ifeq -> 43
    //   19: aload_2
    //   20: invokeinterface next : ()Ljava/lang/Object;
    //   25: checkcast com/blued/android/module/live_china/observer/LiveSetDataObserver$ILiveSetDataObserver
    //   28: astore_3
    //   29: aload_3
    //   30: ifnull -> 10
    //   33: aload_3
    //   34: aload_1
    //   35: invokeinterface a : (Lcom/blued/android/module/live_china/model/LiveMakeLoverFansModel;)V
    //   40: goto -> 10
    //   43: aload_0
    //   44: monitorexit
    //   45: return
    //   46: astore_1
    //   47: aload_0
    //   48: monitorexit
    //   49: aload_1
    //   50: athrow
    // Exception table:
    //   from	to	target	type
    //   2	10	46	finally
    //   10	29	46	finally
    //   33	40	46	finally
  }
  
  public void a(LiveRewardModel paramLiveRewardModel) {
    // Byte code:
    //   0: aload_0
    //   1: monitorenter
    //   2: aload_0
    //   3: getfield b : Ljava/util/ArrayList;
    //   6: invokevirtual iterator : ()Ljava/util/Iterator;
    //   9: astore_2
    //   10: aload_2
    //   11: invokeinterface hasNext : ()Z
    //   16: ifeq -> 43
    //   19: aload_2
    //   20: invokeinterface next : ()Ljava/lang/Object;
    //   25: checkcast com/blued/android/module/live_china/observer/LiveSetDataObserver$ILiveSetDataObserver
    //   28: astore_3
    //   29: aload_3
    //   30: ifnull -> 10
    //   33: aload_3
    //   34: aload_1
    //   35: invokeinterface a : (Lcom/blued/android/module/live_china/model/LiveRewardModel;)V
    //   40: goto -> 10
    //   43: aload_0
    //   44: monitorexit
    //   45: return
    //   46: astore_1
    //   47: aload_0
    //   48: monitorexit
    //   49: aload_1
    //   50: athrow
    // Exception table:
    //   from	to	target	type
    //   2	10	46	finally
    //   10	29	46	finally
    //   33	40	46	finally
  }
  
  public void a(LiveRoomData paramLiveRoomData) {
    // Byte code:
    //   0: aload_0
    //   1: monitorenter
    //   2: aload_0
    //   3: getfield b : Ljava/util/ArrayList;
    //   6: invokevirtual iterator : ()Ljava/util/Iterator;
    //   9: astore_2
    //   10: aload_2
    //   11: invokeinterface hasNext : ()Z
    //   16: ifeq -> 43
    //   19: aload_2
    //   20: invokeinterface next : ()Ljava/lang/Object;
    //   25: checkcast com/blued/android/module/live_china/observer/LiveSetDataObserver$ILiveSetDataObserver
    //   28: astore_3
    //   29: aload_3
    //   30: ifnull -> 10
    //   33: aload_3
    //   34: aload_1
    //   35: invokeinterface a : (Lcom/blued/android/module/live_china/model/LiveRoomData;)V
    //   40: goto -> 10
    //   43: aload_0
    //   44: monitorexit
    //   45: return
    //   46: astore_1
    //   47: aload_0
    //   48: monitorexit
    //   49: aload_1
    //   50: athrow
    // Exception table:
    //   from	to	target	type
    //   2	10	46	finally
    //   10	29	46	finally
    //   33	40	46	finally
  }
  
  public void a(LiveRoomUserModel paramLiveRoomUserModel) {
    // Byte code:
    //   0: aload_0
    //   1: monitorenter
    //   2: aload_0
    //   3: getfield b : Ljava/util/ArrayList;
    //   6: invokevirtual iterator : ()Ljava/util/Iterator;
    //   9: astore_2
    //   10: aload_2
    //   11: invokeinterface hasNext : ()Z
    //   16: ifeq -> 43
    //   19: aload_2
    //   20: invokeinterface next : ()Ljava/lang/Object;
    //   25: checkcast com/blued/android/module/live_china/observer/LiveSetDataObserver$ILiveSetDataObserver
    //   28: astore_3
    //   29: aload_3
    //   30: ifnull -> 10
    //   33: aload_3
    //   34: aload_1
    //   35: invokeinterface a : (Lcom/blued/android/module/live_china/model/LiveRoomUserModel;)V
    //   40: goto -> 10
    //   43: aload_0
    //   44: monitorexit
    //   45: return
    //   46: astore_1
    //   47: aload_0
    //   48: monitorexit
    //   49: aload_1
    //   50: athrow
    // Exception table:
    //   from	to	target	type
    //   2	10	46	finally
    //   10	29	46	finally
    //   33	40	46	finally
  }
  
  public void a(LiveZanExtraModel.Danmaku paramDanmaku) {
    // Byte code:
    //   0: aload_0
    //   1: monitorenter
    //   2: aload_0
    //   3: getfield b : Ljava/util/ArrayList;
    //   6: invokevirtual iterator : ()Ljava/util/Iterator;
    //   9: astore_2
    //   10: aload_2
    //   11: invokeinterface hasNext : ()Z
    //   16: ifeq -> 43
    //   19: aload_2
    //   20: invokeinterface next : ()Ljava/lang/Object;
    //   25: checkcast com/blued/android/module/live_china/observer/LiveSetDataObserver$ILiveSetDataObserver
    //   28: astore_3
    //   29: aload_3
    //   30: ifnull -> 10
    //   33: aload_3
    //   34: aload_1
    //   35: invokeinterface a : (Lcom/blued/android/module/live_china/model/LiveZanExtraModel$Danmaku;)V
    //   40: goto -> 10
    //   43: aload_0
    //   44: monitorexit
    //   45: return
    //   46: astore_1
    //   47: aload_0
    //   48: monitorexit
    //   49: aload_1
    //   50: athrow
    // Exception table:
    //   from	to	target	type
    //   2	10	46	finally
    //   10	29	46	finally
    //   33	40	46	finally
  }
  
  public void a(ILiveSetDataObserver paramILiveSetDataObserver) {
    // Byte code:
    //   0: aload_0
    //   1: monitorenter
    //   2: aload_1
    //   3: ifnull -> 23
    //   6: aload_0
    //   7: getfield b : Ljava/util/ArrayList;
    //   10: aload_1
    //   11: invokevirtual add : (Ljava/lang/Object;)Z
    //   14: pop
    //   15: goto -> 23
    //   18: astore_1
    //   19: aload_0
    //   20: monitorexit
    //   21: aload_1
    //   22: athrow
    //   23: aload_0
    //   24: monitorexit
    //   25: return
    // Exception table:
    //   from	to	target	type
    //   6	15	18	finally
  }
  
  public void a(String paramString) {
    // Byte code:
    //   0: aload_0
    //   1: monitorenter
    //   2: aload_0
    //   3: getfield b : Ljava/util/ArrayList;
    //   6: invokevirtual iterator : ()Ljava/util/Iterator;
    //   9: astore_2
    //   10: aload_2
    //   11: invokeinterface hasNext : ()Z
    //   16: ifeq -> 43
    //   19: aload_2
    //   20: invokeinterface next : ()Ljava/lang/Object;
    //   25: checkcast com/blued/android/module/live_china/observer/LiveSetDataObserver$ILiveSetDataObserver
    //   28: astore_3
    //   29: aload_3
    //   30: ifnull -> 10
    //   33: aload_3
    //   34: aload_1
    //   35: invokeinterface b_ : (Ljava/lang/String;)V
    //   40: goto -> 10
    //   43: aload_0
    //   44: monitorexit
    //   45: return
    //   46: astore_1
    //   47: aload_0
    //   48: monitorexit
    //   49: aload_1
    //   50: athrow
    // Exception table:
    //   from	to	target	type
    //   2	10	46	finally
    //   10	29	46	finally
    //   33	40	46	finally
  }
  
  public void a(String paramString, int paramInt) {
    // Byte code:
    //   0: aload_0
    //   1: monitorenter
    //   2: aload_0
    //   3: getfield b : Ljava/util/ArrayList;
    //   6: invokevirtual iterator : ()Ljava/util/Iterator;
    //   9: astore_3
    //   10: aload_3
    //   11: invokeinterface hasNext : ()Z
    //   16: ifeq -> 47
    //   19: aload_3
    //   20: invokeinterface next : ()Ljava/lang/Object;
    //   25: checkcast com/blued/android/module/live_china/observer/LiveSetDataObserver$ILiveSetDataObserver
    //   28: astore #4
    //   30: aload #4
    //   32: ifnull -> 10
    //   35: aload #4
    //   37: aload_1
    //   38: iload_2
    //   39: invokeinterface a : (Ljava/lang/String;I)V
    //   44: goto -> 10
    //   47: aload_0
    //   48: monitorexit
    //   49: return
    //   50: astore_1
    //   51: aload_0
    //   52: monitorexit
    //   53: aload_1
    //   54: athrow
    // Exception table:
    //   from	to	target	type
    //   2	10	50	finally
    //   10	30	50	finally
    //   35	44	50	finally
  }
  
  public void a(String paramString1, String paramString2) {
    // Byte code:
    //   0: aload_0
    //   1: monitorenter
    //   2: aload_0
    //   3: getfield b : Ljava/util/ArrayList;
    //   6: invokevirtual iterator : ()Ljava/util/Iterator;
    //   9: astore_3
    //   10: aload_3
    //   11: invokeinterface hasNext : ()Z
    //   16: ifeq -> 47
    //   19: aload_3
    //   20: invokeinterface next : ()Ljava/lang/Object;
    //   25: checkcast com/blued/android/module/live_china/observer/LiveSetDataObserver$ILiveSetDataObserver
    //   28: astore #4
    //   30: aload #4
    //   32: ifnull -> 10
    //   35: aload #4
    //   37: aload_1
    //   38: aload_2
    //   39: invokeinterface a : (Ljava/lang/String;Ljava/lang/String;)V
    //   44: goto -> 10
    //   47: aload_0
    //   48: monitorexit
    //   49: return
    //   50: astore_1
    //   51: aload_0
    //   52: monitorexit
    //   53: aload_1
    //   54: athrow
    // Exception table:
    //   from	to	target	type
    //   2	10	50	finally
    //   10	30	50	finally
    //   35	44	50	finally
  }
  
  public void a(List<String> paramList) {
    // Byte code:
    //   0: aload_0
    //   1: monitorenter
    //   2: aload_0
    //   3: getfield b : Ljava/util/ArrayList;
    //   6: invokevirtual iterator : ()Ljava/util/Iterator;
    //   9: astore_2
    //   10: aload_2
    //   11: invokeinterface hasNext : ()Z
    //   16: ifeq -> 43
    //   19: aload_2
    //   20: invokeinterface next : ()Ljava/lang/Object;
    //   25: checkcast com/blued/android/module/live_china/observer/LiveSetDataObserver$ILiveSetDataObserver
    //   28: astore_3
    //   29: aload_3
    //   30: ifnull -> 10
    //   33: aload_3
    //   34: aload_1
    //   35: invokeinterface a_ : (Ljava/util/List;)V
    //   40: goto -> 10
    //   43: aload_0
    //   44: monitorexit
    //   45: return
    //   46: astore_1
    //   47: aload_0
    //   48: monitorexit
    //   49: aload_1
    //   50: athrow
    // Exception table:
    //   from	to	target	type
    //   2	10	46	finally
    //   10	29	46	finally
    //   33	40	46	finally
  }
  
  public void a(boolean paramBoolean) {
    // Byte code:
    //   0: aload_0
    //   1: monitorenter
    //   2: aload_0
    //   3: getfield b : Ljava/util/ArrayList;
    //   6: invokevirtual iterator : ()Ljava/util/Iterator;
    //   9: astore_2
    //   10: aload_2
    //   11: invokeinterface hasNext : ()Z
    //   16: ifeq -> 43
    //   19: aload_2
    //   20: invokeinterface next : ()Ljava/lang/Object;
    //   25: checkcast com/blued/android/module/live_china/observer/LiveSetDataObserver$ILiveSetDataObserver
    //   28: astore_3
    //   29: aload_3
    //   30: ifnull -> 10
    //   33: aload_3
    //   34: iload_1
    //   35: invokeinterface c : (Z)V
    //   40: goto -> 10
    //   43: aload_0
    //   44: monitorexit
    //   45: return
    //   46: astore_2
    //   47: aload_0
    //   48: monitorexit
    //   49: aload_2
    //   50: athrow
    // Exception table:
    //   from	to	target	type
    //   2	10	46	finally
    //   10	29	46	finally
    //   33	40	46	finally
  }
  
  public void a(boolean paramBoolean1, boolean paramBoolean2) {
    // Byte code:
    //   0: aload_0
    //   1: monitorenter
    //   2: aload_0
    //   3: getfield b : Ljava/util/ArrayList;
    //   6: invokevirtual iterator : ()Ljava/util/Iterator;
    //   9: astore_3
    //   10: aload_3
    //   11: invokeinterface hasNext : ()Z
    //   16: ifeq -> 47
    //   19: aload_3
    //   20: invokeinterface next : ()Ljava/lang/Object;
    //   25: checkcast com/blued/android/module/live_china/observer/LiveSetDataObserver$ILiveSetDataObserver
    //   28: astore #4
    //   30: aload #4
    //   32: ifnull -> 10
    //   35: aload #4
    //   37: iload_1
    //   38: iload_2
    //   39: invokeinterface a : (ZZ)V
    //   44: goto -> 10
    //   47: aload_0
    //   48: monitorexit
    //   49: return
    //   50: astore_3
    //   51: aload_0
    //   52: monitorexit
    //   53: aload_3
    //   54: athrow
    // Exception table:
    //   from	to	target	type
    //   2	10	50	finally
    //   10	30	50	finally
    //   35	44	50	finally
  }
  
  public void b() {
    // Byte code:
    //   0: aload_0
    //   1: monitorenter
    //   2: aload_0
    //   3: getfield b : Ljava/util/ArrayList;
    //   6: invokevirtual iterator : ()Ljava/util/Iterator;
    //   9: astore_1
    //   10: aload_1
    //   11: invokeinterface hasNext : ()Z
    //   16: ifeq -> 42
    //   19: aload_1
    //   20: invokeinterface next : ()Ljava/lang/Object;
    //   25: checkcast com/blued/android/module/live_china/observer/LiveSetDataObserver$ILiveSetDataObserver
    //   28: astore_2
    //   29: aload_2
    //   30: ifnull -> 10
    //   33: aload_2
    //   34: invokeinterface I_ : ()V
    //   39: goto -> 10
    //   42: aload_0
    //   43: monitorexit
    //   44: return
    //   45: astore_1
    //   46: aload_0
    //   47: monitorexit
    //   48: aload_1
    //   49: athrow
    // Exception table:
    //   from	to	target	type
    //   2	10	45	finally
    //   10	29	45	finally
    //   33	39	45	finally
  }
  
  public void b(int paramInt) {
    // Byte code:
    //   0: aload_0
    //   1: monitorenter
    //   2: aload_0
    //   3: getfield b : Ljava/util/ArrayList;
    //   6: invokevirtual iterator : ()Ljava/util/Iterator;
    //   9: astore_2
    //   10: aload_2
    //   11: invokeinterface hasNext : ()Z
    //   16: ifeq -> 43
    //   19: aload_2
    //   20: invokeinterface next : ()Ljava/lang/Object;
    //   25: checkcast com/blued/android/module/live_china/observer/LiveSetDataObserver$ILiveSetDataObserver
    //   28: astore_3
    //   29: aload_3
    //   30: ifnull -> 10
    //   33: aload_3
    //   34: iload_1
    //   35: invokeinterface e : (I)V
    //   40: goto -> 10
    //   43: aload_0
    //   44: monitorexit
    //   45: return
    //   46: astore_2
    //   47: aload_0
    //   48: monitorexit
    //   49: aload_2
    //   50: athrow
    // Exception table:
    //   from	to	target	type
    //   2	10	46	finally
    //   10	29	46	finally
    //   33	40	46	finally
  }
  
  public void b(long paramLong) {
    // Byte code:
    //   0: aload_0
    //   1: monitorenter
    //   2: aload_0
    //   3: getfield b : Ljava/util/ArrayList;
    //   6: invokevirtual iterator : ()Ljava/util/Iterator;
    //   9: astore_3
    //   10: aload_3
    //   11: invokeinterface hasNext : ()Z
    //   16: ifeq -> 46
    //   19: aload_3
    //   20: invokeinterface next : ()Ljava/lang/Object;
    //   25: checkcast com/blued/android/module/live_china/observer/LiveSetDataObserver$ILiveSetDataObserver
    //   28: astore #4
    //   30: aload #4
    //   32: ifnull -> 10
    //   35: aload #4
    //   37: lload_1
    //   38: invokeinterface a : (J)V
    //   43: goto -> 10
    //   46: aload_0
    //   47: monitorexit
    //   48: return
    //   49: astore_3
    //   50: aload_0
    //   51: monitorexit
    //   52: aload_3
    //   53: athrow
    // Exception table:
    //   from	to	target	type
    //   2	10	49	finally
    //   10	30	49	finally
    //   35	43	49	finally
  }
  
  public void b(ChattingModel paramChattingModel) {
    // Byte code:
    //   0: aload_0
    //   1: monitorenter
    //   2: aload_0
    //   3: getfield b : Ljava/util/ArrayList;
    //   6: invokevirtual iterator : ()Ljava/util/Iterator;
    //   9: astore_2
    //   10: aload_2
    //   11: invokeinterface hasNext : ()Z
    //   16: ifeq -> 43
    //   19: aload_2
    //   20: invokeinterface next : ()Ljava/lang/Object;
    //   25: checkcast com/blued/android/module/live_china/observer/LiveSetDataObserver$ILiveSetDataObserver
    //   28: astore_3
    //   29: aload_3
    //   30: ifnull -> 10
    //   33: aload_3
    //   34: aload_1
    //   35: invokeinterface a : (Lcom/blued/android/chat/model/ChattingModel;)V
    //   40: goto -> 10
    //   43: aload_0
    //   44: monitorexit
    //   45: return
    //   46: astore_1
    //   47: aload_0
    //   48: monitorexit
    //   49: aload_1
    //   50: athrow
    // Exception table:
    //   from	to	target	type
    //   2	10	46	finally
    //   10	29	46	finally
    //   33	40	46	finally
  }
  
  public void b(LiveGiftModel paramLiveGiftModel) {
    // Byte code:
    //   0: aload_0
    //   1: monitorenter
    //   2: aload_0
    //   3: getfield b : Ljava/util/ArrayList;
    //   6: invokevirtual iterator : ()Ljava/util/Iterator;
    //   9: astore_2
    //   10: aload_2
    //   11: invokeinterface hasNext : ()Z
    //   16: ifeq -> 43
    //   19: aload_2
    //   20: invokeinterface next : ()Ljava/lang/Object;
    //   25: checkcast com/blued/android/module/live_china/observer/LiveSetDataObserver$ILiveSetDataObserver
    //   28: astore_3
    //   29: aload_3
    //   30: ifnull -> 10
    //   33: aload_3
    //   34: aload_1
    //   35: invokeinterface a : (Lcom/blued/android/module/live_china/model/LiveGiftModel;)V
    //   40: goto -> 10
    //   43: aload_0
    //   44: monitorexit
    //   45: return
    //   46: astore_1
    //   47: aload_0
    //   48: monitorexit
    //   49: aload_1
    //   50: athrow
    // Exception table:
    //   from	to	target	type
    //   2	10	46	finally
    //   10	29	46	finally
    //   33	40	46	finally
  }
  
  public void b(ILiveSetDataObserver paramILiveSetDataObserver) {
    // Byte code:
    //   0: aload_0
    //   1: monitorenter
    //   2: aload_1
    //   3: ifnull -> 23
    //   6: aload_0
    //   7: getfield b : Ljava/util/ArrayList;
    //   10: aload_1
    //   11: invokevirtual remove : (Ljava/lang/Object;)Z
    //   14: pop
    //   15: goto -> 23
    //   18: astore_1
    //   19: aload_0
    //   20: monitorexit
    //   21: aload_1
    //   22: athrow
    //   23: aload_0
    //   24: monitorexit
    //   25: return
    // Exception table:
    //   from	to	target	type
    //   6	15	18	finally
  }
  
  public void b(String paramString) {
    // Byte code:
    //   0: aload_0
    //   1: monitorenter
    //   2: aload_0
    //   3: getfield b : Ljava/util/ArrayList;
    //   6: invokevirtual iterator : ()Ljava/util/Iterator;
    //   9: astore_2
    //   10: aload_2
    //   11: invokeinterface hasNext : ()Z
    //   16: ifeq -> 43
    //   19: aload_2
    //   20: invokeinterface next : ()Ljava/lang/Object;
    //   25: checkcast com/blued/android/module/live_china/observer/LiveSetDataObserver$ILiveSetDataObserver
    //   28: astore_3
    //   29: aload_3
    //   30: ifnull -> 10
    //   33: aload_3
    //   34: aload_1
    //   35: invokeinterface f : (Ljava/lang/String;)V
    //   40: goto -> 10
    //   43: aload_0
    //   44: monitorexit
    //   45: return
    //   46: astore_1
    //   47: aload_0
    //   48: monitorexit
    //   49: aload_1
    //   50: athrow
    // Exception table:
    //   from	to	target	type
    //   2	10	46	finally
    //   10	29	46	finally
    //   33	40	46	finally
  }
  
  public void b(List<LiveZanExtraModel.HotWords> paramList) {
    // Byte code:
    //   0: aload_0
    //   1: monitorenter
    //   2: aload_0
    //   3: getfield b : Ljava/util/ArrayList;
    //   6: invokevirtual iterator : ()Ljava/util/Iterator;
    //   9: astore_2
    //   10: aload_2
    //   11: invokeinterface hasNext : ()Z
    //   16: ifeq -> 43
    //   19: aload_2
    //   20: invokeinterface next : ()Ljava/lang/Object;
    //   25: checkcast com/blued/android/module/live_china/observer/LiveSetDataObserver$ILiveSetDataObserver
    //   28: astore_3
    //   29: aload_3
    //   30: ifnull -> 10
    //   33: aload_3
    //   34: aload_1
    //   35: invokeinterface c : (Ljava/util/List;)V
    //   40: goto -> 10
    //   43: aload_0
    //   44: monitorexit
    //   45: return
    //   46: astore_1
    //   47: aload_0
    //   48: monitorexit
    //   49: aload_1
    //   50: athrow
    // Exception table:
    //   from	to	target	type
    //   2	10	46	finally
    //   10	29	46	finally
    //   33	40	46	finally
  }
  
  public void b(boolean paramBoolean) {
    // Byte code:
    //   0: aload_0
    //   1: monitorenter
    //   2: aload_0
    //   3: getfield b : Ljava/util/ArrayList;
    //   6: invokevirtual iterator : ()Ljava/util/Iterator;
    //   9: astore_2
    //   10: aload_2
    //   11: invokeinterface hasNext : ()Z
    //   16: ifeq -> 43
    //   19: aload_2
    //   20: invokeinterface next : ()Ljava/lang/Object;
    //   25: checkcast com/blued/android/module/live_china/observer/LiveSetDataObserver$ILiveSetDataObserver
    //   28: astore_3
    //   29: aload_3
    //   30: ifnull -> 10
    //   33: aload_3
    //   34: iload_1
    //   35: invokeinterface b : (Z)V
    //   40: goto -> 10
    //   43: aload_0
    //   44: monitorexit
    //   45: return
    //   46: astore_2
    //   47: aload_0
    //   48: monitorexit
    //   49: aload_2
    //   50: athrow
    // Exception table:
    //   from	to	target	type
    //   2	10	46	finally
    //   10	29	46	finally
    //   33	40	46	finally
  }
  
  public void c() {
    // Byte code:
    //   0: aload_0
    //   1: monitorenter
    //   2: aload_0
    //   3: getfield b : Ljava/util/ArrayList;
    //   6: invokevirtual iterator : ()Ljava/util/Iterator;
    //   9: astore_1
    //   10: aload_1
    //   11: invokeinterface hasNext : ()Z
    //   16: ifeq -> 42
    //   19: aload_1
    //   20: invokeinterface next : ()Ljava/lang/Object;
    //   25: checkcast com/blued/android/module/live_china/observer/LiveSetDataObserver$ILiveSetDataObserver
    //   28: astore_2
    //   29: aload_2
    //   30: ifnull -> 10
    //   33: aload_2
    //   34: invokeinterface o : ()V
    //   39: goto -> 10
    //   42: aload_0
    //   43: monitorexit
    //   44: return
    //   45: astore_1
    //   46: aload_0
    //   47: monitorexit
    //   48: aload_1
    //   49: athrow
    // Exception table:
    //   from	to	target	type
    //   2	10	45	finally
    //   10	29	45	finally
    //   33	39	45	finally
  }
  
  public void c(int paramInt) {
    // Byte code:
    //   0: aload_0
    //   1: monitorenter
    //   2: aload_0
    //   3: getfield b : Ljava/util/ArrayList;
    //   6: invokevirtual iterator : ()Ljava/util/Iterator;
    //   9: astore_2
    //   10: aload_2
    //   11: invokeinterface hasNext : ()Z
    //   16: ifeq -> 43
    //   19: aload_2
    //   20: invokeinterface next : ()Ljava/lang/Object;
    //   25: checkcast com/blued/android/module/live_china/observer/LiveSetDataObserver$ILiveSetDataObserver
    //   28: astore_3
    //   29: aload_3
    //   30: ifnull -> 10
    //   33: aload_3
    //   34: iload_1
    //   35: invokeinterface d : (I)V
    //   40: goto -> 10
    //   43: aload_0
    //   44: monitorexit
    //   45: return
    //   46: astore_2
    //   47: aload_0
    //   48: monitorexit
    //   49: aload_2
    //   50: athrow
    // Exception table:
    //   from	to	target	type
    //   2	10	46	finally
    //   10	29	46	finally
    //   33	40	46	finally
  }
  
  public void c(ChattingModel paramChattingModel) {
    // Byte code:
    //   0: aload_0
    //   1: monitorenter
    //   2: aload_0
    //   3: getfield b : Ljava/util/ArrayList;
    //   6: invokevirtual iterator : ()Ljava/util/Iterator;
    //   9: astore_2
    //   10: aload_2
    //   11: invokeinterface hasNext : ()Z
    //   16: ifeq -> 43
    //   19: aload_2
    //   20: invokeinterface next : ()Ljava/lang/Object;
    //   25: checkcast com/blued/android/module/live_china/observer/LiveSetDataObserver$ILiveSetDataObserver
    //   28: astore_3
    //   29: aload_3
    //   30: ifnull -> 10
    //   33: aload_3
    //   34: aload_1
    //   35: invokeinterface b : (Lcom/blued/android/chat/model/ChattingModel;)V
    //   40: goto -> 10
    //   43: aload_0
    //   44: monitorexit
    //   45: return
    //   46: astore_1
    //   47: aload_0
    //   48: monitorexit
    //   49: aload_1
    //   50: athrow
    // Exception table:
    //   from	to	target	type
    //   2	10	46	finally
    //   10	29	46	finally
    //   33	40	46	finally
  }
  
  public void c(String paramString) {
    // Byte code:
    //   0: aload_0
    //   1: monitorenter
    //   2: aload_0
    //   3: getfield b : Ljava/util/ArrayList;
    //   6: invokevirtual iterator : ()Ljava/util/Iterator;
    //   9: astore_2
    //   10: aload_2
    //   11: invokeinterface hasNext : ()Z
    //   16: ifeq -> 43
    //   19: aload_2
    //   20: invokeinterface next : ()Ljava/lang/Object;
    //   25: checkcast com/blued/android/module/live_china/observer/LiveSetDataObserver$ILiveSetDataObserver
    //   28: astore_3
    //   29: aload_3
    //   30: ifnull -> 10
    //   33: aload_3
    //   34: aload_1
    //   35: invokeinterface e : (Ljava/lang/String;)V
    //   40: goto -> 10
    //   43: aload_0
    //   44: monitorexit
    //   45: return
    //   46: astore_1
    //   47: aload_0
    //   48: monitorexit
    //   49: aload_1
    //   50: athrow
    // Exception table:
    //   from	to	target	type
    //   2	10	46	finally
    //   10	29	46	finally
    //   33	40	46	finally
  }
  
  public void c(List<BadgeData> paramList) {
    // Byte code:
    //   0: aload_0
    //   1: monitorenter
    //   2: aload_0
    //   3: getfield b : Ljava/util/ArrayList;
    //   6: invokevirtual iterator : ()Ljava/util/Iterator;
    //   9: astore_2
    //   10: aload_2
    //   11: invokeinterface hasNext : ()Z
    //   16: ifeq -> 43
    //   19: aload_2
    //   20: invokeinterface next : ()Ljava/lang/Object;
    //   25: checkcast com/blued/android/module/live_china/observer/LiveSetDataObserver$ILiveSetDataObserver
    //   28: astore_3
    //   29: aload_3
    //   30: ifnull -> 10
    //   33: aload_3
    //   34: aload_1
    //   35: invokeinterface a : (Ljava/util/List;)V
    //   40: goto -> 10
    //   43: aload_0
    //   44: monitorexit
    //   45: return
    //   46: astore_1
    //   47: aload_0
    //   48: monitorexit
    //   49: aload_1
    //   50: athrow
    // Exception table:
    //   from	to	target	type
    //   2	10	46	finally
    //   10	29	46	finally
    //   33	40	46	finally
  }
  
  public void c(boolean paramBoolean) {
    // Byte code:
    //   0: aload_0
    //   1: monitorenter
    //   2: aload_0
    //   3: getfield b : Ljava/util/ArrayList;
    //   6: invokevirtual iterator : ()Ljava/util/Iterator;
    //   9: astore_2
    //   10: aload_2
    //   11: invokeinterface hasNext : ()Z
    //   16: ifeq -> 43
    //   19: aload_2
    //   20: invokeinterface next : ()Ljava/lang/Object;
    //   25: checkcast com/blued/android/module/live_china/observer/LiveSetDataObserver$ILiveSetDataObserver
    //   28: astore_3
    //   29: aload_3
    //   30: ifnull -> 10
    //   33: aload_3
    //   34: iload_1
    //   35: invokeinterface a : (Z)V
    //   40: goto -> 10
    //   43: aload_0
    //   44: monitorexit
    //   45: return
    //   46: astore_2
    //   47: aload_0
    //   48: monitorexit
    //   49: aload_2
    //   50: athrow
    // Exception table:
    //   from	to	target	type
    //   2	10	46	finally
    //   10	29	46	finally
    //   33	40	46	finally
  }
  
  public void d() {
    // Byte code:
    //   0: aload_0
    //   1: monitorenter
    //   2: aload_0
    //   3: getfield b : Ljava/util/ArrayList;
    //   6: invokevirtual iterator : ()Ljava/util/Iterator;
    //   9: astore_1
    //   10: aload_1
    //   11: invokeinterface hasNext : ()Z
    //   16: ifeq -> 42
    //   19: aload_1
    //   20: invokeinterface next : ()Ljava/lang/Object;
    //   25: checkcast com/blued/android/module/live_china/observer/LiveSetDataObserver$ILiveSetDataObserver
    //   28: astore_2
    //   29: aload_2
    //   30: ifnull -> 10
    //   33: aload_2
    //   34: invokeinterface p : ()V
    //   39: goto -> 10
    //   42: aload_0
    //   43: monitorexit
    //   44: return
    //   45: astore_1
    //   46: aload_0
    //   47: monitorexit
    //   48: aload_1
    //   49: athrow
    // Exception table:
    //   from	to	target	type
    //   2	10	45	finally
    //   10	29	45	finally
    //   33	39	45	finally
  }
  
  public void d(int paramInt) {
    // Byte code:
    //   0: aload_0
    //   1: monitorenter
    //   2: aload_0
    //   3: getfield b : Ljava/util/ArrayList;
    //   6: invokevirtual iterator : ()Ljava/util/Iterator;
    //   9: astore_2
    //   10: aload_2
    //   11: invokeinterface hasNext : ()Z
    //   16: ifeq -> 43
    //   19: aload_2
    //   20: invokeinterface next : ()Ljava/lang/Object;
    //   25: checkcast com/blued/android/module/live_china/observer/LiveSetDataObserver$ILiveSetDataObserver
    //   28: astore_3
    //   29: aload_3
    //   30: ifnull -> 10
    //   33: aload_3
    //   34: iload_1
    //   35: invokeinterface c : (I)V
    //   40: goto -> 10
    //   43: aload_0
    //   44: monitorexit
    //   45: return
    //   46: astore_2
    //   47: aload_0
    //   48: monitorexit
    //   49: aload_2
    //   50: athrow
    // Exception table:
    //   from	to	target	type
    //   2	10	46	finally
    //   10	29	46	finally
    //   33	40	46	finally
  }
  
  public void d(String paramString) {
    // Byte code:
    //   0: aload_0
    //   1: monitorenter
    //   2: aload_0
    //   3: getfield b : Ljava/util/ArrayList;
    //   6: invokevirtual iterator : ()Ljava/util/Iterator;
    //   9: astore_2
    //   10: aload_2
    //   11: invokeinterface hasNext : ()Z
    //   16: ifeq -> 43
    //   19: aload_2
    //   20: invokeinterface next : ()Ljava/lang/Object;
    //   25: checkcast com/blued/android/module/live_china/observer/LiveSetDataObserver$ILiveSetDataObserver
    //   28: astore_3
    //   29: aload_3
    //   30: ifnull -> 10
    //   33: aload_3
    //   34: aload_1
    //   35: invokeinterface a_ : (Ljava/lang/String;)V
    //   40: goto -> 10
    //   43: aload_0
    //   44: monitorexit
    //   45: return
    //   46: astore_1
    //   47: aload_0
    //   48: monitorexit
    //   49: aload_1
    //   50: athrow
    // Exception table:
    //   from	to	target	type
    //   2	10	46	finally
    //   10	29	46	finally
    //   33	40	46	finally
  }
  
  public void e() {
    // Byte code:
    //   0: aload_0
    //   1: monitorenter
    //   2: aload_0
    //   3: getfield b : Ljava/util/ArrayList;
    //   6: invokevirtual iterator : ()Ljava/util/Iterator;
    //   9: astore_1
    //   10: aload_1
    //   11: invokeinterface hasNext : ()Z
    //   16: ifeq -> 42
    //   19: aload_1
    //   20: invokeinterface next : ()Ljava/lang/Object;
    //   25: checkcast com/blued/android/module/live_china/observer/LiveSetDataObserver$ILiveSetDataObserver
    //   28: astore_2
    //   29: aload_2
    //   30: ifnull -> 10
    //   33: aload_2
    //   34: invokeinterface r : ()V
    //   39: goto -> 10
    //   42: aload_0
    //   43: monitorexit
    //   44: return
    //   45: astore_1
    //   46: aload_0
    //   47: monitorexit
    //   48: aload_1
    //   49: athrow
    // Exception table:
    //   from	to	target	type
    //   2	10	45	finally
    //   10	29	45	finally
    //   33	39	45	finally
  }
  
  public void e(int paramInt) {
    // Byte code:
    //   0: aload_0
    //   1: monitorenter
    //   2: aload_0
    //   3: getfield b : Ljava/util/ArrayList;
    //   6: invokevirtual iterator : ()Ljava/util/Iterator;
    //   9: astore_2
    //   10: aload_2
    //   11: invokeinterface hasNext : ()Z
    //   16: ifeq -> 43
    //   19: aload_2
    //   20: invokeinterface next : ()Ljava/lang/Object;
    //   25: checkcast com/blued/android/module/live_china/observer/LiveSetDataObserver$ILiveSetDataObserver
    //   28: astore_3
    //   29: aload_3
    //   30: ifnull -> 10
    //   33: aload_3
    //   34: iload_1
    //   35: invokeinterface b : (I)V
    //   40: goto -> 10
    //   43: aload_0
    //   44: monitorexit
    //   45: return
    //   46: astore_2
    //   47: aload_0
    //   48: monitorexit
    //   49: aload_2
    //   50: athrow
    // Exception table:
    //   from	to	target	type
    //   2	10	46	finally
    //   10	29	46	finally
    //   33	40	46	finally
  }
  
  public void e(String paramString) {
    // Byte code:
    //   0: aload_0
    //   1: monitorenter
    //   2: aload_0
    //   3: getfield b : Ljava/util/ArrayList;
    //   6: invokevirtual iterator : ()Ljava/util/Iterator;
    //   9: astore_2
    //   10: aload_2
    //   11: invokeinterface hasNext : ()Z
    //   16: ifeq -> 44
    //   19: aload_2
    //   20: invokeinterface next : ()Ljava/lang/Object;
    //   25: checkcast com/blued/android/module/live_china/observer/LiveSetDataObserver$ILiveSetDataObserver
    //   28: astore_3
    //   29: aload_3
    //   30: ifnull -> 10
    //   33: aload_3
    //   34: aload_1
    //   35: iconst_0
    //   36: invokeinterface a : (Ljava/lang/String;I)V
    //   41: goto -> 10
    //   44: aload_0
    //   45: monitorexit
    //   46: return
    //   47: astore_1
    //   48: aload_0
    //   49: monitorexit
    //   50: aload_1
    //   51: athrow
    // Exception table:
    //   from	to	target	type
    //   2	10	47	finally
    //   10	29	47	finally
    //   33	41	47	finally
  }
  
  public void f() {
    // Byte code:
    //   0: aload_0
    //   1: monitorenter
    //   2: aload_0
    //   3: getfield b : Ljava/util/ArrayList;
    //   6: invokevirtual iterator : ()Ljava/util/Iterator;
    //   9: astore_1
    //   10: aload_1
    //   11: invokeinterface hasNext : ()Z
    //   16: ifeq -> 42
    //   19: aload_1
    //   20: invokeinterface next : ()Ljava/lang/Object;
    //   25: checkcast com/blued/android/module/live_china/observer/LiveSetDataObserver$ILiveSetDataObserver
    //   28: astore_2
    //   29: aload_2
    //   30: ifnull -> 10
    //   33: aload_2
    //   34: invokeinterface s : ()V
    //   39: goto -> 10
    //   42: aload_0
    //   43: monitorexit
    //   44: return
    //   45: astore_1
    //   46: aload_0
    //   47: monitorexit
    //   48: aload_1
    //   49: athrow
    // Exception table:
    //   from	to	target	type
    //   2	10	45	finally
    //   10	29	45	finally
    //   33	39	45	finally
  }
  
  public void g() {
    // Byte code:
    //   0: aload_0
    //   1: monitorenter
    //   2: aload_0
    //   3: getfield b : Ljava/util/ArrayList;
    //   6: invokevirtual iterator : ()Ljava/util/Iterator;
    //   9: astore_1
    //   10: aload_1
    //   11: invokeinterface hasNext : ()Z
    //   16: ifeq -> 42
    //   19: aload_1
    //   20: invokeinterface next : ()Ljava/lang/Object;
    //   25: checkcast com/blued/android/module/live_china/observer/LiveSetDataObserver$ILiveSetDataObserver
    //   28: astore_2
    //   29: aload_2
    //   30: ifnull -> 10
    //   33: aload_2
    //   34: invokeinterface N : ()V
    //   39: goto -> 10
    //   42: aload_0
    //   43: monitorexit
    //   44: return
    //   45: astore_1
    //   46: aload_0
    //   47: monitorexit
    //   48: aload_1
    //   49: athrow
    // Exception table:
    //   from	to	target	type
    //   2	10	45	finally
    //   10	29	45	finally
    //   33	39	45	finally
  }
  
  public void h() {
    // Byte code:
    //   0: aload_0
    //   1: monitorenter
    //   2: aload_0
    //   3: getfield b : Ljava/util/ArrayList;
    //   6: invokevirtual iterator : ()Ljava/util/Iterator;
    //   9: astore_1
    //   10: aload_1
    //   11: invokeinterface hasNext : ()Z
    //   16: ifeq -> 42
    //   19: aload_1
    //   20: invokeinterface next : ()Ljava/lang/Object;
    //   25: checkcast com/blued/android/module/live_china/observer/LiveSetDataObserver$ILiveSetDataObserver
    //   28: astore_2
    //   29: aload_2
    //   30: ifnull -> 10
    //   33: aload_2
    //   34: invokeinterface O : ()V
    //   39: goto -> 10
    //   42: aload_0
    //   43: monitorexit
    //   44: return
    //   45: astore_1
    //   46: aload_0
    //   47: monitorexit
    //   48: aload_1
    //   49: athrow
    // Exception table:
    //   from	to	target	type
    //   2	10	45	finally
    //   10	29	45	finally
    //   33	39	45	finally
  }
  
  public void i() {
    // Byte code:
    //   0: aload_0
    //   1: monitorenter
    //   2: aload_0
    //   3: getfield b : Ljava/util/ArrayList;
    //   6: invokevirtual iterator : ()Ljava/util/Iterator;
    //   9: astore_1
    //   10: aload_1
    //   11: invokeinterface hasNext : ()Z
    //   16: ifeq -> 42
    //   19: aload_1
    //   20: invokeinterface next : ()Ljava/lang/Object;
    //   25: checkcast com/blued/android/module/live_china/observer/LiveSetDataObserver$ILiveSetDataObserver
    //   28: astore_2
    //   29: aload_2
    //   30: ifnull -> 10
    //   33: aload_2
    //   34: invokeinterface M : ()V
    //   39: goto -> 10
    //   42: aload_0
    //   43: monitorexit
    //   44: return
    //   45: astore_1
    //   46: aload_0
    //   47: monitorexit
    //   48: aload_1
    //   49: athrow
    // Exception table:
    //   from	to	target	type
    //   2	10	45	finally
    //   10	29	45	finally
    //   33	39	45	finally
  }
  
  public void j() {
    // Byte code:
    //   0: aload_0
    //   1: monitorenter
    //   2: aload_0
    //   3: getfield b : Ljava/util/ArrayList;
    //   6: invokevirtual iterator : ()Ljava/util/Iterator;
    //   9: astore_1
    //   10: aload_1
    //   11: invokeinterface hasNext : ()Z
    //   16: ifeq -> 42
    //   19: aload_1
    //   20: invokeinterface next : ()Ljava/lang/Object;
    //   25: checkcast com/blued/android/module/live_china/observer/LiveSetDataObserver$ILiveSetDataObserver
    //   28: astore_2
    //   29: aload_2
    //   30: ifnull -> 10
    //   33: aload_2
    //   34: invokeinterface H_ : ()V
    //   39: goto -> 10
    //   42: aload_0
    //   43: monitorexit
    //   44: return
    //   45: astore_1
    //   46: aload_0
    //   47: monitorexit
    //   48: aload_1
    //   49: athrow
    // Exception table:
    //   from	to	target	type
    //   2	10	45	finally
    //   10	29	45	finally
    //   33	39	45	finally
  }
  
  public void k() {
    // Byte code:
    //   0: aload_0
    //   1: monitorenter
    //   2: aload_0
    //   3: getfield b : Ljava/util/ArrayList;
    //   6: invokevirtual iterator : ()Ljava/util/Iterator;
    //   9: astore_1
    //   10: aload_1
    //   11: invokeinterface hasNext : ()Z
    //   16: ifeq -> 42
    //   19: aload_1
    //   20: invokeinterface next : ()Ljava/lang/Object;
    //   25: checkcast com/blued/android/module/live_china/observer/LiveSetDataObserver$ILiveSetDataObserver
    //   28: astore_2
    //   29: aload_2
    //   30: ifnull -> 10
    //   33: aload_2
    //   34: invokeinterface P : ()V
    //   39: goto -> 10
    //   42: aload_0
    //   43: monitorexit
    //   44: return
    //   45: astore_1
    //   46: aload_0
    //   47: monitorexit
    //   48: aload_1
    //   49: athrow
    // Exception table:
    //   from	to	target	type
    //   2	10	45	finally
    //   10	29	45	finally
    //   33	39	45	finally
  }
  
  public void l() {
    // Byte code:
    //   0: aload_0
    //   1: monitorenter
    //   2: aload_0
    //   3: getfield b : Ljava/util/ArrayList;
    //   6: invokevirtual iterator : ()Ljava/util/Iterator;
    //   9: astore_1
    //   10: aload_1
    //   11: invokeinterface hasNext : ()Z
    //   16: ifeq -> 42
    //   19: aload_1
    //   20: invokeinterface next : ()Ljava/lang/Object;
    //   25: checkcast com/blued/android/module/live_china/observer/LiveSetDataObserver$ILiveSetDataObserver
    //   28: astore_2
    //   29: aload_2
    //   30: ifnull -> 10
    //   33: aload_2
    //   34: invokeinterface S : ()V
    //   39: goto -> 10
    //   42: aload_0
    //   43: monitorexit
    //   44: return
    //   45: astore_1
    //   46: aload_0
    //   47: monitorexit
    //   48: aload_1
    //   49: athrow
    // Exception table:
    //   from	to	target	type
    //   2	10	45	finally
    //   10	29	45	finally
    //   33	39	45	finally
  }
  
  public void m() {
    // Byte code:
    //   0: aload_0
    //   1: monitorenter
    //   2: aload_0
    //   3: getfield b : Ljava/util/ArrayList;
    //   6: invokevirtual iterator : ()Ljava/util/Iterator;
    //   9: astore_1
    //   10: aload_1
    //   11: invokeinterface hasNext : ()Z
    //   16: ifeq -> 42
    //   19: aload_1
    //   20: invokeinterface next : ()Ljava/lang/Object;
    //   25: checkcast com/blued/android/module/live_china/observer/LiveSetDataObserver$ILiveSetDataObserver
    //   28: astore_2
    //   29: aload_2
    //   30: ifnull -> 10
    //   33: aload_2
    //   34: invokeinterface L : ()V
    //   39: goto -> 10
    //   42: aload_0
    //   43: monitorexit
    //   44: return
    //   45: astore_1
    //   46: aload_0
    //   47: monitorexit
    //   48: aload_1
    //   49: athrow
    // Exception table:
    //   from	to	target	type
    //   2	10	45	finally
    //   10	29	45	finally
    //   33	39	45	finally
  }
  
  public void n() {
    // Byte code:
    //   0: aload_0
    //   1: monitorenter
    //   2: aload_0
    //   3: getfield b : Ljava/util/ArrayList;
    //   6: invokevirtual iterator : ()Ljava/util/Iterator;
    //   9: astore_1
    //   10: aload_1
    //   11: invokeinterface hasNext : ()Z
    //   16: ifeq -> 42
    //   19: aload_1
    //   20: invokeinterface next : ()Ljava/lang/Object;
    //   25: checkcast com/blued/android/module/live_china/observer/LiveSetDataObserver$ILiveSetDataObserver
    //   28: astore_2
    //   29: aload_2
    //   30: ifnull -> 10
    //   33: aload_2
    //   34: invokeinterface K : ()V
    //   39: goto -> 10
    //   42: aload_0
    //   43: monitorexit
    //   44: return
    //   45: astore_1
    //   46: aload_0
    //   47: monitorexit
    //   48: aload_1
    //   49: athrow
    // Exception table:
    //   from	to	target	type
    //   2	10	45	finally
    //   10	29	45	finally
    //   33	39	45	finally
  }
  
  public void o() {
    // Byte code:
    //   0: aload_0
    //   1: monitorenter
    //   2: aload_0
    //   3: getfield b : Ljava/util/ArrayList;
    //   6: invokevirtual iterator : ()Ljava/util/Iterator;
    //   9: astore_1
    //   10: aload_1
    //   11: invokeinterface hasNext : ()Z
    //   16: ifeq -> 42
    //   19: aload_1
    //   20: invokeinterface next : ()Ljava/lang/Object;
    //   25: checkcast com/blued/android/module/live_china/observer/LiveSetDataObserver$ILiveSetDataObserver
    //   28: astore_2
    //   29: aload_2
    //   30: ifnull -> 10
    //   33: aload_2
    //   34: invokeinterface H : ()V
    //   39: goto -> 10
    //   42: aload_0
    //   43: monitorexit
    //   44: return
    //   45: astore_1
    //   46: aload_0
    //   47: monitorexit
    //   48: aload_1
    //   49: athrow
    // Exception table:
    //   from	to	target	type
    //   2	10	45	finally
    //   10	29	45	finally
    //   33	39	45	finally
  }
  
  public void p() {
    // Byte code:
    //   0: aload_0
    //   1: monitorenter
    //   2: aload_0
    //   3: getfield b : Ljava/util/ArrayList;
    //   6: invokevirtual iterator : ()Ljava/util/Iterator;
    //   9: astore_1
    //   10: aload_1
    //   11: invokeinterface hasNext : ()Z
    //   16: ifeq -> 42
    //   19: aload_1
    //   20: invokeinterface next : ()Ljava/lang/Object;
    //   25: checkcast com/blued/android/module/live_china/observer/LiveSetDataObserver$ILiveSetDataObserver
    //   28: astore_2
    //   29: aload_2
    //   30: ifnull -> 10
    //   33: aload_2
    //   34: invokeinterface G : ()V
    //   39: goto -> 10
    //   42: aload_0
    //   43: monitorexit
    //   44: return
    //   45: astore_1
    //   46: aload_0
    //   47: monitorexit
    //   48: aload_1
    //   49: athrow
    // Exception table:
    //   from	to	target	type
    //   2	10	45	finally
    //   10	29	45	finally
    //   33	39	45	finally
  }
  
  public void q() {
    // Byte code:
    //   0: aload_0
    //   1: monitorenter
    //   2: aload_0
    //   3: getfield b : Ljava/util/ArrayList;
    //   6: invokevirtual iterator : ()Ljava/util/Iterator;
    //   9: astore_1
    //   10: aload_1
    //   11: invokeinterface hasNext : ()Z
    //   16: ifeq -> 42
    //   19: aload_1
    //   20: invokeinterface next : ()Ljava/lang/Object;
    //   25: checkcast com/blued/android/module/live_china/observer/LiveSetDataObserver$ILiveSetDataObserver
    //   28: astore_2
    //   29: aload_2
    //   30: ifnull -> 10
    //   33: aload_2
    //   34: invokeinterface F : ()V
    //   39: goto -> 10
    //   42: aload_0
    //   43: monitorexit
    //   44: return
    //   45: astore_1
    //   46: aload_0
    //   47: monitorexit
    //   48: aload_1
    //   49: athrow
    // Exception table:
    //   from	to	target	type
    //   2	10	45	finally
    //   10	29	45	finally
    //   33	39	45	finally
  }
  
  public void r() {
    // Byte code:
    //   0: aload_0
    //   1: monitorenter
    //   2: aload_0
    //   3: getfield b : Ljava/util/ArrayList;
    //   6: invokevirtual iterator : ()Ljava/util/Iterator;
    //   9: astore_1
    //   10: aload_1
    //   11: invokeinterface hasNext : ()Z
    //   16: ifeq -> 42
    //   19: aload_1
    //   20: invokeinterface next : ()Ljava/lang/Object;
    //   25: checkcast com/blued/android/module/live_china/observer/LiveSetDataObserver$ILiveSetDataObserver
    //   28: astore_2
    //   29: aload_2
    //   30: ifnull -> 10
    //   33: aload_2
    //   34: invokeinterface E : ()V
    //   39: goto -> 10
    //   42: aload_0
    //   43: monitorexit
    //   44: return
    //   45: astore_1
    //   46: aload_0
    //   47: monitorexit
    //   48: aload_1
    //   49: athrow
    // Exception table:
    //   from	to	target	type
    //   2	10	45	finally
    //   10	29	45	finally
    //   33	39	45	finally
  }
  
  public void s() {
    // Byte code:
    //   0: aload_0
    //   1: monitorenter
    //   2: aload_0
    //   3: getfield b : Ljava/util/ArrayList;
    //   6: invokevirtual iterator : ()Ljava/util/Iterator;
    //   9: astore_1
    //   10: aload_1
    //   11: invokeinterface hasNext : ()Z
    //   16: ifeq -> 42
    //   19: aload_1
    //   20: invokeinterface next : ()Ljava/lang/Object;
    //   25: checkcast com/blued/android/module/live_china/observer/LiveSetDataObserver$ILiveSetDataObserver
    //   28: astore_2
    //   29: aload_2
    //   30: ifnull -> 10
    //   33: aload_2
    //   34: invokeinterface x : ()V
    //   39: goto -> 10
    //   42: aload_0
    //   43: monitorexit
    //   44: return
    //   45: astore_1
    //   46: aload_0
    //   47: monitorexit
    //   48: aload_1
    //   49: athrow
    // Exception table:
    //   from	to	target	type
    //   2	10	45	finally
    //   10	29	45	finally
    //   33	39	45	finally
  }
  
  public void t() {
    // Byte code:
    //   0: aload_0
    //   1: monitorenter
    //   2: aload_0
    //   3: getfield b : Ljava/util/ArrayList;
    //   6: invokevirtual iterator : ()Ljava/util/Iterator;
    //   9: astore_1
    //   10: aload_1
    //   11: invokeinterface hasNext : ()Z
    //   16: ifeq -> 42
    //   19: aload_1
    //   20: invokeinterface next : ()Ljava/lang/Object;
    //   25: checkcast com/blued/android/module/live_china/observer/LiveSetDataObserver$ILiveSetDataObserver
    //   28: astore_2
    //   29: aload_2
    //   30: ifnull -> 10
    //   33: aload_2
    //   34: invokeinterface K_ : ()V
    //   39: goto -> 10
    //   42: aload_0
    //   43: monitorexit
    //   44: return
    //   45: astore_1
    //   46: aload_0
    //   47: monitorexit
    //   48: aload_1
    //   49: athrow
    // Exception table:
    //   from	to	target	type
    //   2	10	45	finally
    //   10	29	45	finally
    //   33	39	45	finally
  }
  
  public void u() {
    // Byte code:
    //   0: aload_0
    //   1: monitorenter
    //   2: aload_0
    //   3: getfield b : Ljava/util/ArrayList;
    //   6: invokevirtual iterator : ()Ljava/util/Iterator;
    //   9: astore_1
    //   10: aload_1
    //   11: invokeinterface hasNext : ()Z
    //   16: ifeq -> 42
    //   19: aload_1
    //   20: invokeinterface next : ()Ljava/lang/Object;
    //   25: checkcast com/blued/android/module/live_china/observer/LiveSetDataObserver$ILiveSetDataObserver
    //   28: astore_2
    //   29: aload_2
    //   30: ifnull -> 10
    //   33: aload_2
    //   34: invokeinterface J_ : ()V
    //   39: goto -> 10
    //   42: aload_0
    //   43: monitorexit
    //   44: return
    //   45: astore_1
    //   46: aload_0
    //   47: monitorexit
    //   48: aload_1
    //   49: athrow
    // Exception table:
    //   from	to	target	type
    //   2	10	45	finally
    //   10	29	45	finally
    //   33	39	45	finally
  }
  
  public void v() {
    // Byte code:
    //   0: aload_0
    //   1: monitorenter
    //   2: aload_0
    //   3: getfield b : Ljava/util/ArrayList;
    //   6: invokevirtual iterator : ()Ljava/util/Iterator;
    //   9: astore_1
    //   10: aload_1
    //   11: invokeinterface hasNext : ()Z
    //   16: ifeq -> 42
    //   19: aload_1
    //   20: invokeinterface next : ()Ljava/lang/Object;
    //   25: checkcast com/blued/android/module/live_china/observer/LiveSetDataObserver$ILiveSetDataObserver
    //   28: astore_2
    //   29: aload_2
    //   30: ifnull -> 10
    //   33: aload_2
    //   34: invokeinterface E_ : ()V
    //   39: goto -> 10
    //   42: aload_0
    //   43: monitorexit
    //   44: return
    //   45: astore_1
    //   46: aload_0
    //   47: monitorexit
    //   48: aload_1
    //   49: athrow
    // Exception table:
    //   from	to	target	type
    //   2	10	45	finally
    //   10	29	45	finally
    //   33	39	45	finally
  }
  
  public void w() {
    // Byte code:
    //   0: aload_0
    //   1: monitorenter
    //   2: aload_0
    //   3: getfield b : Ljava/util/ArrayList;
    //   6: invokevirtual iterator : ()Ljava/util/Iterator;
    //   9: astore_1
    //   10: aload_1
    //   11: invokeinterface hasNext : ()Z
    //   16: ifeq -> 42
    //   19: aload_1
    //   20: invokeinterface next : ()Ljava/lang/Object;
    //   25: checkcast com/blued/android/module/live_china/observer/LiveSetDataObserver$ILiveSetDataObserver
    //   28: astore_2
    //   29: aload_2
    //   30: ifnull -> 10
    //   33: aload_2
    //   34: invokeinterface F_ : ()V
    //   39: goto -> 10
    //   42: aload_0
    //   43: monitorexit
    //   44: return
    //   45: astore_1
    //   46: aload_0
    //   47: monitorexit
    //   48: aload_1
    //   49: athrow
    // Exception table:
    //   from	to	target	type
    //   2	10	45	finally
    //   10	29	45	finally
    //   33	39	45	finally
  }
  
  public void x() {
    // Byte code:
    //   0: aload_0
    //   1: monitorenter
    //   2: aload_0
    //   3: getfield b : Ljava/util/ArrayList;
    //   6: invokevirtual iterator : ()Ljava/util/Iterator;
    //   9: astore_1
    //   10: aload_1
    //   11: invokeinterface hasNext : ()Z
    //   16: ifeq -> 42
    //   19: aload_1
    //   20: invokeinterface next : ()Ljava/lang/Object;
    //   25: checkcast com/blued/android/module/live_china/observer/LiveSetDataObserver$ILiveSetDataObserver
    //   28: astore_2
    //   29: aload_2
    //   30: ifnull -> 10
    //   33: aload_2
    //   34: invokeinterface G_ : ()V
    //   39: goto -> 10
    //   42: aload_0
    //   43: monitorexit
    //   44: return
    //   45: astore_1
    //   46: aload_0
    //   47: monitorexit
    //   48: aload_1
    //   49: athrow
    // Exception table:
    //   from	to	target	type
    //   2	10	45	finally
    //   10	29	45	finally
    //   33	39	45	finally
  }
  
  public static interface ILiveSetDataObserver {
    void E();
    
    void E_();
    
    void F();
    
    void F_();
    
    void G();
    
    void G_();
    
    void H();
    
    void H_();
    
    void I_();
    
    void J_();
    
    void K();
    
    void K_();
    
    void L();
    
    void M();
    
    void N();
    
    void O();
    
    void P();
    
    void S();
    
    void a(int param1Int1, int param1Int2, int param1Int3, float param1Float);
    
    void a(int param1Int1, int param1Int2, int param1Int3, int param1Int4);
    
    void a(long param1Long);
    
    void a(EditText param1EditText);
    
    void a(ChattingModel param1ChattingModel);
    
    void a(LiveGiftModel param1LiveGiftModel);
    
    void a(LiveHornModel param1LiveHornModel, boolean param1Boolean);
    
    void a(LiveMakeLoverFansModel param1LiveMakeLoverFansModel);
    
    void a(LiveRewardModel param1LiveRewardModel);
    
    void a(LiveRoomData param1LiveRoomData);
    
    void a(LiveRoomUserModel param1LiveRoomUserModel);
    
    void a(LiveZanExtraModel.Danmaku param1Danmaku);
    
    void a(String param1String, int param1Int);
    
    void a(String param1String1, String param1String2);
    
    void a(List<BadgeData> param1List);
    
    void a(boolean param1Boolean);
    
    void a(boolean param1Boolean1, boolean param1Boolean2);
    
    void a_(String param1String);
    
    void a_(List<String> param1List);
    
    void b(int param1Int);
    
    void b(long param1Long);
    
    void b(ChattingModel param1ChattingModel);
    
    void b(LiveGiftModel param1LiveGiftModel);
    
    void b(boolean param1Boolean);
    
    void b_(String param1String);
    
    void c(int param1Int);
    
    void c(ChattingModel param1ChattingModel);
    
    void c(List<LiveZanExtraModel.HotWords> param1List);
    
    void c(boolean param1Boolean);
    
    void d(int param1Int);
    
    void e(int param1Int);
    
    void e(String param1String);
    
    void f(int param1Int);
    
    void f(String param1String);
    
    void o();
    
    void p();
    
    void r();
    
    void s();
    
    void x();
  }
}


/* Location:              D:\code\BluedHook\classes.dex\com.soft.blued5032032-dex2jar.jar!\com\blued\android\module\live_china\observer\LiveSetDataObserver.class
 * Java compiler version: 6 (50.0)
 * JD-Core Version:       1.1.3
 */