package com.bytedance.sdk.a.b.a.b;

import com.bytedance.sdk.a.b.ac;
import java.util.LinkedHashSet;
import java.util.Set;

public final class d {
  private final Set<ac> a = new LinkedHashSet<ac>();
  
  public void a(ac paramac) {
    // Byte code:
    //   0: aload_0
    //   1: monitorenter
    //   2: aload_0
    //   3: getfield a : Ljava/util/Set;
    //   6: aload_1
    //   7: invokeinterface add : (Ljava/lang/Object;)Z
    //   12: pop
    //   13: aload_0
    //   14: monitorexit
    //   15: return
    //   16: astore_1
    //   17: aload_0
    //   18: monitorexit
    //   19: aload_1
    //   20: athrow
    // Exception table:
    //   from	to	target	type
    //   2	13	16	finally
  }
  
  public void b(ac paramac) {
    // Byte code:
    //   0: aload_0
    //   1: monitorenter
    //   2: aload_0
    //   3: getfield a : Ljava/util/Set;
    //   6: aload_1
    //   7: invokeinterface remove : (Ljava/lang/Object;)Z
    //   12: pop
    //   13: aload_0
    //   14: monitorexit
    //   15: return
    //   16: astore_1
    //   17: aload_0
    //   18: monitorexit
    //   19: aload_1
    //   20: athrow
    // Exception table:
    //   from	to	target	type
    //   2	13	16	finally
  }
  
  public boolean c(ac paramac) {
    // Byte code:
    //   0: aload_0
    //   1: monitorenter
    //   2: aload_0
    //   3: getfield a : Ljava/util/Set;
    //   6: aload_1
    //   7: invokeinterface contains : (Ljava/lang/Object;)Z
    //   12: istore_2
    //   13: aload_0
    //   14: monitorexit
    //   15: iload_2
    //   16: ireturn
    //   17: astore_1
    //   18: aload_0
    //   19: monitorexit
    //   20: aload_1
    //   21: athrow
    // Exception table:
    //   from	to	target	type
    //   2	13	17	finally
  }
}


/* Location:              D:\code\BluedHook\classes.dex\com.soft.blued7575468-dex2jar.jar!\com\bytedance\sdk\a\b\a\b\d.class
 * Java compiler version: 6 (50.0)
 * JD-Core Version:       1.1.3
 */