package com.amap.api.mapcore2d;

class am extends bn<bs> {
  void a(bs parambs) {
    // Byte code:
    //   0: aload_0
    //   1: monitorenter
    //   2: aload_0
    //   3: aload_1
    //   4: invokevirtual remove : (Ljava/lang/Object;)Z
    //   7: pop
    //   8: aload_0
    //   9: monitorexit
    //   10: return
    //   11: astore_1
    //   12: aload_0
    //   13: monitorexit
    //   14: aload_1
    //   15: athrow
    // Exception table:
    //   from	to	target	type
    //   2	8	11	finally
  }
  
  boolean b(bs parambs) {
    // Byte code:
    //   0: aload_0
    //   1: monitorenter
    //   2: aload_0
    //   3: aload_1
    //   4: invokevirtual contains : (Ljava/lang/Object;)Z
    //   7: istore_2
    //   8: iload_2
    //   9: iconst_1
    //   10: if_icmpne -> 17
    //   13: aload_0
    //   14: monitorexit
    //   15: iconst_0
    //   16: ireturn
    //   17: aload_0
    //   18: aload_1
    //   19: invokevirtual a : (Ljava/lang/Object;)V
    //   22: aload_0
    //   23: monitorexit
    //   24: iconst_1
    //   25: ireturn
    //   26: astore_1
    //   27: aload_0
    //   28: monitorexit
    //   29: aload_1
    //   30: athrow
    // Exception table:
    //   from	to	target	type
    //   2	8	26	finally
    //   17	22	26	finally
  }
}


/* Location:              D:\code\BluedHook\classes.dex\com.soft.blued7646532-dex2jar.jar!\com\amap\api\mapcore2d\am.class
 * Java compiler version: 6 (50.0)
 * JD-Core Version:       1.1.3
 */