package androidx.constraintlayout.solver.widgets;

import androidx.constraintlayout.solver.LinearSystem;

class Chain {
  static void a(ConstraintWidgetContainer paramConstraintWidgetContainer, LinearSystem paramLinearSystem, int paramInt) {
    byte b;
    int i;
    ChainHead[] arrayOfChainHead;
    int j = 0;
    if (paramInt == 0) {
      i = paramConstraintWidgetContainer.ak;
      arrayOfChainHead = paramConstraintWidgetContainer.an;
      b = 0;
    } else {
      b = 2;
      i = paramConstraintWidgetContainer.al;
      arrayOfChainHead = paramConstraintWidgetContainer.am;
    } 
    while (j < i) {
      ChainHead chainHead = arrayOfChainHead[j];
      chainHead.define();
      if (paramConstraintWidgetContainer.optimizeFor(4)) {
        if (!Optimizer.a(paramConstraintWidgetContainer, paramLinearSystem, paramInt, b, chainHead))
          a(paramConstraintWidgetContainer, paramLinearSystem, paramInt, b, chainHead); 
      } else {
        a(paramConstraintWidgetContainer, paramLinearSystem, paramInt, b, chainHead);
      } 
      j++;
    } 
  }
  
  static void a(ConstraintWidgetContainer paramConstraintWidgetContainer, LinearSystem paramLinearSystem, int paramInt1, int paramInt2, ChainHead paramChainHead) {
    // Byte code:
    //   0: aload #4
    //   2: getfield a : Landroidx/constraintlayout/solver/widgets/ConstraintWidget;
    //   5: astore #24
    //   7: aload #4
    //   9: getfield c : Landroidx/constraintlayout/solver/widgets/ConstraintWidget;
    //   12: astore #22
    //   14: aload #4
    //   16: getfield b : Landroidx/constraintlayout/solver/widgets/ConstraintWidget;
    //   19: astore #19
    //   21: aload #4
    //   23: getfield d : Landroidx/constraintlayout/solver/widgets/ConstraintWidget;
    //   26: astore #23
    //   28: aload #4
    //   30: getfield e : Landroidx/constraintlayout/solver/widgets/ConstraintWidget;
    //   33: astore #17
    //   35: aload #4
    //   37: getfield k : F
    //   40: fstore #5
    //   42: aload #4
    //   44: getfield f : Landroidx/constraintlayout/solver/widgets/ConstraintWidget;
    //   47: astore #16
    //   49: aload #4
    //   51: getfield g : Landroidx/constraintlayout/solver/widgets/ConstraintWidget;
    //   54: astore #16
    //   56: aload_0
    //   57: getfield A : [Landroidx/constraintlayout/solver/widgets/ConstraintWidget$DimensionBehaviour;
    //   60: iload_2
    //   61: aaload
    //   62: getstatic androidx/constraintlayout/solver/widgets/ConstraintWidget$DimensionBehaviour.WRAP_CONTENT : Landroidx/constraintlayout/solver/widgets/ConstraintWidget$DimensionBehaviour;
    //   65: if_acmpne -> 74
    //   68: iconst_1
    //   69: istore #12
    //   71: goto -> 77
    //   74: iconst_0
    //   75: istore #12
    //   77: iload_2
    //   78: ifne -> 136
    //   81: aload #17
    //   83: getfield W : I
    //   86: ifne -> 95
    //   89: iconst_1
    //   90: istore #8
    //   92: goto -> 98
    //   95: iconst_0
    //   96: istore #8
    //   98: aload #17
    //   100: getfield W : I
    //   103: iconst_1
    //   104: if_icmpne -> 113
    //   107: iconst_1
    //   108: istore #9
    //   110: goto -> 116
    //   113: iconst_0
    //   114: istore #9
    //   116: iload #8
    //   118: istore #10
    //   120: iload #9
    //   122: istore #11
    //   124: aload #17
    //   126: getfield W : I
    //   129: iconst_2
    //   130: if_icmpne -> 198
    //   133: goto -> 188
    //   136: aload #17
    //   138: getfield X : I
    //   141: ifne -> 150
    //   144: iconst_1
    //   145: istore #8
    //   147: goto -> 153
    //   150: iconst_0
    //   151: istore #8
    //   153: aload #17
    //   155: getfield X : I
    //   158: iconst_1
    //   159: if_icmpne -> 168
    //   162: iconst_1
    //   163: istore #9
    //   165: goto -> 171
    //   168: iconst_0
    //   169: istore #9
    //   171: iload #8
    //   173: istore #10
    //   175: iload #9
    //   177: istore #11
    //   179: aload #17
    //   181: getfield X : I
    //   184: iconst_2
    //   185: if_icmpne -> 198
    //   188: iconst_1
    //   189: istore #13
    //   191: iload #9
    //   193: istore #11
    //   195: goto -> 205
    //   198: iconst_0
    //   199: istore #13
    //   201: iload #10
    //   203: istore #8
    //   205: aload #24
    //   207: astore #18
    //   209: iconst_0
    //   210: istore #9
    //   212: iload #8
    //   214: istore #10
    //   216: iload #9
    //   218: istore #8
    //   220: aconst_null
    //   221: astore #20
    //   223: iload #8
    //   225: ifne -> 607
    //   228: aload #18
    //   230: getfield y : [Landroidx/constraintlayout/solver/widgets/ConstraintAnchor;
    //   233: iload_3
    //   234: aaload
    //   235: astore #16
    //   237: iload #12
    //   239: ifne -> 256
    //   242: iload #13
    //   244: ifeq -> 250
    //   247: goto -> 256
    //   250: iconst_4
    //   251: istore #9
    //   253: goto -> 259
    //   256: iconst_1
    //   257: istore #9
    //   259: aload #16
    //   261: invokevirtual getMargin : ()I
    //   264: istore #15
    //   266: iload #15
    //   268: istore #14
    //   270: aload #16
    //   272: getfield c : Landroidx/constraintlayout/solver/widgets/ConstraintAnchor;
    //   275: ifnull -> 302
    //   278: iload #15
    //   280: istore #14
    //   282: aload #18
    //   284: aload #24
    //   286: if_acmpeq -> 302
    //   289: iload #15
    //   291: aload #16
    //   293: getfield c : Landroidx/constraintlayout/solver/widgets/ConstraintAnchor;
    //   296: invokevirtual getMargin : ()I
    //   299: iadd
    //   300: istore #14
    //   302: iload #13
    //   304: ifeq -> 328
    //   307: aload #18
    //   309: aload #24
    //   311: if_acmpeq -> 328
    //   314: aload #18
    //   316: aload #19
    //   318: if_acmpeq -> 328
    //   321: bipush #6
    //   323: istore #9
    //   325: goto -> 344
    //   328: iload #10
    //   330: ifeq -> 344
    //   333: iload #12
    //   335: ifeq -> 344
    //   338: iconst_4
    //   339: istore #9
    //   341: goto -> 344
    //   344: aload #16
    //   346: getfield c : Landroidx/constraintlayout/solver/widgets/ConstraintAnchor;
    //   349: ifnull -> 428
    //   352: aload #18
    //   354: aload #19
    //   356: if_acmpne -> 382
    //   359: aload_1
    //   360: aload #16
    //   362: getfield e : Landroidx/constraintlayout/solver/SolverVariable;
    //   365: aload #16
    //   367: getfield c : Landroidx/constraintlayout/solver/widgets/ConstraintAnchor;
    //   370: getfield e : Landroidx/constraintlayout/solver/SolverVariable;
    //   373: iload #14
    //   375: iconst_5
    //   376: invokevirtual addGreaterThan : (Landroidx/constraintlayout/solver/SolverVariable;Landroidx/constraintlayout/solver/SolverVariable;II)V
    //   379: goto -> 403
    //   382: aload_1
    //   383: aload #16
    //   385: getfield e : Landroidx/constraintlayout/solver/SolverVariable;
    //   388: aload #16
    //   390: getfield c : Landroidx/constraintlayout/solver/widgets/ConstraintAnchor;
    //   393: getfield e : Landroidx/constraintlayout/solver/SolverVariable;
    //   396: iload #14
    //   398: bipush #6
    //   400: invokevirtual addGreaterThan : (Landroidx/constraintlayout/solver/SolverVariable;Landroidx/constraintlayout/solver/SolverVariable;II)V
    //   403: aload_1
    //   404: aload #16
    //   406: getfield e : Landroidx/constraintlayout/solver/SolverVariable;
    //   409: aload #16
    //   411: getfield c : Landroidx/constraintlayout/solver/widgets/ConstraintAnchor;
    //   414: getfield e : Landroidx/constraintlayout/solver/SolverVariable;
    //   417: iload #14
    //   419: iload #9
    //   421: invokevirtual addEquality : (Landroidx/constraintlayout/solver/SolverVariable;Landroidx/constraintlayout/solver/SolverVariable;II)Landroidx/constraintlayout/solver/ArrayRow;
    //   424: pop
    //   425: goto -> 428
    //   428: iload #12
    //   430: ifeq -> 513
    //   433: aload #18
    //   435: invokevirtual getVisibility : ()I
    //   438: bipush #8
    //   440: if_icmpeq -> 487
    //   443: aload #18
    //   445: getfield A : [Landroidx/constraintlayout/solver/widgets/ConstraintWidget$DimensionBehaviour;
    //   448: iload_2
    //   449: aaload
    //   450: getstatic androidx/constraintlayout/solver/widgets/ConstraintWidget$DimensionBehaviour.MATCH_CONSTRAINT : Landroidx/constraintlayout/solver/widgets/ConstraintWidget$DimensionBehaviour;
    //   453: if_acmpne -> 487
    //   456: aload_1
    //   457: aload #18
    //   459: getfield y : [Landroidx/constraintlayout/solver/widgets/ConstraintAnchor;
    //   462: iload_3
    //   463: iconst_1
    //   464: iadd
    //   465: aaload
    //   466: getfield e : Landroidx/constraintlayout/solver/SolverVariable;
    //   469: aload #18
    //   471: getfield y : [Landroidx/constraintlayout/solver/widgets/ConstraintAnchor;
    //   474: iload_3
    //   475: aaload
    //   476: getfield e : Landroidx/constraintlayout/solver/SolverVariable;
    //   479: iconst_0
    //   480: iconst_5
    //   481: invokevirtual addGreaterThan : (Landroidx/constraintlayout/solver/SolverVariable;Landroidx/constraintlayout/solver/SolverVariable;II)V
    //   484: goto -> 487
    //   487: aload_1
    //   488: aload #18
    //   490: getfield y : [Landroidx/constraintlayout/solver/widgets/ConstraintAnchor;
    //   493: iload_3
    //   494: aaload
    //   495: getfield e : Landroidx/constraintlayout/solver/SolverVariable;
    //   498: aload_0
    //   499: getfield y : [Landroidx/constraintlayout/solver/widgets/ConstraintAnchor;
    //   502: iload_3
    //   503: aaload
    //   504: getfield e : Landroidx/constraintlayout/solver/SolverVariable;
    //   507: iconst_0
    //   508: bipush #6
    //   510: invokevirtual addGreaterThan : (Landroidx/constraintlayout/solver/SolverVariable;Landroidx/constraintlayout/solver/SolverVariable;II)V
    //   513: aload #18
    //   515: getfield y : [Landroidx/constraintlayout/solver/widgets/ConstraintAnchor;
    //   518: iload_3
    //   519: iconst_1
    //   520: iadd
    //   521: aaload
    //   522: getfield c : Landroidx/constraintlayout/solver/widgets/ConstraintAnchor;
    //   525: astore #21
    //   527: aload #20
    //   529: astore #16
    //   531: aload #21
    //   533: ifnull -> 589
    //   536: aload #21
    //   538: getfield a : Landroidx/constraintlayout/solver/widgets/ConstraintWidget;
    //   541: astore #21
    //   543: aload #20
    //   545: astore #16
    //   547: aload #21
    //   549: getfield y : [Landroidx/constraintlayout/solver/widgets/ConstraintAnchor;
    //   552: iload_3
    //   553: aaload
    //   554: getfield c : Landroidx/constraintlayout/solver/widgets/ConstraintAnchor;
    //   557: ifnull -> 589
    //   560: aload #21
    //   562: getfield y : [Landroidx/constraintlayout/solver/widgets/ConstraintAnchor;
    //   565: iload_3
    //   566: aaload
    //   567: getfield c : Landroidx/constraintlayout/solver/widgets/ConstraintAnchor;
    //   570: getfield a : Landroidx/constraintlayout/solver/widgets/ConstraintWidget;
    //   573: aload #18
    //   575: if_acmpeq -> 585
    //   578: aload #20
    //   580: astore #16
    //   582: goto -> 589
    //   585: aload #21
    //   587: astore #16
    //   589: aload #16
    //   591: ifnull -> 601
    //   594: aload #16
    //   596: astore #18
    //   598: goto -> 604
    //   601: iconst_1
    //   602: istore #8
    //   604: goto -> 220
    //   607: aload #23
    //   609: ifnull -> 678
    //   612: aload #22
    //   614: getfield y : [Landroidx/constraintlayout/solver/widgets/ConstraintAnchor;
    //   617: astore #16
    //   619: iload_3
    //   620: iconst_1
    //   621: iadd
    //   622: istore #8
    //   624: aload #16
    //   626: iload #8
    //   628: aaload
    //   629: getfield c : Landroidx/constraintlayout/solver/widgets/ConstraintAnchor;
    //   632: ifnull -> 678
    //   635: aload #23
    //   637: getfield y : [Landroidx/constraintlayout/solver/widgets/ConstraintAnchor;
    //   640: iload #8
    //   642: aaload
    //   643: astore #16
    //   645: aload_1
    //   646: aload #16
    //   648: getfield e : Landroidx/constraintlayout/solver/SolverVariable;
    //   651: aload #22
    //   653: getfield y : [Landroidx/constraintlayout/solver/widgets/ConstraintAnchor;
    //   656: iload #8
    //   658: aaload
    //   659: getfield c : Landroidx/constraintlayout/solver/widgets/ConstraintAnchor;
    //   662: getfield e : Landroidx/constraintlayout/solver/SolverVariable;
    //   665: aload #16
    //   667: invokevirtual getMargin : ()I
    //   670: ineg
    //   671: iconst_5
    //   672: invokevirtual addLowerThan : (Landroidx/constraintlayout/solver/SolverVariable;Landroidx/constraintlayout/solver/SolverVariable;II)V
    //   675: goto -> 678
    //   678: iload #12
    //   680: ifeq -> 728
    //   683: aload_0
    //   684: getfield y : [Landroidx/constraintlayout/solver/widgets/ConstraintAnchor;
    //   687: astore_0
    //   688: iload_3
    //   689: iconst_1
    //   690: iadd
    //   691: istore #8
    //   693: aload_1
    //   694: aload_0
    //   695: iload #8
    //   697: aaload
    //   698: getfield e : Landroidx/constraintlayout/solver/SolverVariable;
    //   701: aload #22
    //   703: getfield y : [Landroidx/constraintlayout/solver/widgets/ConstraintAnchor;
    //   706: iload #8
    //   708: aaload
    //   709: getfield e : Landroidx/constraintlayout/solver/SolverVariable;
    //   712: aload #22
    //   714: getfield y : [Landroidx/constraintlayout/solver/widgets/ConstraintAnchor;
    //   717: iload #8
    //   719: aaload
    //   720: invokevirtual getMargin : ()I
    //   723: bipush #6
    //   725: invokevirtual addGreaterThan : (Landroidx/constraintlayout/solver/SolverVariable;Landroidx/constraintlayout/solver/SolverVariable;II)V
    //   728: aload #4
    //   730: getfield h : Ljava/util/ArrayList;
    //   733: astore_0
    //   734: aload_0
    //   735: ifnull -> 1030
    //   738: aload_0
    //   739: invokevirtual size : ()I
    //   742: istore #8
    //   744: iload #8
    //   746: iconst_1
    //   747: if_icmple -> 1030
    //   750: aload #4
    //   752: getfield l : Z
    //   755: ifeq -> 777
    //   758: aload #4
    //   760: getfield n : Z
    //   763: ifne -> 777
    //   766: aload #4
    //   768: getfield j : I
    //   771: i2f
    //   772: fstore #6
    //   774: goto -> 781
    //   777: fload #5
    //   779: fstore #6
    //   781: aconst_null
    //   782: astore #16
    //   784: iconst_0
    //   785: istore #9
    //   787: fconst_0
    //   788: fstore #7
    //   790: iload #9
    //   792: iload #8
    //   794: if_icmpge -> 1030
    //   797: aload_0
    //   798: iload #9
    //   800: invokevirtual get : (I)Ljava/lang/Object;
    //   803: checkcast androidx/constraintlayout/solver/widgets/ConstraintWidget
    //   806: astore #18
    //   808: aload #18
    //   810: getfield aa : [F
    //   813: iload_2
    //   814: faload
    //   815: fstore #5
    //   817: fload #5
    //   819: fconst_0
    //   820: fcmpg
    //   821: ifge -> 870
    //   824: aload #4
    //   826: getfield n : Z
    //   829: ifeq -> 864
    //   832: aload_1
    //   833: aload #18
    //   835: getfield y : [Landroidx/constraintlayout/solver/widgets/ConstraintAnchor;
    //   838: iload_3
    //   839: iconst_1
    //   840: iadd
    //   841: aaload
    //   842: getfield e : Landroidx/constraintlayout/solver/SolverVariable;
    //   845: aload #18
    //   847: getfield y : [Landroidx/constraintlayout/solver/widgets/ConstraintAnchor;
    //   850: iload_3
    //   851: aaload
    //   852: getfield e : Landroidx/constraintlayout/solver/SolverVariable;
    //   855: iconst_0
    //   856: iconst_4
    //   857: invokevirtual addEquality : (Landroidx/constraintlayout/solver/SolverVariable;Landroidx/constraintlayout/solver/SolverVariable;II)Landroidx/constraintlayout/solver/ArrayRow;
    //   860: pop
    //   861: goto -> 907
    //   864: fconst_1
    //   865: fstore #5
    //   867: goto -> 870
    //   870: fload #5
    //   872: fconst_0
    //   873: fcmpl
    //   874: ifne -> 914
    //   877: aload_1
    //   878: aload #18
    //   880: getfield y : [Landroidx/constraintlayout/solver/widgets/ConstraintAnchor;
    //   883: iload_3
    //   884: iconst_1
    //   885: iadd
    //   886: aaload
    //   887: getfield e : Landroidx/constraintlayout/solver/SolverVariable;
    //   890: aload #18
    //   892: getfield y : [Landroidx/constraintlayout/solver/widgets/ConstraintAnchor;
    //   895: iload_3
    //   896: aaload
    //   897: getfield e : Landroidx/constraintlayout/solver/SolverVariable;
    //   900: iconst_0
    //   901: bipush #6
    //   903: invokevirtual addEquality : (Landroidx/constraintlayout/solver/SolverVariable;Landroidx/constraintlayout/solver/SolverVariable;II)Landroidx/constraintlayout/solver/ArrayRow;
    //   906: pop
    //   907: fload #7
    //   909: fstore #5
    //   911: goto -> 1017
    //   914: aload #16
    //   916: ifnull -> 1013
    //   919: aload #16
    //   921: getfield y : [Landroidx/constraintlayout/solver/widgets/ConstraintAnchor;
    //   924: iload_3
    //   925: aaload
    //   926: getfield e : Landroidx/constraintlayout/solver/SolverVariable;
    //   929: astore #20
    //   931: aload #16
    //   933: getfield y : [Landroidx/constraintlayout/solver/widgets/ConstraintAnchor;
    //   936: astore #16
    //   938: iload_3
    //   939: iconst_1
    //   940: iadd
    //   941: istore #12
    //   943: aload #16
    //   945: iload #12
    //   947: aaload
    //   948: getfield e : Landroidx/constraintlayout/solver/SolverVariable;
    //   951: astore #16
    //   953: aload #18
    //   955: getfield y : [Landroidx/constraintlayout/solver/widgets/ConstraintAnchor;
    //   958: iload_3
    //   959: aaload
    //   960: getfield e : Landroidx/constraintlayout/solver/SolverVariable;
    //   963: astore #21
    //   965: aload #18
    //   967: getfield y : [Landroidx/constraintlayout/solver/widgets/ConstraintAnchor;
    //   970: iload #12
    //   972: aaload
    //   973: getfield e : Landroidx/constraintlayout/solver/SolverVariable;
    //   976: astore #25
    //   978: aload_1
    //   979: invokevirtual createRow : ()Landroidx/constraintlayout/solver/ArrayRow;
    //   982: astore #26
    //   984: aload #26
    //   986: fload #7
    //   988: fload #6
    //   990: fload #5
    //   992: aload #20
    //   994: aload #16
    //   996: aload #21
    //   998: aload #25
    //   1000: invokevirtual createRowEqualMatchDimensions : (FFFLandroidx/constraintlayout/solver/SolverVariable;Landroidx/constraintlayout/solver/SolverVariable;Landroidx/constraintlayout/solver/SolverVariable;Landroidx/constraintlayout/solver/SolverVariable;)Landroidx/constraintlayout/solver/ArrayRow;
    //   1003: pop
    //   1004: aload_1
    //   1005: aload #26
    //   1007: invokevirtual addConstraint : (Landroidx/constraintlayout/solver/ArrayRow;)V
    //   1010: goto -> 1013
    //   1013: aload #18
    //   1015: astore #16
    //   1017: iload #9
    //   1019: iconst_1
    //   1020: iadd
    //   1021: istore #9
    //   1023: fload #5
    //   1025: fstore #7
    //   1027: goto -> 790
    //   1030: aload #19
    //   1032: ifnull -> 1236
    //   1035: aload #19
    //   1037: aload #23
    //   1039: if_acmpeq -> 1047
    //   1042: iload #13
    //   1044: ifeq -> 1236
    //   1047: aload #24
    //   1049: getfield y : [Landroidx/constraintlayout/solver/widgets/ConstraintAnchor;
    //   1052: iload_3
    //   1053: aaload
    //   1054: astore #16
    //   1056: aload #22
    //   1058: getfield y : [Landroidx/constraintlayout/solver/widgets/ConstraintAnchor;
    //   1061: astore_0
    //   1062: iload_3
    //   1063: iconst_1
    //   1064: iadd
    //   1065: istore #8
    //   1067: aload_0
    //   1068: iload #8
    //   1070: aaload
    //   1071: astore #18
    //   1073: aload #24
    //   1075: getfield y : [Landroidx/constraintlayout/solver/widgets/ConstraintAnchor;
    //   1078: iload_3
    //   1079: aaload
    //   1080: getfield c : Landroidx/constraintlayout/solver/widgets/ConstraintAnchor;
    //   1083: ifnull -> 1103
    //   1086: aload #24
    //   1088: getfield y : [Landroidx/constraintlayout/solver/widgets/ConstraintAnchor;
    //   1091: iload_3
    //   1092: aaload
    //   1093: getfield c : Landroidx/constraintlayout/solver/widgets/ConstraintAnchor;
    //   1096: getfield e : Landroidx/constraintlayout/solver/SolverVariable;
    //   1099: astore_0
    //   1100: goto -> 1105
    //   1103: aconst_null
    //   1104: astore_0
    //   1105: aload #22
    //   1107: getfield y : [Landroidx/constraintlayout/solver/widgets/ConstraintAnchor;
    //   1110: iload #8
    //   1112: aaload
    //   1113: getfield c : Landroidx/constraintlayout/solver/widgets/ConstraintAnchor;
    //   1116: ifnull -> 1138
    //   1119: aload #22
    //   1121: getfield y : [Landroidx/constraintlayout/solver/widgets/ConstraintAnchor;
    //   1124: iload #8
    //   1126: aaload
    //   1127: getfield c : Landroidx/constraintlayout/solver/widgets/ConstraintAnchor;
    //   1130: getfield e : Landroidx/constraintlayout/solver/SolverVariable;
    //   1133: astore #4
    //   1135: goto -> 1141
    //   1138: aconst_null
    //   1139: astore #4
    //   1141: aload #19
    //   1143: aload #23
    //   1145: if_acmpne -> 1167
    //   1148: aload #19
    //   1150: getfield y : [Landroidx/constraintlayout/solver/widgets/ConstraintAnchor;
    //   1153: iload_3
    //   1154: aaload
    //   1155: astore #16
    //   1157: aload #19
    //   1159: getfield y : [Landroidx/constraintlayout/solver/widgets/ConstraintAnchor;
    //   1162: iload #8
    //   1164: aaload
    //   1165: astore #18
    //   1167: aload_0
    //   1168: ifnull -> 2315
    //   1171: aload #4
    //   1173: ifnull -> 2315
    //   1176: iload_2
    //   1177: ifne -> 1190
    //   1180: aload #17
    //   1182: getfield P : F
    //   1185: fstore #5
    //   1187: goto -> 1197
    //   1190: aload #17
    //   1192: getfield Q : F
    //   1195: fstore #5
    //   1197: aload #16
    //   1199: invokevirtual getMargin : ()I
    //   1202: istore_2
    //   1203: aload #18
    //   1205: invokevirtual getMargin : ()I
    //   1208: istore #8
    //   1210: aload_1
    //   1211: aload #16
    //   1213: getfield e : Landroidx/constraintlayout/solver/SolverVariable;
    //   1216: aload_0
    //   1217: iload_2
    //   1218: fload #5
    //   1220: aload #4
    //   1222: aload #18
    //   1224: getfield e : Landroidx/constraintlayout/solver/SolverVariable;
    //   1227: iload #8
    //   1229: iconst_5
    //   1230: invokevirtual addCentering : (Landroidx/constraintlayout/solver/SolverVariable;Landroidx/constraintlayout/solver/SolverVariable;IFLandroidx/constraintlayout/solver/SolverVariable;Landroidx/constraintlayout/solver/SolverVariable;II)V
    //   1233: goto -> 2315
    //   1236: iload #10
    //   1238: ifeq -> 1736
    //   1241: aload #19
    //   1243: ifnull -> 1736
    //   1246: aload #4
    //   1248: getfield j : I
    //   1251: ifle -> 1273
    //   1254: aload #4
    //   1256: getfield i : I
    //   1259: aload #4
    //   1261: getfield j : I
    //   1264: if_icmpne -> 1273
    //   1267: iconst_1
    //   1268: istore #12
    //   1270: goto -> 1276
    //   1273: iconst_0
    //   1274: istore #12
    //   1276: aload #19
    //   1278: astore #4
    //   1280: aload #4
    //   1282: astore #18
    //   1284: aload #4
    //   1286: ifnull -> 2315
    //   1289: aload #4
    //   1291: getfield ac : [Landroidx/constraintlayout/solver/widgets/ConstraintWidget;
    //   1294: iload_2
    //   1295: aaload
    //   1296: astore #16
    //   1298: aload #16
    //   1300: ifnull -> 1325
    //   1303: aload #16
    //   1305: invokevirtual getVisibility : ()I
    //   1308: bipush #8
    //   1310: if_icmpne -> 1325
    //   1313: aload #16
    //   1315: getfield ac : [Landroidx/constraintlayout/solver/widgets/ConstraintWidget;
    //   1318: iload_2
    //   1319: aaload
    //   1320: astore #16
    //   1322: goto -> 1298
    //   1325: aload #16
    //   1327: ifnonnull -> 1343
    //   1330: aload #4
    //   1332: aload #23
    //   1334: if_acmpne -> 1340
    //   1337: goto -> 1343
    //   1340: goto -> 1715
    //   1343: aload #4
    //   1345: getfield y : [Landroidx/constraintlayout/solver/widgets/ConstraintAnchor;
    //   1348: iload_3
    //   1349: aaload
    //   1350: astore #20
    //   1352: aload #20
    //   1354: getfield e : Landroidx/constraintlayout/solver/SolverVariable;
    //   1357: astore #26
    //   1359: aload #20
    //   1361: getfield c : Landroidx/constraintlayout/solver/widgets/ConstraintAnchor;
    //   1364: ifnull -> 1380
    //   1367: aload #20
    //   1369: getfield c : Landroidx/constraintlayout/solver/widgets/ConstraintAnchor;
    //   1372: getfield e : Landroidx/constraintlayout/solver/SolverVariable;
    //   1375: astore #17
    //   1377: goto -> 1383
    //   1380: aconst_null
    //   1381: astore #17
    //   1383: aload #18
    //   1385: aload #4
    //   1387: if_acmpeq -> 1406
    //   1390: aload #18
    //   1392: getfield y : [Landroidx/constraintlayout/solver/widgets/ConstraintAnchor;
    //   1395: iload_3
    //   1396: iconst_1
    //   1397: iadd
    //   1398: aaload
    //   1399: getfield e : Landroidx/constraintlayout/solver/SolverVariable;
    //   1402: astore_0
    //   1403: goto -> 1458
    //   1406: aload #17
    //   1408: astore_0
    //   1409: aload #4
    //   1411: aload #19
    //   1413: if_acmpne -> 1458
    //   1416: aload #17
    //   1418: astore_0
    //   1419: aload #18
    //   1421: aload #4
    //   1423: if_acmpne -> 1458
    //   1426: aload #24
    //   1428: getfield y : [Landroidx/constraintlayout/solver/widgets/ConstraintAnchor;
    //   1431: iload_3
    //   1432: aaload
    //   1433: getfield c : Landroidx/constraintlayout/solver/widgets/ConstraintAnchor;
    //   1436: ifnull -> 1456
    //   1439: aload #24
    //   1441: getfield y : [Landroidx/constraintlayout/solver/widgets/ConstraintAnchor;
    //   1444: iload_3
    //   1445: aaload
    //   1446: getfield c : Landroidx/constraintlayout/solver/widgets/ConstraintAnchor;
    //   1449: getfield e : Landroidx/constraintlayout/solver/SolverVariable;
    //   1452: astore_0
    //   1453: goto -> 1458
    //   1456: aconst_null
    //   1457: astore_0
    //   1458: aload #20
    //   1460: invokevirtual getMargin : ()I
    //   1463: istore #13
    //   1465: aload #4
    //   1467: getfield y : [Landroidx/constraintlayout/solver/widgets/ConstraintAnchor;
    //   1470: astore #17
    //   1472: iload_3
    //   1473: iconst_1
    //   1474: iadd
    //   1475: istore #14
    //   1477: aload #17
    //   1479: iload #14
    //   1481: aaload
    //   1482: invokevirtual getMargin : ()I
    //   1485: istore #9
    //   1487: aload #16
    //   1489: ifnull -> 1524
    //   1492: aload #16
    //   1494: getfield y : [Landroidx/constraintlayout/solver/widgets/ConstraintAnchor;
    //   1497: iload_3
    //   1498: aaload
    //   1499: astore #17
    //   1501: aload #17
    //   1503: getfield e : Landroidx/constraintlayout/solver/SolverVariable;
    //   1506: astore #20
    //   1508: aload #4
    //   1510: getfield y : [Landroidx/constraintlayout/solver/widgets/ConstraintAnchor;
    //   1513: iload #14
    //   1515: aaload
    //   1516: getfield e : Landroidx/constraintlayout/solver/SolverVariable;
    //   1519: astore #21
    //   1521: goto -> 1576
    //   1524: aload #22
    //   1526: getfield y : [Landroidx/constraintlayout/solver/widgets/ConstraintAnchor;
    //   1529: iload #14
    //   1531: aaload
    //   1532: getfield c : Landroidx/constraintlayout/solver/widgets/ConstraintAnchor;
    //   1535: astore #25
    //   1537: aload #25
    //   1539: ifnull -> 1552
    //   1542: aload #25
    //   1544: getfield e : Landroidx/constraintlayout/solver/SolverVariable;
    //   1547: astore #17
    //   1549: goto -> 1555
    //   1552: aconst_null
    //   1553: astore #17
    //   1555: aload #4
    //   1557: getfield y : [Landroidx/constraintlayout/solver/widgets/ConstraintAnchor;
    //   1560: iload #14
    //   1562: aaload
    //   1563: getfield e : Landroidx/constraintlayout/solver/SolverVariable;
    //   1566: astore #21
    //   1568: aload #17
    //   1570: astore #20
    //   1572: aload #25
    //   1574: astore #17
    //   1576: iload #9
    //   1578: istore #8
    //   1580: aload #17
    //   1582: ifnull -> 1595
    //   1585: iload #9
    //   1587: aload #17
    //   1589: invokevirtual getMargin : ()I
    //   1592: iadd
    //   1593: istore #8
    //   1595: iload #13
    //   1597: istore #9
    //   1599: aload #18
    //   1601: ifnull -> 1620
    //   1604: iload #13
    //   1606: aload #18
    //   1608: getfield y : [Landroidx/constraintlayout/solver/widgets/ConstraintAnchor;
    //   1611: iload #14
    //   1613: aaload
    //   1614: invokevirtual getMargin : ()I
    //   1617: iadd
    //   1618: istore #9
    //   1620: aload #26
    //   1622: ifnull -> 1340
    //   1625: aload_0
    //   1626: ifnull -> 1340
    //   1629: aload #20
    //   1631: ifnull -> 1340
    //   1634: aload #21
    //   1636: ifnull -> 1340
    //   1639: aload #4
    //   1641: aload #19
    //   1643: if_acmpne -> 1658
    //   1646: aload #19
    //   1648: getfield y : [Landroidx/constraintlayout/solver/widgets/ConstraintAnchor;
    //   1651: iload_3
    //   1652: aaload
    //   1653: invokevirtual getMargin : ()I
    //   1656: istore #9
    //   1658: aload #4
    //   1660: aload #23
    //   1662: if_acmpne -> 1681
    //   1665: aload #23
    //   1667: getfield y : [Landroidx/constraintlayout/solver/widgets/ConstraintAnchor;
    //   1670: iload #14
    //   1672: aaload
    //   1673: invokevirtual getMargin : ()I
    //   1676: istore #8
    //   1678: goto -> 1681
    //   1681: iload #12
    //   1683: ifeq -> 1693
    //   1686: bipush #6
    //   1688: istore #13
    //   1690: goto -> 1696
    //   1693: iconst_4
    //   1694: istore #13
    //   1696: aload_1
    //   1697: aload #26
    //   1699: aload_0
    //   1700: iload #9
    //   1702: ldc 0.5
    //   1704: aload #20
    //   1706: aload #21
    //   1708: iload #8
    //   1710: iload #13
    //   1712: invokevirtual addCentering : (Landroidx/constraintlayout/solver/SolverVariable;Landroidx/constraintlayout/solver/SolverVariable;IFLandroidx/constraintlayout/solver/SolverVariable;Landroidx/constraintlayout/solver/SolverVariable;II)V
    //   1715: aload #4
    //   1717: invokevirtual getVisibility : ()I
    //   1720: bipush #8
    //   1722: if_icmpeq -> 1729
    //   1725: aload #4
    //   1727: astore #18
    //   1729: aload #16
    //   1731: astore #4
    //   1733: goto -> 1284
    //   1736: iload #11
    //   1738: ifeq -> 2315
    //   1741: aload #19
    //   1743: ifnull -> 2315
    //   1746: aload #4
    //   1748: getfield j : I
    //   1751: ifle -> 1773
    //   1754: aload #4
    //   1756: getfield i : I
    //   1759: aload #4
    //   1761: getfield j : I
    //   1764: if_icmpne -> 1773
    //   1767: iconst_1
    //   1768: istore #8
    //   1770: goto -> 1776
    //   1773: iconst_0
    //   1774: istore #8
    //   1776: aload #19
    //   1778: astore #4
    //   1780: aload #4
    //   1782: astore #16
    //   1784: aload #4
    //   1786: ifnull -> 2155
    //   1789: aload #4
    //   1791: getfield ac : [Landroidx/constraintlayout/solver/widgets/ConstraintWidget;
    //   1794: iload_2
    //   1795: aaload
    //   1796: astore_0
    //   1797: aload_0
    //   1798: ifnull -> 1820
    //   1801: aload_0
    //   1802: invokevirtual getVisibility : ()I
    //   1805: bipush #8
    //   1807: if_icmpne -> 1820
    //   1810: aload_0
    //   1811: getfield ac : [Landroidx/constraintlayout/solver/widgets/ConstraintWidget;
    //   1814: iload_2
    //   1815: aaload
    //   1816: astore_0
    //   1817: goto -> 1797
    //   1820: aload #4
    //   1822: aload #19
    //   1824: if_acmpeq -> 2128
    //   1827: aload #4
    //   1829: aload #23
    //   1831: if_acmpeq -> 2128
    //   1834: aload_0
    //   1835: ifnull -> 2128
    //   1838: aload_0
    //   1839: aload #23
    //   1841: if_acmpne -> 1849
    //   1844: aconst_null
    //   1845: astore_0
    //   1846: goto -> 1849
    //   1849: aload #4
    //   1851: getfield y : [Landroidx/constraintlayout/solver/widgets/ConstraintAnchor;
    //   1854: iload_3
    //   1855: aaload
    //   1856: astore #17
    //   1858: aload #17
    //   1860: getfield e : Landroidx/constraintlayout/solver/SolverVariable;
    //   1863: astore #25
    //   1865: aload #17
    //   1867: getfield c : Landroidx/constraintlayout/solver/widgets/ConstraintAnchor;
    //   1870: ifnull -> 1883
    //   1873: aload #17
    //   1875: getfield c : Landroidx/constraintlayout/solver/widgets/ConstraintAnchor;
    //   1878: getfield e : Landroidx/constraintlayout/solver/SolverVariable;
    //   1881: astore #18
    //   1883: aload #16
    //   1885: getfield y : [Landroidx/constraintlayout/solver/widgets/ConstraintAnchor;
    //   1888: astore #18
    //   1890: iload_3
    //   1891: iconst_1
    //   1892: iadd
    //   1893: istore #14
    //   1895: aload #18
    //   1897: iload #14
    //   1899: aaload
    //   1900: getfield e : Landroidx/constraintlayout/solver/SolverVariable;
    //   1903: astore #26
    //   1905: aload #17
    //   1907: invokevirtual getMargin : ()I
    //   1910: istore #13
    //   1912: aload #4
    //   1914: getfield y : [Landroidx/constraintlayout/solver/widgets/ConstraintAnchor;
    //   1917: iload #14
    //   1919: aaload
    //   1920: invokevirtual getMargin : ()I
    //   1923: istore #12
    //   1925: aload_0
    //   1926: ifnull -> 1971
    //   1929: aload_0
    //   1930: getfield y : [Landroidx/constraintlayout/solver/widgets/ConstraintAnchor;
    //   1933: iload_3
    //   1934: aaload
    //   1935: astore #18
    //   1937: aload #18
    //   1939: getfield e : Landroidx/constraintlayout/solver/SolverVariable;
    //   1942: astore #20
    //   1944: aload #18
    //   1946: getfield c : Landroidx/constraintlayout/solver/widgets/ConstraintAnchor;
    //   1949: ifnull -> 1965
    //   1952: aload #18
    //   1954: getfield c : Landroidx/constraintlayout/solver/widgets/ConstraintAnchor;
    //   1957: getfield e : Landroidx/constraintlayout/solver/SolverVariable;
    //   1960: astore #17
    //   1962: goto -> 2023
    //   1965: aconst_null
    //   1966: astore #17
    //   1968: goto -> 2023
    //   1971: aload #4
    //   1973: getfield y : [Landroidx/constraintlayout/solver/widgets/ConstraintAnchor;
    //   1976: iload #14
    //   1978: aaload
    //   1979: getfield c : Landroidx/constraintlayout/solver/widgets/ConstraintAnchor;
    //   1982: astore #21
    //   1984: aload #21
    //   1986: ifnull -> 1999
    //   1989: aload #21
    //   1991: getfield e : Landroidx/constraintlayout/solver/SolverVariable;
    //   1994: astore #18
    //   1996: goto -> 2002
    //   1999: aconst_null
    //   2000: astore #18
    //   2002: aload #4
    //   2004: getfield y : [Landroidx/constraintlayout/solver/widgets/ConstraintAnchor;
    //   2007: iload #14
    //   2009: aaload
    //   2010: getfield e : Landroidx/constraintlayout/solver/SolverVariable;
    //   2013: astore #17
    //   2015: aload #18
    //   2017: astore #20
    //   2019: aload #21
    //   2021: astore #18
    //   2023: iload #12
    //   2025: istore #9
    //   2027: aload #18
    //   2029: ifnull -> 2042
    //   2032: iload #12
    //   2034: aload #18
    //   2036: invokevirtual getMargin : ()I
    //   2039: iadd
    //   2040: istore #9
    //   2042: iload #13
    //   2044: istore #12
    //   2046: aload #16
    //   2048: ifnull -> 2067
    //   2051: iload #13
    //   2053: aload #16
    //   2055: getfield y : [Landroidx/constraintlayout/solver/widgets/ConstraintAnchor;
    //   2058: iload #14
    //   2060: aaload
    //   2061: invokevirtual getMargin : ()I
    //   2064: iadd
    //   2065: istore #12
    //   2067: iload #8
    //   2069: ifeq -> 2079
    //   2072: bipush #6
    //   2074: istore #13
    //   2076: goto -> 2082
    //   2079: iconst_4
    //   2080: istore #13
    //   2082: aload #25
    //   2084: ifnull -> 2125
    //   2087: aload #26
    //   2089: ifnull -> 2125
    //   2092: aload #20
    //   2094: ifnull -> 2125
    //   2097: aload #17
    //   2099: ifnull -> 2125
    //   2102: aload_1
    //   2103: aload #25
    //   2105: aload #26
    //   2107: iload #12
    //   2109: ldc 0.5
    //   2111: aload #20
    //   2113: aload #17
    //   2115: iload #9
    //   2117: iload #13
    //   2119: invokevirtual addCentering : (Landroidx/constraintlayout/solver/SolverVariable;Landroidx/constraintlayout/solver/SolverVariable;IFLandroidx/constraintlayout/solver/SolverVariable;Landroidx/constraintlayout/solver/SolverVariable;II)V
    //   2122: goto -> 2125
    //   2125: goto -> 2128
    //   2128: aload #4
    //   2130: invokevirtual getVisibility : ()I
    //   2133: bipush #8
    //   2135: if_icmpeq -> 2141
    //   2138: goto -> 2145
    //   2141: aload #16
    //   2143: astore #4
    //   2145: aload #4
    //   2147: astore #16
    //   2149: aload_0
    //   2150: astore #4
    //   2152: goto -> 1784
    //   2155: aload #19
    //   2157: getfield y : [Landroidx/constraintlayout/solver/widgets/ConstraintAnchor;
    //   2160: iload_3
    //   2161: aaload
    //   2162: astore_0
    //   2163: aload #24
    //   2165: getfield y : [Landroidx/constraintlayout/solver/widgets/ConstraintAnchor;
    //   2168: iload_3
    //   2169: aaload
    //   2170: getfield c : Landroidx/constraintlayout/solver/widgets/ConstraintAnchor;
    //   2173: astore #4
    //   2175: aload #23
    //   2177: getfield y : [Landroidx/constraintlayout/solver/widgets/ConstraintAnchor;
    //   2180: astore #16
    //   2182: iload_3
    //   2183: iconst_1
    //   2184: iadd
    //   2185: istore_2
    //   2186: aload #16
    //   2188: iload_2
    //   2189: aaload
    //   2190: astore #16
    //   2192: aload #22
    //   2194: getfield y : [Landroidx/constraintlayout/solver/widgets/ConstraintAnchor;
    //   2197: iload_2
    //   2198: aaload
    //   2199: getfield c : Landroidx/constraintlayout/solver/widgets/ConstraintAnchor;
    //   2202: astore #17
    //   2204: aload #4
    //   2206: ifnull -> 2281
    //   2209: aload #19
    //   2211: aload #23
    //   2213: if_acmpeq -> 2238
    //   2216: aload_1
    //   2217: aload_0
    //   2218: getfield e : Landroidx/constraintlayout/solver/SolverVariable;
    //   2221: aload #4
    //   2223: getfield e : Landroidx/constraintlayout/solver/SolverVariable;
    //   2226: aload_0
    //   2227: invokevirtual getMargin : ()I
    //   2230: iconst_5
    //   2231: invokevirtual addEquality : (Landroidx/constraintlayout/solver/SolverVariable;Landroidx/constraintlayout/solver/SolverVariable;II)Landroidx/constraintlayout/solver/ArrayRow;
    //   2234: pop
    //   2235: goto -> 2281
    //   2238: aload #17
    //   2240: ifnull -> 2281
    //   2243: aload_1
    //   2244: aload_0
    //   2245: getfield e : Landroidx/constraintlayout/solver/SolverVariable;
    //   2248: aload #4
    //   2250: getfield e : Landroidx/constraintlayout/solver/SolverVariable;
    //   2253: aload_0
    //   2254: invokevirtual getMargin : ()I
    //   2257: ldc 0.5
    //   2259: aload #16
    //   2261: getfield e : Landroidx/constraintlayout/solver/SolverVariable;
    //   2264: aload #17
    //   2266: getfield e : Landroidx/constraintlayout/solver/SolverVariable;
    //   2269: aload #16
    //   2271: invokevirtual getMargin : ()I
    //   2274: iconst_5
    //   2275: invokevirtual addCentering : (Landroidx/constraintlayout/solver/SolverVariable;Landroidx/constraintlayout/solver/SolverVariable;IFLandroidx/constraintlayout/solver/SolverVariable;Landroidx/constraintlayout/solver/SolverVariable;II)V
    //   2278: goto -> 2281
    //   2281: aload #17
    //   2283: ifnull -> 2315
    //   2286: aload #19
    //   2288: aload #23
    //   2290: if_acmpeq -> 2315
    //   2293: aload_1
    //   2294: aload #16
    //   2296: getfield e : Landroidx/constraintlayout/solver/SolverVariable;
    //   2299: aload #17
    //   2301: getfield e : Landroidx/constraintlayout/solver/SolverVariable;
    //   2304: aload #16
    //   2306: invokevirtual getMargin : ()I
    //   2309: ineg
    //   2310: iconst_5
    //   2311: invokevirtual addEquality : (Landroidx/constraintlayout/solver/SolverVariable;Landroidx/constraintlayout/solver/SolverVariable;II)Landroidx/constraintlayout/solver/ArrayRow;
    //   2314: pop
    //   2315: iload #10
    //   2317: ifne -> 2325
    //   2320: iload #11
    //   2322: ifeq -> 2524
    //   2325: aload #19
    //   2327: ifnull -> 2524
    //   2330: aload #19
    //   2332: getfield y : [Landroidx/constraintlayout/solver/widgets/ConstraintAnchor;
    //   2335: iload_3
    //   2336: aaload
    //   2337: astore #16
    //   2339: aload #23
    //   2341: getfield y : [Landroidx/constraintlayout/solver/widgets/ConstraintAnchor;
    //   2344: astore_0
    //   2345: iload_3
    //   2346: iconst_1
    //   2347: iadd
    //   2348: istore_2
    //   2349: aload_0
    //   2350: iload_2
    //   2351: aaload
    //   2352: astore #17
    //   2354: aload #16
    //   2356: getfield c : Landroidx/constraintlayout/solver/widgets/ConstraintAnchor;
    //   2359: ifnull -> 2375
    //   2362: aload #16
    //   2364: getfield c : Landroidx/constraintlayout/solver/widgets/ConstraintAnchor;
    //   2367: getfield e : Landroidx/constraintlayout/solver/SolverVariable;
    //   2370: astore #4
    //   2372: goto -> 2378
    //   2375: aconst_null
    //   2376: astore #4
    //   2378: aload #17
    //   2380: getfield c : Landroidx/constraintlayout/solver/widgets/ConstraintAnchor;
    //   2383: ifnull -> 2398
    //   2386: aload #17
    //   2388: getfield c : Landroidx/constraintlayout/solver/widgets/ConstraintAnchor;
    //   2391: getfield e : Landroidx/constraintlayout/solver/SolverVariable;
    //   2394: astore_0
    //   2395: goto -> 2400
    //   2398: aconst_null
    //   2399: astore_0
    //   2400: aload #22
    //   2402: aload #23
    //   2404: if_acmpeq -> 2435
    //   2407: aload #22
    //   2409: getfield y : [Landroidx/constraintlayout/solver/widgets/ConstraintAnchor;
    //   2412: iload_2
    //   2413: aaload
    //   2414: astore_0
    //   2415: aload_0
    //   2416: getfield c : Landroidx/constraintlayout/solver/widgets/ConstraintAnchor;
    //   2419: ifnull -> 2433
    //   2422: aload_0
    //   2423: getfield c : Landroidx/constraintlayout/solver/widgets/ConstraintAnchor;
    //   2426: getfield e : Landroidx/constraintlayout/solver/SolverVariable;
    //   2429: astore_0
    //   2430: goto -> 2435
    //   2433: aconst_null
    //   2434: astore_0
    //   2435: aload #19
    //   2437: aload #23
    //   2439: if_acmpne -> 2460
    //   2442: aload #19
    //   2444: getfield y : [Landroidx/constraintlayout/solver/widgets/ConstraintAnchor;
    //   2447: iload_3
    //   2448: aaload
    //   2449: astore #16
    //   2451: aload #19
    //   2453: getfield y : [Landroidx/constraintlayout/solver/widgets/ConstraintAnchor;
    //   2456: iload_2
    //   2457: aaload
    //   2458: astore #17
    //   2460: aload #4
    //   2462: ifnull -> 2524
    //   2465: aload_0
    //   2466: ifnull -> 2524
    //   2469: aload #16
    //   2471: invokevirtual getMargin : ()I
    //   2474: istore_3
    //   2475: aload #23
    //   2477: ifnonnull -> 2487
    //   2480: aload #22
    //   2482: astore #18
    //   2484: goto -> 2491
    //   2487: aload #23
    //   2489: astore #18
    //   2491: aload #18
    //   2493: getfield y : [Landroidx/constraintlayout/solver/widgets/ConstraintAnchor;
    //   2496: iload_2
    //   2497: aaload
    //   2498: invokevirtual getMargin : ()I
    //   2501: istore_2
    //   2502: aload_1
    //   2503: aload #16
    //   2505: getfield e : Landroidx/constraintlayout/solver/SolverVariable;
    //   2508: aload #4
    //   2510: iload_3
    //   2511: ldc 0.5
    //   2513: aload_0
    //   2514: aload #17
    //   2516: getfield e : Landroidx/constraintlayout/solver/SolverVariable;
    //   2519: iload_2
    //   2520: iconst_5
    //   2521: invokevirtual addCentering : (Landroidx/constraintlayout/solver/SolverVariable;Landroidx/constraintlayout/solver/SolverVariable;IFLandroidx/constraintlayout/solver/SolverVariable;Landroidx/constraintlayout/solver/SolverVariable;II)V
    //   2524: return
  }
}


/* Location:              D:\code\BluedHook\classes.dex\com.soft.blued7646532-dex2jar.jar!\androidx\constraintlayout\solver\widgets\Chain.class
 * Java compiler version: 6 (50.0)
 * JD-Core Version:       1.1.3
 */