package com.tencent.bugly.yaq;

import java.util.Map;

public class BuglyStrategy {
  private String a;
  
  private String b;
  
  private String c;
  
  private long d;
  
  private String e;
  
  private String f;
  
  private boolean g;
  
  private boolean h;
  
  private boolean i;
  
  private Class<?> j;
  
  private boolean k;
  
  private boolean l;
  
  private boolean m;
  
  private boolean n;
  
  private a o;
  
  public BuglyStrategy() {
    throw new VerifyError("bad dex opcode");
  }
  
  public String getAppChannel() {
    // Byte code:
    //   0: aload_0
    //   1: monitorenter
    //   2: new java/lang/VerifyError
    //   5: dup
    //   6: ldc 'bad dex opcode'
    //   8: invokespecial <init> : (Ljava/lang/String;)V
    //   11: athrow
    //   12: astore_1
    //   13: aload_0
    //   14: monitorexit
    //   15: aload_1
    //   16: athrow
    // Exception table:
    //   from	to	target	type
    //   2	12	12	finally
  }
  
  public String getAppPackageName() {
    // Byte code:
    //   0: aload_0
    //   1: monitorenter
    //   2: new java/lang/VerifyError
    //   5: dup
    //   6: ldc 'bad dex opcode'
    //   8: invokespecial <init> : (Ljava/lang/String;)V
    //   11: athrow
    //   12: astore_1
    //   13: aload_0
    //   14: monitorexit
    //   15: aload_1
    //   16: athrow
    // Exception table:
    //   from	to	target	type
    //   2	12	12	finally
  }
  
  public long getAppReportDelay() {
    // Byte code:
    //   0: aload_0
    //   1: monitorenter
    //   2: new java/lang/VerifyError
    //   5: dup
    //   6: ldc 'bad dex opcode'
    //   8: invokespecial <init> : (Ljava/lang/String;)V
    //   11: athrow
    //   12: astore_1
    //   13: aload_0
    //   14: monitorexit
    //   15: aload_1
    //   16: athrow
    // Exception table:
    //   from	to	target	type
    //   2	12	12	finally
  }
  
  public String getAppVersion() {
    // Byte code:
    //   0: aload_0
    //   1: monitorenter
    //   2: new java/lang/VerifyError
    //   5: dup
    //   6: ldc 'bad dex opcode'
    //   8: invokespecial <init> : (Ljava/lang/String;)V
    //   11: athrow
    //   12: astore_1
    //   13: aload_0
    //   14: monitorexit
    //   15: aload_1
    //   16: athrow
    // Exception table:
    //   from	to	target	type
    //   2	12	12	finally
  }
  
  public a getCrashHandleCallback() {
    // Byte code:
    //   0: aload_0
    //   1: monitorenter
    //   2: new java/lang/VerifyError
    //   5: dup
    //   6: ldc 'bad dex opcode'
    //   8: invokespecial <init> : (Ljava/lang/String;)V
    //   11: athrow
    //   12: astore_1
    //   13: aload_0
    //   14: monitorexit
    //   15: aload_1
    //   16: athrow
    // Exception table:
    //   from	to	target	type
    //   2	12	12	finally
  }
  
  public String getDeviceID() {
    // Byte code:
    //   0: aload_0
    //   1: monitorenter
    //   2: new java/lang/VerifyError
    //   5: dup
    //   6: ldc 'bad dex opcode'
    //   8: invokespecial <init> : (Ljava/lang/String;)V
    //   11: athrow
    //   12: astore_1
    //   13: aload_0
    //   14: monitorexit
    //   15: aload_1
    //   16: athrow
    // Exception table:
    //   from	to	target	type
    //   2	12	12	finally
  }
  
  public String getLibBuglySOFilePath() {
    // Byte code:
    //   0: aload_0
    //   1: monitorenter
    //   2: new java/lang/VerifyError
    //   5: dup
    //   6: ldc 'bad dex opcode'
    //   8: invokespecial <init> : (Ljava/lang/String;)V
    //   11: athrow
    //   12: astore_1
    //   13: aload_0
    //   14: monitorexit
    //   15: aload_1
    //   16: athrow
    // Exception table:
    //   from	to	target	type
    //   2	12	12	finally
  }
  
  public Class<?> getUserInfoActivity() {
    // Byte code:
    //   0: aload_0
    //   1: monitorenter
    //   2: new java/lang/VerifyError
    //   5: dup
    //   6: ldc 'bad dex opcode'
    //   8: invokespecial <init> : (Ljava/lang/String;)V
    //   11: athrow
    //   12: astore_1
    //   13: aload_0
    //   14: monitorexit
    //   15: aload_1
    //   16: athrow
    // Exception table:
    //   from	to	target	type
    //   2	12	12	finally
  }
  
  public boolean isBuglyLogUpload() {
    // Byte code:
    //   0: aload_0
    //   1: monitorenter
    //   2: new java/lang/VerifyError
    //   5: dup
    //   6: ldc 'bad dex opcode'
    //   8: invokespecial <init> : (Ljava/lang/String;)V
    //   11: athrow
    //   12: astore_1
    //   13: aload_0
    //   14: monitorexit
    //   15: aload_1
    //   16: athrow
    // Exception table:
    //   from	to	target	type
    //   2	12	12	finally
  }
  
  public boolean isEnableANRCrashMonitor() {
    // Byte code:
    //   0: aload_0
    //   1: monitorenter
    //   2: new java/lang/VerifyError
    //   5: dup
    //   6: ldc 'bad dex opcode'
    //   8: invokespecial <init> : (Ljava/lang/String;)V
    //   11: athrow
    //   12: astore_1
    //   13: aload_0
    //   14: monitorexit
    //   15: aload_1
    //   16: athrow
    // Exception table:
    //   from	to	target	type
    //   2	12	12	finally
  }
  
  public boolean isEnableNativeCrashMonitor() {
    // Byte code:
    //   0: aload_0
    //   1: monitorenter
    //   2: new java/lang/VerifyError
    //   5: dup
    //   6: ldc 'bad dex opcode'
    //   8: invokespecial <init> : (Ljava/lang/String;)V
    //   11: athrow
    //   12: astore_1
    //   13: aload_0
    //   14: monitorexit
    //   15: aload_1
    //   16: athrow
    // Exception table:
    //   from	to	target	type
    //   2	12	12	finally
  }
  
  public boolean isEnableUserInfo() {
    // Byte code:
    //   0: aload_0
    //   1: monitorenter
    //   2: new java/lang/VerifyError
    //   5: dup
    //   6: ldc 'bad dex opcode'
    //   8: invokespecial <init> : (Ljava/lang/String;)V
    //   11: athrow
    //   12: astore_1
    //   13: aload_0
    //   14: monitorexit
    //   15: aload_1
    //   16: athrow
    // Exception table:
    //   from	to	target	type
    //   2	12	12	finally
  }
  
  public boolean isReplaceOldChannel() {
    throw new VerifyError("bad dex opcode");
  }
  
  public boolean isUploadProcess() {
    // Byte code:
    //   0: aload_0
    //   1: monitorenter
    //   2: new java/lang/VerifyError
    //   5: dup
    //   6: ldc 'bad dex opcode'
    //   8: invokespecial <init> : (Ljava/lang/String;)V
    //   11: athrow
    //   12: astore_1
    //   13: aload_0
    //   14: monitorexit
    //   15: aload_1
    //   16: athrow
    // Exception table:
    //   from	to	target	type
    //   2	12	12	finally
  }
  
  public boolean recordUserInfoOnceADay() {
    // Byte code:
    //   0: aload_0
    //   1: monitorenter
    //   2: new java/lang/VerifyError
    //   5: dup
    //   6: ldc 'bad dex opcode'
    //   8: invokespecial <init> : (Ljava/lang/String;)V
    //   11: athrow
    //   12: astore_1
    //   13: aload_0
    //   14: monitorexit
    //   15: aload_1
    //   16: athrow
    // Exception table:
    //   from	to	target	type
    //   2	12	12	finally
  }
  
  public BuglyStrategy setAppChannel(String paramString) {
    // Byte code:
    //   0: aload_0
    //   1: monitorenter
    //   2: new java/lang/VerifyError
    //   5: dup
    //   6: ldc 'bad dex opcode'
    //   8: invokespecial <init> : (Ljava/lang/String;)V
    //   11: athrow
    //   12: astore_1
    //   13: aload_0
    //   14: monitorexit
    //   15: aload_1
    //   16: athrow
    // Exception table:
    //   from	to	target	type
    //   2	12	12	finally
  }
  
  public BuglyStrategy setAppPackageName(String paramString) {
    // Byte code:
    //   0: aload_0
    //   1: monitorenter
    //   2: new java/lang/VerifyError
    //   5: dup
    //   6: ldc 'bad dex opcode'
    //   8: invokespecial <init> : (Ljava/lang/String;)V
    //   11: athrow
    //   12: astore_1
    //   13: aload_0
    //   14: monitorexit
    //   15: aload_1
    //   16: athrow
    // Exception table:
    //   from	to	target	type
    //   2	12	12	finally
  }
  
  public BuglyStrategy setAppReportDelay(long paramLong) {
    // Byte code:
    //   0: aload_0
    //   1: monitorenter
    //   2: new java/lang/VerifyError
    //   5: dup
    //   6: ldc 'bad dex opcode'
    //   8: invokespecial <init> : (Ljava/lang/String;)V
    //   11: athrow
    //   12: astore_3
    //   13: aload_0
    //   14: monitorexit
    //   15: aload_3
    //   16: athrow
    // Exception table:
    //   from	to	target	type
    //   2	12	12	finally
  }
  
  public BuglyStrategy setAppVersion(String paramString) {
    // Byte code:
    //   0: aload_0
    //   1: monitorenter
    //   2: new java/lang/VerifyError
    //   5: dup
    //   6: ldc 'bad dex opcode'
    //   8: invokespecial <init> : (Ljava/lang/String;)V
    //   11: athrow
    //   12: astore_1
    //   13: aload_0
    //   14: monitorexit
    //   15: aload_1
    //   16: athrow
    // Exception table:
    //   from	to	target	type
    //   2	12	12	finally
  }
  
  public BuglyStrategy setBuglyLogUpload(boolean paramBoolean) {
    // Byte code:
    //   0: aload_0
    //   1: monitorenter
    //   2: new java/lang/VerifyError
    //   5: dup
    //   6: ldc 'bad dex opcode'
    //   8: invokespecial <init> : (Ljava/lang/String;)V
    //   11: athrow
    //   12: astore_2
    //   13: aload_0
    //   14: monitorexit
    //   15: aload_2
    //   16: athrow
    // Exception table:
    //   from	to	target	type
    //   2	12	12	finally
  }
  
  public BuglyStrategy setCrashHandleCallback(a parama) {
    // Byte code:
    //   0: aload_0
    //   1: monitorenter
    //   2: new java/lang/VerifyError
    //   5: dup
    //   6: ldc 'bad dex opcode'
    //   8: invokespecial <init> : (Ljava/lang/String;)V
    //   11: athrow
    //   12: astore_1
    //   13: aload_0
    //   14: monitorexit
    //   15: aload_1
    //   16: athrow
    // Exception table:
    //   from	to	target	type
    //   2	12	12	finally
  }
  
  public BuglyStrategy setDeviceID(String paramString) {
    // Byte code:
    //   0: aload_0
    //   1: monitorenter
    //   2: new java/lang/VerifyError
    //   5: dup
    //   6: ldc 'bad dex opcode'
    //   8: invokespecial <init> : (Ljava/lang/String;)V
    //   11: athrow
    //   12: astore_1
    //   13: aload_0
    //   14: monitorexit
    //   15: aload_1
    //   16: athrow
    // Exception table:
    //   from	to	target	type
    //   2	12	12	finally
  }
  
  public BuglyStrategy setEnableANRCrashMonitor(boolean paramBoolean) {
    // Byte code:
    //   0: aload_0
    //   1: monitorenter
    //   2: new java/lang/VerifyError
    //   5: dup
    //   6: ldc 'bad dex opcode'
    //   8: invokespecial <init> : (Ljava/lang/String;)V
    //   11: athrow
    //   12: astore_2
    //   13: aload_0
    //   14: monitorexit
    //   15: aload_2
    //   16: athrow
    // Exception table:
    //   from	to	target	type
    //   2	12	12	finally
  }
  
  public BuglyStrategy setEnableNativeCrashMonitor(boolean paramBoolean) {
    // Byte code:
    //   0: aload_0
    //   1: monitorenter
    //   2: new java/lang/VerifyError
    //   5: dup
    //   6: ldc 'bad dex opcode'
    //   8: invokespecial <init> : (Ljava/lang/String;)V
    //   11: athrow
    //   12: astore_2
    //   13: aload_0
    //   14: monitorexit
    //   15: aload_2
    //   16: athrow
    // Exception table:
    //   from	to	target	type
    //   2	12	12	finally
  }
  
  public BuglyStrategy setEnableUserInfo(boolean paramBoolean) {
    // Byte code:
    //   0: aload_0
    //   1: monitorenter
    //   2: new java/lang/VerifyError
    //   5: dup
    //   6: ldc 'bad dex opcode'
    //   8: invokespecial <init> : (Ljava/lang/String;)V
    //   11: athrow
    //   12: astore_2
    //   13: aload_0
    //   14: monitorexit
    //   15: aload_2
    //   16: athrow
    // Exception table:
    //   from	to	target	type
    //   2	12	12	finally
  }
  
  public BuglyStrategy setLibBuglySOFilePath(String paramString) {
    // Byte code:
    //   0: aload_0
    //   1: monitorenter
    //   2: new java/lang/VerifyError
    //   5: dup
    //   6: ldc 'bad dex opcode'
    //   8: invokespecial <init> : (Ljava/lang/String;)V
    //   11: athrow
    //   12: astore_1
    //   13: aload_0
    //   14: monitorexit
    //   15: aload_1
    //   16: athrow
    // Exception table:
    //   from	to	target	type
    //   2	12	12	finally
  }
  
  public BuglyStrategy setRecordUserInfoOnceADay(boolean paramBoolean) {
    // Byte code:
    //   0: aload_0
    //   1: monitorenter
    //   2: new java/lang/VerifyError
    //   5: dup
    //   6: ldc 'bad dex opcode'
    //   8: invokespecial <init> : (Ljava/lang/String;)V
    //   11: athrow
    //   12: astore_2
    //   13: aload_0
    //   14: monitorexit
    //   15: aload_2
    //   16: athrow
    // Exception table:
    //   from	to	target	type
    //   2	12	12	finally
  }
  
  public void setReplaceOldChannel(boolean paramBoolean) {
    throw new VerifyError("bad dex opcode");
  }
  
  public BuglyStrategy setUploadProcess(boolean paramBoolean) {
    // Byte code:
    //   0: aload_0
    //   1: monitorenter
    //   2: new java/lang/VerifyError
    //   5: dup
    //   6: ldc 'bad dex opcode'
    //   8: invokespecial <init> : (Ljava/lang/String;)V
    //   11: athrow
    //   12: astore_2
    //   13: aload_0
    //   14: monitorexit
    //   15: aload_2
    //   16: athrow
    // Exception table:
    //   from	to	target	type
    //   2	12	12	finally
  }
  
  public BuglyStrategy setUserInfoActivity(Class<?> paramClass) {
    // Byte code:
    //   0: aload_0
    //   1: monitorenter
    //   2: new java/lang/VerifyError
    //   5: dup
    //   6: ldc 'bad dex opcode'
    //   8: invokespecial <init> : (Ljava/lang/String;)V
    //   11: athrow
    //   12: astore_1
    //   13: aload_0
    //   14: monitorexit
    //   15: aload_1
    //   16: athrow
    // Exception table:
    //   from	to	target	type
    //   2	12	12	finally
  }
  
  public static class a {
    public static final int CRASHTYPE_ANR = 4;
    
    public static final int CRASHTYPE_BLOCK = 7;
    
    public static final int CRASHTYPE_COCOS2DX_JS = 5;
    
    public static final int CRASHTYPE_COCOS2DX_LUA = 6;
    
    public static final int CRASHTYPE_JAVA_CATCH = 1;
    
    public static final int CRASHTYPE_JAVA_CRASH = 0;
    
    public static final int CRASHTYPE_NATIVE = 2;
    
    public static final int CRASHTYPE_U3D = 3;
    
    public static final int MAX_USERDATA_KEY_LENGTH = 100;
    
    public static final int MAX_USERDATA_VALUE_LENGTH = 30000;
    
    public a() {
      throw new VerifyError("bad dex opcode");
    }
    
    public Map<String, String> onCrashHandleStart(int param1Int, String param1String1, String param1String2, String param1String3) {
      /* monitor enter ThisExpression{InnerObjectType{ObjectType{com/tencent/bugly/yaq/BuglyStrategy}.Lcom/tencent/bugly/yaq/BuglyStrategy$a;}} */
      /* monitor exit ThisExpression{InnerObjectType{ObjectType{com/tencent/bugly/yaq/BuglyStrategy}.Lcom/tencent/bugly/yaq/BuglyStrategy$a;}} */
      return null;
    }
    
    public byte[] onCrashHandleStart2GetExtraDatas(int param1Int, String param1String1, String param1String2, String param1String3) {
      /* monitor enter ThisExpression{InnerObjectType{ObjectType{com/tencent/bugly/yaq/BuglyStrategy}.Lcom/tencent/bugly/yaq/BuglyStrategy$a;}} */
      /* monitor exit ThisExpression{InnerObjectType{ObjectType{com/tencent/bugly/yaq/BuglyStrategy}.Lcom/tencent/bugly/yaq/BuglyStrategy$a;}} */
      return null;
    }
  }
}


/* Location:              D:\code\BluedHook\classes.dex\com.soft.blued555128-dex2jar.jar!\com\tencent\bugly\yaq\BuglyStrategy.class
 * Java compiler version: 6 (50.0)
 * JD-Core Version:       1.1.3
 */