package com.blued.android.module.im.biz.receipt;

import com.blued.android.module.im.biz.Common;
import com.blued.android.module.im.grpc.ChannelManager;
import com.blued.android.module.im.grpc.IMThreadManager;
import com.blued.android.statistics.util.NamedRunnable;
import com.blued.im.private_chat.ReceiptGrpc;
import com.blued.im.private_chat.ReceiptOuterClass;

public abstract class ReceiptBase {
  protected ChannelManager a;
  
  protected IMThreadManager b;
  
  public ReceiptBase(ChannelManager paramChannelManager, IMThreadManager paramIMThreadManager) {
    this.a = paramChannelManager;
    this.b = paramIMThreadManager;
  }
  
  protected abstract ReceiptOuterClass.ReceiptResponse a(ReceiptGrpc.ReceiptBlockingStub paramReceiptBlockingStub, ReceiptOuterClass.ReceiptRequest paramReceiptRequest);
  
  protected abstract String a();
  
  public void a(boolean paramBoolean1, int paramInt1, int paramInt2, int paramInt3, int paramInt4, boolean paramBoolean2, OnReceiptResponseListener paramOnReceiptResponseListener) {
    if (this.a != null) {
      if (this.b == null)
        return; 
      try {
        ReceiptOuterClass.ReceiptRequest receiptRequest = ReceiptOuterClass.ReceiptRequest.newBuilder().setCommon(Common.a().b()).setSessionType(paramInt1).setFrom(paramInt2).setTo(paramInt3).setIsDeleteMsg(paramBoolean2).setSeqnum(paramInt4).build();
        this.b.a((Runnable)new SendReceiptRunnable(this, paramBoolean1, receiptRequest, paramOnReceiptResponseListener));
        return;
      } catch (Exception exception) {
        exception.printStackTrace();
      } 
    } 
  }
  
  class SendReceiptRunnable extends NamedRunnable {
    private boolean b;
    
    private ReceiptOuterClass.ReceiptRequest c;
    
    private OnReceiptResponseListener d;
    
    public SendReceiptRunnable(ReceiptBase this$0, boolean param1Boolean, ReceiptOuterClass.ReceiptRequest param1ReceiptRequest, OnReceiptResponseListener param1OnReceiptResponseListener) {
      super("receipt");
      this.b = param1Boolean;
      this.c = param1ReceiptRequest;
      this.d = param1OnReceiptResponseListener;
    }
    
    public void a() {
      // Byte code:
      //   0: invokestatic b : ()Z
      //   3: ifeq -> 58
      //   6: invokestatic a : ()Lcom/blued/android/statistics/util/Logger;
      //   9: astore #6
      //   11: new java/lang/StringBuilder
      //   14: dup
      //   15: invokespecial <init> : ()V
      //   18: astore #7
      //   20: aload #7
      //   22: ldc '>> SendReceiptMessage Request : '
      //   24: invokevirtual append : (Ljava/lang/String;)Ljava/lang/StringBuilder;
      //   27: pop
      //   28: aload #7
      //   30: aload_0
      //   31: getfield c : Lcom/blued/im/private_chat/ReceiptOuterClass$ReceiptRequest;
      //   34: invokevirtual toString : ()Ljava/lang/String;
      //   37: invokevirtual append : (Ljava/lang/String;)Ljava/lang/StringBuilder;
      //   40: pop
      //   41: aload #6
      //   43: iconst_1
      //   44: anewarray java/lang/Object
      //   47: dup
      //   48: iconst_0
      //   49: aload #7
      //   51: invokevirtual toString : ()Ljava/lang/String;
      //   54: aastore
      //   55: invokevirtual b : ([Ljava/lang/Object;)V
      //   58: invokestatic uptimeMillis : ()J
      //   61: lstore #4
      //   63: bipush #100
      //   65: istore_1
      //   66: bipush #-2
      //   68: istore_2
      //   69: aconst_null
      //   70: astore #12
      //   72: aconst_null
      //   73: astore #11
      //   75: aconst_null
      //   76: astore #8
      //   78: aload_0
      //   79: getfield a : Lcom/blued/android/module/im/biz/receipt/ReceiptBase;
      //   82: getfield a : Lcom/blued/android/module/im/grpc/ChannelManager;
      //   85: invokevirtual d : ()Lio/grpc/Channel;
      //   88: invokestatic newBlockingStub : (Lio/grpc/Channel;)Lcom/blued/im/private_chat/ReceiptGrpc$ReceiptBlockingStub;
      //   91: astore #6
      //   93: aload_0
      //   94: getfield a : Lcom/blued/android/module/im/biz/receipt/ReceiptBase;
      //   97: getfield a : Lcom/blued/android/module/im/grpc/ChannelManager;
      //   100: aload #6
      //   102: invokevirtual a : (Lio/grpc/stub/AbstractStub;)Lio/grpc/stub/AbstractStub;
      //   105: checkcast com/blued/im/private_chat/ReceiptGrpc$ReceiptBlockingStub
      //   108: ldc 'gzip'
      //   110: invokevirtual withCompression : (Ljava/lang/String;)Lio/grpc/stub/AbstractStub;
      //   113: checkcast com/blued/im/private_chat/ReceiptGrpc$ReceiptBlockingStub
      //   116: ldc2_w 30
      //   119: getstatic java/util/concurrent/TimeUnit.SECONDS : Ljava/util/concurrent/TimeUnit;
      //   122: invokevirtual withDeadlineAfter : (JLjava/util/concurrent/TimeUnit;)Lio/grpc/stub/AbstractStub;
      //   125: checkcast com/blued/im/private_chat/ReceiptGrpc$ReceiptBlockingStub
      //   128: astore #6
      //   130: aload_0
      //   131: getfield a : Lcom/blued/android/module/im/biz/receipt/ReceiptBase;
      //   134: aload #6
      //   136: aload_0
      //   137: getfield c : Lcom/blued/im/private_chat/ReceiptOuterClass$ReceiptRequest;
      //   140: invokevirtual a : (Lcom/blued/im/private_chat/ReceiptGrpc$ReceiptBlockingStub;Lcom/blued/im/private_chat/ReceiptOuterClass$ReceiptRequest;)Lcom/blued/im/private_chat/ReceiptOuterClass$ReceiptResponse;
      //   143: astore #6
      //   145: aload #6
      //   147: ifnull -> 154
      //   150: sipush #200
      //   153: istore_1
      //   154: iload_1
      //   155: istore_3
      //   156: aload #6
      //   158: astore #7
      //   160: invokestatic b : ()Z
      //   163: ifeq -> 192
      //   166: iload_1
      //   167: istore_3
      //   168: aload #6
      //   170: astore #7
      //   172: invokestatic a : ()Lcom/blued/android/statistics/util/Logger;
      //   175: iconst_2
      //   176: anewarray java/lang/Object
      //   179: dup
      //   180: iconst_0
      //   181: ldc '>> SendReceiptMessage response : \\n'
      //   183: aastore
      //   184: dup
      //   185: iconst_1
      //   186: aload #6
      //   188: aastore
      //   189: invokevirtual a : ([Ljava/lang/Object;)V
      //   192: aload #6
      //   194: astore #7
      //   196: aload_0
      //   197: getfield d : Lcom/blued/android/module/im/biz/receipt/OnReceiptResponseListener;
      //   200: ifnull -> 288
      //   203: iload_1
      //   204: getstatic io/grpc/Status$Code.DEADLINE_EXCEEDED : Lio/grpc/Status$Code;
      //   207: invokevirtual value : ()I
      //   210: if_icmpne -> 216
      //   213: goto -> 218
      //   216: iconst_m1
      //   217: istore_2
      //   218: aload #6
      //   220: astore #7
      //   222: aload #6
      //   224: ifnonnull -> 239
      //   227: invokestatic newBuilder : ()Lcom/blued/im/private_chat/ReceiptOuterClass$ReceiptResponse$Builder;
      //   230: iload_2
      //   231: invokevirtual setCodeValue : (I)Lcom/blued/im/private_chat/ReceiptOuterClass$ReceiptResponse$Builder;
      //   234: invokevirtual build : ()Lcom/blued/im/private_chat/ReceiptOuterClass$ReceiptResponse;
      //   237: astore #7
      //   239: aload #7
      //   241: invokevirtual getCodeValue : ()I
      //   244: istore_2
      //   245: iload_2
      //   246: getstatic com/blued/im/private_chat/CodeOuterClass$Code.PRIVATE_SUCCESS : Lcom/blued/im/private_chat/CodeOuterClass$Code;
      //   249: invokevirtual getNumber : ()I
      //   252: if_icmpne -> 277
      //   255: aload_0
      //   256: getfield d : Lcom/blued/android/module/im/biz/receipt/OnReceiptResponseListener;
      //   259: aload #7
      //   261: invokevirtual getSeqnum : ()J
      //   264: aload #7
      //   266: invokevirtual getResponseTime : ()J
      //   269: invokeinterface onSuccess : (JJ)V
      //   274: goto -> 288
      //   277: aload_0
      //   278: getfield d : Lcom/blued/android/module/im/biz/receipt/OnReceiptResponseListener;
      //   281: iload_2
      //   282: aconst_null
      //   283: invokeinterface onFailure : (ILjava/lang/Exception;)V
      //   288: invokestatic uptimeMillis : ()J
      //   291: lload #4
      //   293: lsub
      //   294: lstore #4
      //   296: aload #7
      //   298: ifnonnull -> 308
      //   301: aload #8
      //   303: astore #6
      //   305: goto -> 315
      //   308: aload #7
      //   310: invokevirtual getRequestId : ()Ljava/lang/String;
      //   313: astore #6
      //   315: invokestatic b : ()Lcom/blued/android/statistics/biz/Apm;
      //   318: astore #8
      //   320: aload_0
      //   321: getfield b : Z
      //   324: ifeq -> 335
      //   327: getstatic com/blued/das/apm/ApmProtos$GrpcRequestTypeProto$BUSINESS.GROUP_CHAT : Lcom/blued/das/apm/ApmProtos$GrpcRequestTypeProto$BUSINESS;
      //   330: astore #7
      //   332: goto -> 340
      //   335: getstatic com/blued/das/apm/ApmProtos$GrpcRequestTypeProto$BUSINESS.PRIVATE_CHAT : Lcom/blued/das/apm/ApmProtos$GrpcRequestTypeProto$BUSINESS;
      //   338: astore #7
      //   340: aload #8
      //   342: aload #7
      //   344: aload_0
      //   345: getfield a : Lcom/blued/android/module/im/biz/receipt/ReceiptBase;
      //   348: invokevirtual a : ()Ljava/lang/String;
      //   351: iload_1
      //   352: lload #4
      //   354: aload #6
      //   356: aconst_null
      //   357: aload_0
      //   358: getfield a : Lcom/blued/android/module/im/biz/receipt/ReceiptBase;
      //   361: getfield a : Lcom/blued/android/module/im/grpc/ChannelManager;
      //   364: invokevirtual a : ()Ljava/lang/String;
      //   367: aload_0
      //   368: getfield a : Lcom/blued/android/module/im/biz/receipt/ReceiptBase;
      //   371: getfield a : Lcom/blued/android/module/im/grpc/ChannelManager;
      //   374: invokevirtual b : ()Ljava/lang/String;
      //   377: invokevirtual a : (Lcom/blued/das/apm/ApmProtos$GrpcRequestTypeProto$BUSINESS;Ljava/lang/String;IJLjava/lang/String;Ljava/lang/Throwable;Ljava/lang/String;Ljava/lang/String;)V
      //   380: invokestatic b : ()Z
      //   383: ifeq -> 765
      //   386: invokestatic a : ()Lcom/blued/android/statistics/util/Logger;
      //   389: iconst_2
      //   390: anewarray java/lang/Object
      //   393: dup
      //   394: iconst_0
      //   395: ldc '>> SendReceiptMessage spendTime='
      //   397: aastore
      //   398: dup
      //   399: iconst_1
      //   400: lload #4
      //   402: invokestatic valueOf : (J)Ljava/lang/Long;
      //   405: aastore
      //   406: invokevirtual a : ([Ljava/lang/Object;)V
      //   409: return
      //   410: astore #8
      //   412: goto -> 432
      //   415: astore #7
      //   417: aconst_null
      //   418: astore #8
      //   420: aload #8
      //   422: astore #6
      //   424: goto -> 792
      //   427: astore #8
      //   429: aconst_null
      //   430: astore #6
      //   432: iload_1
      //   433: istore_3
      //   434: aload #6
      //   436: astore #7
      //   438: aload_0
      //   439: getfield a : Lcom/blued/android/module/im/biz/receipt/ReceiptBase;
      //   442: getfield a : Lcom/blued/android/module/im/grpc/ChannelManager;
      //   445: aload #8
      //   447: invokevirtual a : (Ljava/lang/Exception;)Lio/grpc/Status;
      //   450: astore #13
      //   452: iload_1
      //   453: istore_3
      //   454: aload #6
      //   456: astore #7
      //   458: aload #13
      //   460: invokevirtual getCode : ()Lio/grpc/Status$Code;
      //   463: getstatic io/grpc/Status$Code.UNKNOWN : Lio/grpc/Status$Code;
      //   466: if_acmpne -> 476
      //   469: aload #8
      //   471: astore #7
      //   473: goto -> 508
      //   476: iload_1
      //   477: istore_3
      //   478: aload #6
      //   480: astore #7
      //   482: aload #13
      //   484: invokevirtual asException : ()Lio/grpc/StatusException;
      //   487: astore #10
      //   489: iload_1
      //   490: istore_3
      //   491: aload #10
      //   493: astore #9
      //   495: aload #13
      //   497: invokevirtual getCode : ()Lio/grpc/Status$Code;
      //   500: invokevirtual value : ()I
      //   503: istore_1
      //   504: aload #10
      //   506: astore #7
      //   508: iload_1
      //   509: istore_3
      //   510: aload #7
      //   512: astore #9
      //   514: invokestatic b : ()Z
      //   517: ifeq -> 546
      //   520: iload_1
      //   521: istore_3
      //   522: aload #7
      //   524: astore #9
      //   526: invokestatic a : ()Lcom/blued/android/statistics/util/Logger;
      //   529: iconst_2
      //   530: anewarray java/lang/Object
      //   533: dup
      //   534: iconst_0
      //   535: ldc '>> SendReceiptMessage Exception : \\n'
      //   537: aastore
      //   538: dup
      //   539: iconst_1
      //   540: aload #8
      //   542: aastore
      //   543: invokevirtual d : ([Ljava/lang/Object;)V
      //   546: aload #6
      //   548: astore #8
      //   550: aload_0
      //   551: getfield d : Lcom/blued/android/module/im/biz/receipt/OnReceiptResponseListener;
      //   554: ifnull -> 643
      //   557: iload_1
      //   558: getstatic io/grpc/Status$Code.DEADLINE_EXCEEDED : Lio/grpc/Status$Code;
      //   561: invokevirtual value : ()I
      //   564: if_icmpne -> 570
      //   567: goto -> 572
      //   570: iconst_m1
      //   571: istore_2
      //   572: aload #6
      //   574: astore #8
      //   576: aload #6
      //   578: ifnonnull -> 593
      //   581: invokestatic newBuilder : ()Lcom/blued/im/private_chat/ReceiptOuterClass$ReceiptResponse$Builder;
      //   584: iload_2
      //   585: invokevirtual setCodeValue : (I)Lcom/blued/im/private_chat/ReceiptOuterClass$ReceiptResponse$Builder;
      //   588: invokevirtual build : ()Lcom/blued/im/private_chat/ReceiptOuterClass$ReceiptResponse;
      //   591: astore #8
      //   593: aload #8
      //   595: invokevirtual getCodeValue : ()I
      //   598: istore_2
      //   599: iload_2
      //   600: getstatic com/blued/im/private_chat/CodeOuterClass$Code.PRIVATE_SUCCESS : Lcom/blued/im/private_chat/CodeOuterClass$Code;
      //   603: invokevirtual getNumber : ()I
      //   606: if_icmpne -> 631
      //   609: aload_0
      //   610: getfield d : Lcom/blued/android/module/im/biz/receipt/OnReceiptResponseListener;
      //   613: aload #8
      //   615: invokevirtual getSeqnum : ()J
      //   618: aload #8
      //   620: invokevirtual getResponseTime : ()J
      //   623: invokeinterface onSuccess : (JJ)V
      //   628: goto -> 643
      //   631: aload_0
      //   632: getfield d : Lcom/blued/android/module/im/biz/receipt/OnReceiptResponseListener;
      //   635: iload_2
      //   636: aload #7
      //   638: invokeinterface onFailure : (ILjava/lang/Exception;)V
      //   643: invokestatic uptimeMillis : ()J
      //   646: lload #4
      //   648: lsub
      //   649: lstore #4
      //   651: aload #8
      //   653: ifnonnull -> 663
      //   656: aload #12
      //   658: astore #6
      //   660: goto -> 670
      //   663: aload #8
      //   665: invokevirtual getRequestId : ()Ljava/lang/String;
      //   668: astore #6
      //   670: invokestatic b : ()Lcom/blued/android/statistics/biz/Apm;
      //   673: astore #9
      //   675: aload_0
      //   676: getfield b : Z
      //   679: ifeq -> 690
      //   682: getstatic com/blued/das/apm/ApmProtos$GrpcRequestTypeProto$BUSINESS.GROUP_CHAT : Lcom/blued/das/apm/ApmProtos$GrpcRequestTypeProto$BUSINESS;
      //   685: astore #8
      //   687: goto -> 695
      //   690: getstatic com/blued/das/apm/ApmProtos$GrpcRequestTypeProto$BUSINESS.PRIVATE_CHAT : Lcom/blued/das/apm/ApmProtos$GrpcRequestTypeProto$BUSINESS;
      //   693: astore #8
      //   695: aload #9
      //   697: aload #8
      //   699: aload_0
      //   700: getfield a : Lcom/blued/android/module/im/biz/receipt/ReceiptBase;
      //   703: invokevirtual a : ()Ljava/lang/String;
      //   706: iload_1
      //   707: lload #4
      //   709: aload #6
      //   711: aload #7
      //   713: aload_0
      //   714: getfield a : Lcom/blued/android/module/im/biz/receipt/ReceiptBase;
      //   717: getfield a : Lcom/blued/android/module/im/grpc/ChannelManager;
      //   720: invokevirtual a : ()Ljava/lang/String;
      //   723: aload_0
      //   724: getfield a : Lcom/blued/android/module/im/biz/receipt/ReceiptBase;
      //   727: getfield a : Lcom/blued/android/module/im/grpc/ChannelManager;
      //   730: invokevirtual b : ()Ljava/lang/String;
      //   733: invokevirtual a : (Lcom/blued/das/apm/ApmProtos$GrpcRequestTypeProto$BUSINESS;Ljava/lang/String;IJLjava/lang/String;Ljava/lang/Throwable;Ljava/lang/String;Ljava/lang/String;)V
      //   736: invokestatic b : ()Z
      //   739: ifeq -> 765
      //   742: invokestatic a : ()Lcom/blued/android/statistics/util/Logger;
      //   745: iconst_2
      //   746: anewarray java/lang/Object
      //   749: dup
      //   750: iconst_0
      //   751: ldc '>> SendReceiptMessage spendTime='
      //   753: aastore
      //   754: dup
      //   755: iconst_1
      //   756: lload #4
      //   758: invokestatic valueOf : (J)Ljava/lang/Long;
      //   761: aastore
      //   762: invokevirtual a : ([Ljava/lang/Object;)V
      //   765: return
      //   766: astore #7
      //   768: aload #9
      //   770: astore #8
      //   772: iload_3
      //   773: istore_1
      //   774: goto -> 792
      //   777: astore #9
      //   779: aconst_null
      //   780: astore #8
      //   782: aload #7
      //   784: astore #6
      //   786: iload_3
      //   787: istore_1
      //   788: aload #9
      //   790: astore #7
      //   792: aload #6
      //   794: astore #9
      //   796: aload_0
      //   797: getfield d : Lcom/blued/android/module/im/biz/receipt/OnReceiptResponseListener;
      //   800: ifnull -> 889
      //   803: iload_1
      //   804: getstatic io/grpc/Status$Code.DEADLINE_EXCEEDED : Lio/grpc/Status$Code;
      //   807: invokevirtual value : ()I
      //   810: if_icmpne -> 816
      //   813: goto -> 818
      //   816: iconst_m1
      //   817: istore_2
      //   818: aload #6
      //   820: astore #9
      //   822: aload #6
      //   824: ifnonnull -> 839
      //   827: invokestatic newBuilder : ()Lcom/blued/im/private_chat/ReceiptOuterClass$ReceiptResponse$Builder;
      //   830: iload_2
      //   831: invokevirtual setCodeValue : (I)Lcom/blued/im/private_chat/ReceiptOuterClass$ReceiptResponse$Builder;
      //   834: invokevirtual build : ()Lcom/blued/im/private_chat/ReceiptOuterClass$ReceiptResponse;
      //   837: astore #9
      //   839: aload #9
      //   841: invokevirtual getCodeValue : ()I
      //   844: istore_2
      //   845: iload_2
      //   846: getstatic com/blued/im/private_chat/CodeOuterClass$Code.PRIVATE_SUCCESS : Lcom/blued/im/private_chat/CodeOuterClass$Code;
      //   849: invokevirtual getNumber : ()I
      //   852: if_icmpne -> 877
      //   855: aload_0
      //   856: getfield d : Lcom/blued/android/module/im/biz/receipt/OnReceiptResponseListener;
      //   859: aload #9
      //   861: invokevirtual getSeqnum : ()J
      //   864: aload #9
      //   866: invokevirtual getResponseTime : ()J
      //   869: invokeinterface onSuccess : (JJ)V
      //   874: goto -> 889
      //   877: aload_0
      //   878: getfield d : Lcom/blued/android/module/im/biz/receipt/OnReceiptResponseListener;
      //   881: iload_2
      //   882: aload #8
      //   884: invokeinterface onFailure : (ILjava/lang/Exception;)V
      //   889: invokestatic uptimeMillis : ()J
      //   892: lload #4
      //   894: lsub
      //   895: lstore #4
      //   897: aload #9
      //   899: ifnonnull -> 909
      //   902: aload #11
      //   904: astore #6
      //   906: goto -> 916
      //   909: aload #9
      //   911: invokevirtual getRequestId : ()Ljava/lang/String;
      //   914: astore #6
      //   916: invokestatic b : ()Lcom/blued/android/statistics/biz/Apm;
      //   919: astore #10
      //   921: aload_0
      //   922: getfield b : Z
      //   925: ifeq -> 936
      //   928: getstatic com/blued/das/apm/ApmProtos$GrpcRequestTypeProto$BUSINESS.GROUP_CHAT : Lcom/blued/das/apm/ApmProtos$GrpcRequestTypeProto$BUSINESS;
      //   931: astore #9
      //   933: goto -> 941
      //   936: getstatic com/blued/das/apm/ApmProtos$GrpcRequestTypeProto$BUSINESS.PRIVATE_CHAT : Lcom/blued/das/apm/ApmProtos$GrpcRequestTypeProto$BUSINESS;
      //   939: astore #9
      //   941: aload #10
      //   943: aload #9
      //   945: aload_0
      //   946: getfield a : Lcom/blued/android/module/im/biz/receipt/ReceiptBase;
      //   949: invokevirtual a : ()Ljava/lang/String;
      //   952: iload_1
      //   953: lload #4
      //   955: aload #6
      //   957: aload #8
      //   959: aload_0
      //   960: getfield a : Lcom/blued/android/module/im/biz/receipt/ReceiptBase;
      //   963: getfield a : Lcom/blued/android/module/im/grpc/ChannelManager;
      //   966: invokevirtual a : ()Ljava/lang/String;
      //   969: aload_0
      //   970: getfield a : Lcom/blued/android/module/im/biz/receipt/ReceiptBase;
      //   973: getfield a : Lcom/blued/android/module/im/grpc/ChannelManager;
      //   976: invokevirtual b : ()Ljava/lang/String;
      //   979: invokevirtual a : (Lcom/blued/das/apm/ApmProtos$GrpcRequestTypeProto$BUSINESS;Ljava/lang/String;IJLjava/lang/String;Ljava/lang/Throwable;Ljava/lang/String;Ljava/lang/String;)V
      //   982: invokestatic b : ()Z
      //   985: ifeq -> 1011
      //   988: invokestatic a : ()Lcom/blued/android/statistics/util/Logger;
      //   991: iconst_2
      //   992: anewarray java/lang/Object
      //   995: dup
      //   996: iconst_0
      //   997: ldc '>> SendReceiptMessage spendTime='
      //   999: aastore
      //   1000: dup
      //   1001: iconst_1
      //   1002: lload #4
      //   1004: invokestatic valueOf : (J)Ljava/lang/Long;
      //   1007: aastore
      //   1008: invokevirtual a : ([Ljava/lang/Object;)V
      //   1011: aload #7
      //   1013: athrow
      // Exception table:
      //   from	to	target	type
      //   78	145	427	java/lang/Exception
      //   78	145	415	finally
      //   160	166	410	java/lang/Exception
      //   160	166	777	finally
      //   172	192	410	java/lang/Exception
      //   172	192	777	finally
      //   438	452	777	finally
      //   458	469	777	finally
      //   482	489	777	finally
      //   495	504	766	finally
      //   514	520	766	finally
      //   526	546	766	finally
    }
  }
}


/* Location:              D:\code\BluedHook\classes.dex\com.soft.blued5032032-dex2jar.jar!\com\blued\android\module\im\biz\receipt\ReceiptBase.class
 * Java compiler version: 6 (50.0)
 * JD-Core Version:       1.1.3
 */