package com.amap.api.col.s;

import java.util.concurrent.ConcurrentHashMap;

public final class cc {
  public static String a = "9aj&#k81";
  
  public static String b = "IaHR0cDovL2xvZ3MuYW1hcC5jb20vd3MvbG9nL3VwbG9hZD9wcm9kdWN0PSVzJnR5cGU9JXMmcGxhdGZvcm09JXMmY2hhbm5lbD0lcyZzaWduPSVz";
  
  static byte[] c;
  
  public static boolean d = false;
  
  public static boolean e = false;
  
  public static final Integer f;
  
  public static final Integer g;
  
  public static final Integer h;
  
  public static final Integer i;
  
  public static final Integer j;
  
  private static String k = "ADgAIwBbAA8AagAIAHIAEwCFAD8AxABDAQcAIQEoADgBYAA8AZwAnwI7APADKwAHAzIADAM+AA9LWVc1a2NtOXBaQzV2Y3k1VFpYSjJhV05sVFdGdVlXZGxjZ1FaMlYwVTJWeWRtbGpaUUljR2h2Ym1VVWFYQm9iMjVsYzNWaWFXNW1id01ZMjl0TG1GdVpISnZhV1F1YVc1MFpYSnVZV3d1ZEdWc1pYQm9iMjU1TGtsVVpXeGxjR2h2Ym5ra1UzUjFZZ1FZMjl0TG1GdVpISnZhV1F1YVc1MFpYSnVZV3d1ZEdWc1pYQm9iMjU1TGtsUWFHOXVaVk4xWWtsdVptOGtVM1IxWWdHVkZKQlRsTkJRMVJKVDA1ZloyVjBSR1YyYVdObFNXUT1FWTI5dExtRnVaSEp2YVdRdWFXNTBaWEp1WVd3dWRHVnNaWEJvYjI1NUxrbFVaV3hsY0dodmJua0lZMjl0TG1GdVpISnZhV1F1YVc1MFpYSnVZV3d1ZEdWc1pYQm9iMjU1TGtsUWFHOXVaVk4xWWtsdVptOEVJbXRsZVNJNklpVnpJaXdpY0d4aGRHWnZjbTBpT2lKaGJtUnliMmxrSWl3aVpHbDFJam9pSlhNaUxDSndhMmNpT2lJbGN5SXNJbTF2WkdWc0lqb2lKWE1pTENKaGNIQnVZVzFsSWpvaUpYTWlMQ0poY0hCMlpYSnphVzl1SWpvaUpYTWlMQ0p6ZVhOMlpYSnphVzl1SWpvaUpYTWlMQUdJbXRsZVNJNklpVnpJaXdpY0d4aGRHWnZjbTBpT2lKaGJtUnliMmxrSWl3aVpHbDFJam9pSlhNaUxDSnRZV01pT2lJbGN5SXNJblJwWkNJNklpVnpJaXdpZFcxcFpIUWlPaUlsY3lJc0ltMWhiblZtWVdOMGRYSmxJam9pSlhNaUxDSmtaWFpwWTJVaU9pSWxjeUlzSW5OcGJTSTZJaVZ6SWl3aWNHdG5Jam9pSlhNaUxDSnRiMlJsYkNJNklpVnpJaXdpWVhCd2RtVnljMmx2YmlJNklpVnpJaXdpWVhCd2JtRnRaU0k2SWlWeklnPUlZV2xrUFFNZkhObGNtbGhiRDBRWVc1a2NtOXBaRjlwWkE=";
  
  private static volatile ConcurrentHashMap<String, String> l = new ConcurrentHashMap<String, String>(8);
  
  static {
    f = Integer.valueOf(1);
    g = Integer.valueOf(2);
    h = Integer.valueOf(3);
    i = Integer.valueOf(4);
    j = Integer.valueOf(5);
  }
  
  public static String a(String paramString) {
    // Byte code:
    //   0: ldc ''
    //   2: astore_2
    //   3: aload_2
    //   4: astore_1
    //   5: getstatic com/amap/api/col/s/cc.l : Ljava/util/concurrent/ConcurrentHashMap;
    //   8: astore_3
    //   9: aload_2
    //   10: astore_1
    //   11: aload_3
    //   12: monitorenter
    //   13: aload_2
    //   14: astore_1
    //   15: getstatic com/amap/api/col/s/cc.l : Ljava/util/concurrent/ConcurrentHashMap;
    //   18: ifnull -> 49
    //   21: aload_2
    //   22: astore_1
    //   23: getstatic com/amap/api/col/s/cc.l : Ljava/util/concurrent/ConcurrentHashMap;
    //   26: aload_0
    //   27: invokevirtual containsKey : (Ljava/lang/Object;)Z
    //   30: ifeq -> 49
    //   33: aload_2
    //   34: astore_1
    //   35: getstatic com/amap/api/col/s/cc.l : Ljava/util/concurrent/ConcurrentHashMap;
    //   38: aload_0
    //   39: invokevirtual get : (Ljava/lang/Object;)Ljava/lang/Object;
    //   42: checkcast java/lang/String
    //   45: astore_0
    //   46: goto -> 52
    //   49: ldc ''
    //   51: astore_0
    //   52: aload_3
    //   53: monitorexit
    //   54: aload_0
    //   55: areturn
    //   56: astore_2
    //   57: goto -> 63
    //   60: astore_2
    //   61: aload_1
    //   62: astore_0
    //   63: aload_0
    //   64: astore_1
    //   65: aload_3
    //   66: monitorexit
    //   67: aload_0
    //   68: astore_1
    //   69: aload_2
    //   70: athrow
    //   71: aload_1
    //   72: areturn
    //   73: astore_0
    //   74: goto -> 71
    // Exception table:
    //   from	to	target	type
    //   5	9	73	finally
    //   11	13	73	finally
    //   15	21	60	finally
    //   23	33	60	finally
    //   35	46	60	finally
    //   52	54	56	finally
    //   65	67	60	finally
    //   69	71	73	finally
  }
  
  public static void a(String paramString1, String paramString2) {
    try {
      return;
    } finally {
      paramString1 = null;
    } 
  }
  
  public static byte[] a(int paramInt) {
    if (c == null)
      c = bn.b(k); 
    byte[] arrayOfByte = new byte[4];
    System.arraycopy(c, paramInt * 4, arrayOfByte, 0, 4);
    paramInt = arrayOfByte[0];
    byte b = arrayOfByte[1];
    int i = (arrayOfByte[2] & 0xFF) * 256 + (arrayOfByte[3] & 0xFF);
    arrayOfByte = new byte[i];
    System.arraycopy(c, (paramInt & 0xFF) * 256 + (b & 0xFF), arrayOfByte, 0, i);
    return arrayOfByte;
  }
}


/* Location:              D:\code\BluedHook\classes.dex\com.soft.blued7646532-dex2jar.jar!\com\amap\api\col\s\cc.class
 * Java compiler version: 6 (50.0)
 * JD-Core Version:       1.1.3
 */