package com.geetest.onepassv2.g;

import android.net.Network;
import com.geetest.onelogin.j.h;
import java.io.InputStream;
import java.net.HttpURLConnection;
import javax.net.ssl.HostnameVerifier;
import javax.net.ssl.SSLSession;
import org.json.JSONObject;

public class a {
  public static String a(String paramString1, String paramString2, String paramString3, Network paramNetwork, String paramString4, String paramString5, com.geetest.onepassv2.a.a parama) {
    // Byte code:
    //   0: new java/lang/StringBuilder
    //   3: dup
    //   4: invokespecial <init> : ()V
    //   7: astore #8
    //   9: aload #8
    //   11: ldc '当前请求 '
    //   13: invokevirtual append : (Ljava/lang/String;)Ljava/lang/StringBuilder;
    //   16: pop
    //   17: aload #8
    //   19: aload_0
    //   20: invokevirtual append : (Ljava/lang/String;)Ljava/lang/StringBuilder;
    //   23: pop
    //   24: aload #8
    //   26: ldc ' 开始请求'
    //   28: invokevirtual append : (Ljava/lang/String;)Ljava/lang/StringBuilder;
    //   31: pop
    //   32: aload #8
    //   34: invokevirtual toString : ()Ljava/lang/String;
    //   37: invokestatic b : (Ljava/lang/String;)V
    //   40: new java/lang/StringBuilder
    //   43: dup
    //   44: invokespecial <init> : ()V
    //   47: astore #8
    //   49: aload #8
    //   51: ldc '设置的超时时间为: '
    //   53: invokevirtual append : (Ljava/lang/String;)Ljava/lang/StringBuilder;
    //   56: pop
    //   57: aload #8
    //   59: aload #6
    //   61: invokevirtual b : ()I
    //   64: invokevirtual append : (I)Ljava/lang/StringBuilder;
    //   67: pop
    //   68: aload #8
    //   70: invokevirtual toString : ()Ljava/lang/String;
    //   73: invokestatic b : (Ljava/lang/String;)V
    //   76: aload #6
    //   78: aload_2
    //   79: invokevirtual k : (Ljava/lang/String;)V
    //   82: aload #6
    //   84: ldc '30100'
    //   86: invokevirtual l : (Ljava/lang/String;)V
    //   89: aload #6
    //   91: ldc 'v1.5'
    //   93: invokevirtual m : (Ljava/lang/String;)V
    //   96: aload #6
    //   98: aload_1
    //   99: invokevirtual n : (Ljava/lang/String;)V
    //   102: aload #6
    //   104: aload #4
    //   106: invokevirtual o : (Ljava/lang/String;)V
    //   109: aload #6
    //   111: aload #5
    //   113: invokevirtual p : (Ljava/lang/String;)V
    //   116: aload_0
    //   117: invokestatic a : (Ljava/lang/String;)Ljava/net/URL;
    //   120: astore #13
    //   122: ldc 'https'
    //   124: aload #13
    //   126: invokevirtual getProtocol : ()Ljava/lang/String;
    //   129: invokevirtual toLowerCase : ()Ljava/lang/String;
    //   132: invokevirtual equals : (Ljava/lang/Object;)Z
    //   135: istore #7
    //   137: ldc ''
    //   139: astore #12
    //   141: iload #7
    //   143: ifeq -> 583
    //   146: ldc 'TLS'
    //   148: invokestatic getInstance : (Ljava/lang/String;)Ljavax/net/ssl/SSLContext;
    //   151: astore #14
    //   153: new com/geetest/onelogin/j/q
    //   156: dup
    //   157: invokespecial <init> : ()V
    //   160: astore #15
    //   162: aconst_null
    //   163: astore #11
    //   165: aconst_null
    //   166: astore #10
    //   168: aload #10
    //   170: astore #9
    //   172: aload #11
    //   174: astore #8
    //   176: aload #14
    //   178: aconst_null
    //   179: iconst_1
    //   180: anewarray javax/net/ssl/TrustManager
    //   183: dup
    //   184: iconst_0
    //   185: aload #15
    //   187: aastore
    //   188: aconst_null
    //   189: invokevirtual init : ([Ljavax/net/ssl/KeyManager;[Ljavax/net/ssl/TrustManager;Ljava/security/SecureRandom;)V
    //   192: aload #10
    //   194: astore #9
    //   196: aload #11
    //   198: astore #8
    //   200: aload #14
    //   202: invokevirtual getSocketFactory : ()Ljavax/net/ssl/SSLSocketFactory;
    //   205: invokestatic setDefaultSSLSocketFactory : (Ljavax/net/ssl/SSLSocketFactory;)V
    //   208: aload #10
    //   210: astore #9
    //   212: aload #11
    //   214: astore #8
    //   216: new com/geetest/onepassv2/g/a$1
    //   219: dup
    //   220: invokespecial <init> : ()V
    //   223: invokestatic setDefaultHostnameVerifier : (Ljavax/net/ssl/HostnameVerifier;)V
    //   226: aload #10
    //   228: astore #9
    //   230: aload #11
    //   232: astore #8
    //   234: aload #13
    //   236: invokevirtual openConnection : ()Ljava/net/URLConnection;
    //   239: checkcast javax/net/ssl/HttpsURLConnection
    //   242: astore #10
    //   244: aload_3
    //   245: ifnull -> 269
    //   248: getstatic android/os/Build$VERSION.SDK_INT : I
    //   251: bipush #21
    //   253: if_icmplt -> 921
    //   256: aload_3
    //   257: aload #13
    //   259: invokevirtual openConnection : (Ljava/net/URL;)Ljava/net/URLConnection;
    //   262: checkcast javax/net/ssl/HttpsURLConnection
    //   265: astore_3
    //   266: goto -> 278
    //   269: aload #13
    //   271: invokevirtual openConnection : ()Ljava/net/URLConnection;
    //   274: checkcast javax/net/ssl/HttpsURLConnection
    //   277: astore_3
    //   278: goto -> 924
    //   281: aload_3
    //   282: astore #9
    //   284: aload_3
    //   285: astore #8
    //   287: aload_3
    //   288: iconst_1
    //   289: invokevirtual setDoInput : (Z)V
    //   292: aload_3
    //   293: astore #9
    //   295: aload_3
    //   296: astore #8
    //   298: aload_3
    //   299: iconst_0
    //   300: invokevirtual setDoOutput : (Z)V
    //   303: aload_3
    //   304: astore #9
    //   306: aload_3
    //   307: astore #8
    //   309: aload_3
    //   310: ldc 'GET'
    //   312: invokevirtual setRequestMethod : (Ljava/lang/String;)V
    //   315: aload_3
    //   316: astore #9
    //   318: aload_3
    //   319: astore #8
    //   321: aload_3
    //   322: aload #6
    //   324: invokevirtual b : ()I
    //   327: invokevirtual setConnectTimeout : (I)V
    //   330: aload_3
    //   331: astore #9
    //   333: aload_3
    //   334: astore #8
    //   336: aload_3
    //   337: aload #6
    //   339: invokevirtual b : ()I
    //   342: invokevirtual setReadTimeout : (I)V
    //   345: aload_3
    //   346: astore #9
    //   348: aload_3
    //   349: astore #8
    //   351: aload_3
    //   352: ldc 'client_id'
    //   354: aload_2
    //   355: invokevirtual setRequestProperty : (Ljava/lang/String;Ljava/lang/String;)V
    //   358: aload_3
    //   359: astore #9
    //   361: aload_3
    //   362: astore #8
    //   364: aload_3
    //   365: ldc 'client_type'
    //   367: ldc '30100'
    //   369: invokevirtual setRequestProperty : (Ljava/lang/String;Ljava/lang/String;)V
    //   372: aload_3
    //   373: astore #9
    //   375: aload_3
    //   376: astore #8
    //   378: aload_3
    //   379: ldc 'version'
    //   381: ldc 'v1.5'
    //   383: invokevirtual setRequestProperty : (Ljava/lang/String;Ljava/lang/String;)V
    //   386: aload_3
    //   387: astore #9
    //   389: aload_3
    //   390: astore #8
    //   392: aload_3
    //   393: ldc 'Authorization'
    //   395: aload_1
    //   396: invokevirtual setRequestProperty : (Ljava/lang/String;Ljava/lang/String;)V
    //   399: aload_3
    //   400: astore #9
    //   402: aload_3
    //   403: astore #8
    //   405: aload_3
    //   406: ldc 'packname'
    //   408: aload #4
    //   410: invokevirtual setRequestProperty : (Ljava/lang/String;Ljava/lang/String;)V
    //   413: aload_3
    //   414: astore #9
    //   416: aload_3
    //   417: astore #8
    //   419: aload_3
    //   420: ldc 'packsign'
    //   422: aload #5
    //   424: invokevirtual setRequestProperty : (Ljava/lang/String;Ljava/lang/String;)V
    //   427: aload_3
    //   428: astore #9
    //   430: aload_3
    //   431: astore #8
    //   433: aload_3
    //   434: invokevirtual connect : ()V
    //   437: aload_3
    //   438: astore #8
    //   440: aload_0
    //   441: aload_3
    //   442: invokestatic a : (Ljava/lang/String;Ljava/net/HttpURLConnection;)Ljava/lang/String;
    //   445: astore_1
    //   446: aload_3
    //   447: ifnull -> 454
    //   450: aload_3
    //   451: invokevirtual disconnect : ()V
    //   454: aload_1
    //   455: areturn
    //   456: astore_1
    //   457: goto -> 498
    //   460: astore_0
    //   461: aload #10
    //   463: astore #8
    //   465: goto -> 571
    //   468: astore_1
    //   469: aload #10
    //   471: astore_3
    //   472: goto -> 498
    //   475: astore_1
    //   476: aload #9
    //   478: astore_3
    //   479: goto -> 485
    //   482: astore_1
    //   483: aconst_null
    //   484: astore_3
    //   485: goto -> 498
    //   488: astore_0
    //   489: aconst_null
    //   490: astore #8
    //   492: goto -> 571
    //   495: astore_1
    //   496: aconst_null
    //   497: astore_3
    //   498: aload_3
    //   499: astore #8
    //   501: new java/lang/StringBuilder
    //   504: dup
    //   505: invokespecial <init> : ()V
    //   508: astore_2
    //   509: aload_3
    //   510: astore #8
    //   512: aload_2
    //   513: ldc 'url: '
    //   515: invokevirtual append : (Ljava/lang/String;)Ljava/lang/StringBuilder;
    //   518: pop
    //   519: aload_3
    //   520: astore #8
    //   522: aload_2
    //   523: aload_0
    //   524: invokevirtual append : (Ljava/lang/String;)Ljava/lang/StringBuilder;
    //   527: pop
    //   528: aload_3
    //   529: astore #8
    //   531: aload_2
    //   532: ldc ', error: '
    //   534: invokevirtual append : (Ljava/lang/String;)Ljava/lang/StringBuilder;
    //   537: pop
    //   538: aload_3
    //   539: astore #8
    //   541: aload_2
    //   542: aload_1
    //   543: invokevirtual toString : ()Ljava/lang/String;
    //   546: invokevirtual append : (Ljava/lang/String;)Ljava/lang/StringBuilder;
    //   549: pop
    //   550: aload_3
    //   551: astore #8
    //   553: aload_2
    //   554: invokevirtual toString : ()Ljava/lang/String;
    //   557: invokestatic c : (Ljava/lang/String;)V
    //   560: aload_3
    //   561: ifnull -> 927
    //   564: aload_3
    //   565: invokevirtual disconnect : ()V
    //   568: aload #12
    //   570: areturn
    //   571: aload #8
    //   573: ifnull -> 581
    //   576: aload #8
    //   578: invokevirtual disconnect : ()V
    //   581: aload_0
    //   582: athrow
    //   583: aconst_null
    //   584: astore #8
    //   586: aconst_null
    //   587: astore #4
    //   589: aload #13
    //   591: invokevirtual openConnection : ()Ljava/net/URLConnection;
    //   594: checkcast java/net/HttpURLConnection
    //   597: astore #5
    //   599: aload #5
    //   601: iconst_1
    //   602: invokevirtual setDoInput : (Z)V
    //   605: aload #5
    //   607: iconst_0
    //   608: invokevirtual setDoOutput : (Z)V
    //   611: aload #5
    //   613: ldc 'GET'
    //   615: invokevirtual setRequestMethod : (Ljava/lang/String;)V
    //   618: aload_3
    //   619: ifnull -> 643
    //   622: getstatic android/os/Build$VERSION.SDK_INT : I
    //   625: bipush #21
    //   627: if_icmplt -> 934
    //   630: aload_3
    //   631: aload #13
    //   633: invokevirtual openConnection : (Ljava/net/URL;)Ljava/net/URLConnection;
    //   636: checkcast java/net/HttpURLConnection
    //   639: astore_3
    //   640: goto -> 652
    //   643: aload #13
    //   645: invokevirtual openConnection : ()Ljava/net/URLConnection;
    //   648: checkcast java/net/HttpURLConnection
    //   651: astore_3
    //   652: aload_3
    //   653: astore #4
    //   655: aload_3
    //   656: astore #8
    //   658: aload_3
    //   659: aload #6
    //   661: invokevirtual b : ()I
    //   664: invokevirtual setConnectTimeout : (I)V
    //   667: aload_3
    //   668: astore #4
    //   670: aload_3
    //   671: astore #8
    //   673: aload_3
    //   674: aload #6
    //   676: invokevirtual b : ()I
    //   679: invokevirtual setReadTimeout : (I)V
    //   682: aload_3
    //   683: astore #4
    //   685: aload_3
    //   686: astore #8
    //   688: aload_3
    //   689: ldc 'client_id'
    //   691: aload_2
    //   692: invokevirtual setRequestProperty : (Ljava/lang/String;Ljava/lang/String;)V
    //   695: aload_3
    //   696: astore #4
    //   698: aload_3
    //   699: astore #8
    //   701: aload_3
    //   702: ldc 'client_type'
    //   704: ldc '30100'
    //   706: invokevirtual setRequestProperty : (Ljava/lang/String;Ljava/lang/String;)V
    //   709: aload_3
    //   710: astore #4
    //   712: aload_3
    //   713: astore #8
    //   715: aload_3
    //   716: ldc 'version'
    //   718: ldc 'v1.5'
    //   720: invokevirtual setRequestProperty : (Ljava/lang/String;Ljava/lang/String;)V
    //   723: aload_3
    //   724: astore #4
    //   726: aload_3
    //   727: astore #8
    //   729: aload_3
    //   730: ldc 'Authorization'
    //   732: aload_1
    //   733: invokevirtual setRequestProperty : (Ljava/lang/String;Ljava/lang/String;)V
    //   736: aload_3
    //   737: astore #4
    //   739: aload_3
    //   740: astore #8
    //   742: aload_3
    //   743: invokevirtual connect : ()V
    //   746: aload_3
    //   747: astore #4
    //   749: aload_3
    //   750: astore #8
    //   752: aload_0
    //   753: aload_3
    //   754: invokestatic a : (Ljava/lang/String;Ljava/net/HttpURLConnection;)Ljava/lang/String;
    //   757: astore_1
    //   758: aload_3
    //   759: ifnull -> 766
    //   762: aload_3
    //   763: invokevirtual disconnect : ()V
    //   766: aload_1
    //   767: areturn
    //   768: astore_0
    //   769: aload #5
    //   771: astore #4
    //   773: goto -> 870
    //   776: astore_1
    //   777: aload #5
    //   779: astore #8
    //   781: goto -> 789
    //   784: astore_0
    //   785: goto -> 870
    //   788: astore_1
    //   789: aload #8
    //   791: astore #4
    //   793: new java/lang/StringBuilder
    //   796: dup
    //   797: invokespecial <init> : ()V
    //   800: astore_2
    //   801: aload #8
    //   803: astore #4
    //   805: aload_2
    //   806: ldc 'url: '
    //   808: invokevirtual append : (Ljava/lang/String;)Ljava/lang/StringBuilder;
    //   811: pop
    //   812: aload #8
    //   814: astore #4
    //   816: aload_2
    //   817: aload_0
    //   818: invokevirtual append : (Ljava/lang/String;)Ljava/lang/StringBuilder;
    //   821: pop
    //   822: aload #8
    //   824: astore #4
    //   826: aload_2
    //   827: ldc ', error: '
    //   829: invokevirtual append : (Ljava/lang/String;)Ljava/lang/StringBuilder;
    //   832: pop
    //   833: aload #8
    //   835: astore #4
    //   837: aload_2
    //   838: aload_1
    //   839: invokevirtual toString : ()Ljava/lang/String;
    //   842: invokevirtual append : (Ljava/lang/String;)Ljava/lang/StringBuilder;
    //   845: pop
    //   846: aload #8
    //   848: astore #4
    //   850: aload_2
    //   851: invokevirtual toString : ()Ljava/lang/String;
    //   854: invokestatic c : (Ljava/lang/String;)V
    //   857: aload #8
    //   859: ifnull -> 940
    //   862: aload #8
    //   864: invokevirtual disconnect : ()V
    //   867: aload #12
    //   869: areturn
    //   870: aload #4
    //   872: ifnull -> 880
    //   875: aload #4
    //   877: invokevirtual disconnect : ()V
    //   880: aload_0
    //   881: athrow
    //   882: astore_0
    //   883: goto -> 887
    //   886: astore_0
    //   887: new java/lang/StringBuilder
    //   890: dup
    //   891: invokespecial <init> : ()V
    //   894: astore_1
    //   895: aload_1
    //   896: ldc 'error: '
    //   898: invokevirtual append : (Ljava/lang/String;)Ljava/lang/StringBuilder;
    //   901: pop
    //   902: aload_1
    //   903: aload_0
    //   904: invokevirtual toString : ()Ljava/lang/String;
    //   907: invokevirtual append : (Ljava/lang/String;)Ljava/lang/StringBuilder;
    //   910: pop
    //   911: aload_1
    //   912: invokevirtual toString : ()Ljava/lang/String;
    //   915: invokestatic c : (Ljava/lang/String;)V
    //   918: ldc ''
    //   920: areturn
    //   921: aload #10
    //   923: astore_3
    //   924: goto -> 281
    //   927: aload #12
    //   929: areturn
    //   930: astore_0
    //   931: goto -> 571
    //   934: aload #5
    //   936: astore_3
    //   937: goto -> 652
    //   940: aload #12
    //   942: areturn
    // Exception table:
    //   from	to	target	type
    //   122	137	886	java/lang/Exception
    //   146	153	495	java/lang/Exception
    //   146	153	488	finally
    //   153	162	482	java/lang/Exception
    //   153	162	488	finally
    //   176	192	475	java/lang/Exception
    //   176	192	930	finally
    //   200	208	475	java/lang/Exception
    //   200	208	930	finally
    //   216	226	475	java/lang/Exception
    //   216	226	930	finally
    //   234	244	475	java/lang/Exception
    //   234	244	930	finally
    //   248	266	468	java/lang/Exception
    //   248	266	460	finally
    //   269	278	468	java/lang/Exception
    //   269	278	460	finally
    //   287	292	475	java/lang/Exception
    //   287	292	930	finally
    //   298	303	475	java/lang/Exception
    //   298	303	930	finally
    //   309	315	475	java/lang/Exception
    //   309	315	930	finally
    //   321	330	475	java/lang/Exception
    //   321	330	930	finally
    //   336	345	475	java/lang/Exception
    //   336	345	930	finally
    //   351	358	475	java/lang/Exception
    //   351	358	930	finally
    //   364	372	475	java/lang/Exception
    //   364	372	930	finally
    //   378	386	475	java/lang/Exception
    //   378	386	930	finally
    //   392	399	475	java/lang/Exception
    //   392	399	930	finally
    //   405	413	475	java/lang/Exception
    //   405	413	930	finally
    //   419	427	475	java/lang/Exception
    //   419	427	930	finally
    //   433	437	475	java/lang/Exception
    //   433	437	930	finally
    //   440	446	456	java/lang/Exception
    //   440	446	930	finally
    //   450	454	882	java/lang/Exception
    //   501	509	930	finally
    //   512	519	930	finally
    //   522	528	930	finally
    //   531	538	930	finally
    //   541	550	930	finally
    //   553	560	930	finally
    //   564	568	882	java/lang/Exception
    //   576	581	882	java/lang/Exception
    //   581	583	882	java/lang/Exception
    //   589	599	788	java/lang/Exception
    //   589	599	784	finally
    //   599	618	776	java/lang/Exception
    //   599	618	768	finally
    //   622	640	776	java/lang/Exception
    //   622	640	768	finally
    //   643	652	776	java/lang/Exception
    //   643	652	768	finally
    //   658	667	788	java/lang/Exception
    //   658	667	784	finally
    //   673	682	788	java/lang/Exception
    //   673	682	784	finally
    //   688	695	788	java/lang/Exception
    //   688	695	784	finally
    //   701	709	788	java/lang/Exception
    //   701	709	784	finally
    //   715	723	788	java/lang/Exception
    //   715	723	784	finally
    //   729	736	788	java/lang/Exception
    //   729	736	784	finally
    //   742	746	788	java/lang/Exception
    //   742	746	784	finally
    //   752	758	788	java/lang/Exception
    //   752	758	784	finally
    //   762	766	882	java/lang/Exception
    //   793	801	784	finally
    //   805	812	784	finally
    //   816	822	784	finally
    //   826	833	784	finally
    //   837	846	784	finally
    //   850	857	784	finally
    //   862	867	882	java/lang/Exception
    //   875	880	882	java/lang/Exception
    //   880	882	882	java/lang/Exception
  }
  
  private static String a(String paramString, HttpURLConnection paramHttpURLConnection) {
    byte[] arrayOfByte = new byte[1024];
    StringBuffer stringBuffer = new StringBuffer();
    try {
      InputStream inputStream = paramHttpURLConnection.getInputStream();
      while (true) {
        int i = inputStream.read(arrayOfByte);
        if (i != -1) {
          stringBuffer.append(new String(arrayOfByte, 0, i, "UTF-8"));
          continue;
        } 
        inputStream.close();
        i = paramHttpURLConnection.getResponseCode();
        if (i == 200)
          return stringBuffer.toString(); 
        StringBuilder stringBuilder = new StringBuilder();
        stringBuilder.append("url: ");
        stringBuilder.append(paramString);
        stringBuilder.append(", responseCode: ");
        stringBuilder.append(i);
        h.c(stringBuilder.toString());
        return "";
      } 
    } catch (Exception exception) {
      StringBuilder stringBuilder = new StringBuilder();
      stringBuilder.append("url: ");
      stringBuilder.append(paramString);
      stringBuilder.append(", error: ");
      stringBuilder.append(exception.toString());
      h.c(stringBuilder.toString());
      return "";
    } 
  }
  
  public static String a(String paramString, JSONObject paramJSONObject, Network paramNetwork, int paramInt) {
    // Byte code:
    //   0: new java/lang/StringBuilder
    //   3: dup
    //   4: invokespecial <init> : ()V
    //   7: astore #6
    //   9: aload #6
    //   11: ldc '当前请求 '
    //   13: invokevirtual append : (Ljava/lang/String;)Ljava/lang/StringBuilder;
    //   16: pop
    //   17: aload #6
    //   19: aload_0
    //   20: invokevirtual append : (Ljava/lang/String;)Ljava/lang/StringBuilder;
    //   23: pop
    //   24: aload #6
    //   26: ldc ' 开始请求, 超时时间为: '
    //   28: invokevirtual append : (Ljava/lang/String;)Ljava/lang/StringBuilder;
    //   31: pop
    //   32: aload #6
    //   34: iload_3
    //   35: invokevirtual append : (I)Ljava/lang/StringBuilder;
    //   38: pop
    //   39: aload #6
    //   41: invokevirtual toString : ()Ljava/lang/String;
    //   44: invokestatic b : (Ljava/lang/String;)V
    //   47: aload_0
    //   48: invokestatic a : (Ljava/lang/String;)Ljava/net/URL;
    //   51: astore #10
    //   53: ldc 'https'
    //   55: aload #10
    //   57: invokevirtual getProtocol : ()Ljava/lang/String;
    //   60: invokevirtual toLowerCase : ()Ljava/lang/String;
    //   63: invokevirtual equals : (Ljava/lang/Object;)Z
    //   66: istore #5
    //   68: aconst_null
    //   69: astore #9
    //   71: aconst_null
    //   72: astore #6
    //   74: aconst_null
    //   75: astore #8
    //   77: aconst_null
    //   78: astore #7
    //   80: iload #5
    //   82: ifeq -> 827
    //   85: aload #7
    //   87: astore #6
    //   89: aload #9
    //   91: astore #8
    //   93: ldc 'TLS'
    //   95: invokestatic getInstance : (Ljava/lang/String;)Ljavax/net/ssl/SSLContext;
    //   98: astore #11
    //   100: aload #7
    //   102: astore #6
    //   104: aload #9
    //   106: astore #8
    //   108: aload #11
    //   110: aconst_null
    //   111: iconst_1
    //   112: anewarray javax/net/ssl/TrustManager
    //   115: dup
    //   116: iconst_0
    //   117: new com/geetest/onelogin/j/q
    //   120: dup
    //   121: invokespecial <init> : ()V
    //   124: aastore
    //   125: aconst_null
    //   126: invokevirtual init : ([Ljavax/net/ssl/KeyManager;[Ljavax/net/ssl/TrustManager;Ljava/security/SecureRandom;)V
    //   129: aload #7
    //   131: astore #6
    //   133: aload #9
    //   135: astore #8
    //   137: aload #11
    //   139: invokevirtual getSocketFactory : ()Ljavax/net/ssl/SSLSocketFactory;
    //   142: invokestatic setDefaultSSLSocketFactory : (Ljavax/net/ssl/SSLSocketFactory;)V
    //   145: aload #7
    //   147: astore #6
    //   149: aload #9
    //   151: astore #8
    //   153: new com/geetest/onepassv2/g/a$2
    //   156: dup
    //   157: invokespecial <init> : ()V
    //   160: invokestatic setDefaultHostnameVerifier : (Ljavax/net/ssl/HostnameVerifier;)V
    //   163: aload #7
    //   165: astore #6
    //   167: aload #9
    //   169: astore #8
    //   171: aload #10
    //   173: invokevirtual openConnection : ()Ljava/net/URLConnection;
    //   176: checkcast javax/net/ssl/HttpsURLConnection
    //   179: astore #7
    //   181: aload_2
    //   182: ifnull -> 207
    //   185: getstatic android/os/Build$VERSION.SDK_INT : I
    //   188: bipush #21
    //   190: if_icmplt -> 1519
    //   193: aload_2
    //   194: aload #10
    //   196: invokevirtual openConnection : (Ljava/net/URL;)Ljava/net/URLConnection;
    //   199: checkcast javax/net/ssl/HttpsURLConnection
    //   202: astore #6
    //   204: goto -> 217
    //   207: aload #10
    //   209: invokevirtual openConnection : ()Ljava/net/URLConnection;
    //   212: checkcast javax/net/ssl/HttpsURLConnection
    //   215: astore #6
    //   217: aload #6
    //   219: astore #7
    //   221: aload #7
    //   223: astore #6
    //   225: aload #7
    //   227: astore #8
    //   229: aload #7
    //   231: iload_3
    //   232: invokevirtual setConnectTimeout : (I)V
    //   235: aload #7
    //   237: astore #6
    //   239: aload #7
    //   241: astore #8
    //   243: aload #7
    //   245: iload_3
    //   246: invokevirtual setReadTimeout : (I)V
    //   249: aload #7
    //   251: astore #6
    //   253: aload #7
    //   255: astore #8
    //   257: aload #7
    //   259: iconst_1
    //   260: invokevirtual setDoInput : (Z)V
    //   263: aload #7
    //   265: astore #6
    //   267: aload #7
    //   269: astore #8
    //   271: aload #7
    //   273: iconst_1
    //   274: invokevirtual setDoOutput : (Z)V
    //   277: aload #7
    //   279: astore #6
    //   281: aload #7
    //   283: astore #8
    //   285: aload #7
    //   287: ldc 'POST'
    //   289: invokevirtual setRequestMethod : (Ljava/lang/String;)V
    //   292: aload #7
    //   294: astore #6
    //   296: aload #7
    //   298: astore #8
    //   300: aload #7
    //   302: iconst_0
    //   303: invokevirtual setUseCaches : (Z)V
    //   306: aload #7
    //   308: astore #6
    //   310: aload #7
    //   312: astore #8
    //   314: aload #7
    //   316: invokevirtual connect : ()V
    //   319: aload_1
    //   320: ifnull -> 384
    //   323: aload #7
    //   325: astore #6
    //   327: aload #7
    //   329: astore #8
    //   331: aload #7
    //   333: invokevirtual getOutputStream : ()Ljava/io/OutputStream;
    //   336: astore #9
    //   338: aload #7
    //   340: astore #6
    //   342: aload #7
    //   344: astore #8
    //   346: aload #9
    //   348: aload_1
    //   349: invokevirtual toString : ()Ljava/lang/String;
    //   352: invokevirtual getBytes : ()[B
    //   355: invokevirtual write : ([B)V
    //   358: aload #7
    //   360: astore #6
    //   362: aload #7
    //   364: astore #8
    //   366: aload #9
    //   368: invokevirtual flush : ()V
    //   371: aload #7
    //   373: astore #6
    //   375: aload #7
    //   377: astore #8
    //   379: aload #9
    //   381: invokevirtual close : ()V
    //   384: aload #7
    //   386: astore #6
    //   388: aload #7
    //   390: astore #8
    //   392: aload #7
    //   394: invokevirtual getResponseCode : ()I
    //   397: istore #4
    //   399: iload #4
    //   401: sipush #302
    //   404: if_icmpne -> 572
    //   407: aload_2
    //   408: ifnull -> 491
    //   411: aload #7
    //   413: astore #6
    //   415: aload #7
    //   417: astore #8
    //   419: getstatic android/os/Build$VERSION.SDK_INT : I
    //   422: bipush #21
    //   424: if_icmplt -> 572
    //   427: aload #7
    //   429: astore #6
    //   431: aload #7
    //   433: astore #8
    //   435: aload_2
    //   436: new java/net/URL
    //   439: dup
    //   440: aload #7
    //   442: ldc_w 'Location'
    //   445: invokevirtual getHeaderField : (Ljava/lang/String;)Ljava/lang/String;
    //   448: invokespecial <init> : (Ljava/lang/String;)V
    //   451: invokevirtual openConnection : (Ljava/net/URL;)Ljava/net/URLConnection;
    //   454: checkcast javax/net/ssl/HttpsURLConnection
    //   457: astore_1
    //   458: aload_1
    //   459: astore_2
    //   460: aload_1
    //   461: astore #6
    //   463: aload_1
    //   464: iload_3
    //   465: invokevirtual setConnectTimeout : (I)V
    //   468: aload_1
    //   469: astore_2
    //   470: aload_1
    //   471: astore #6
    //   473: aload_1
    //   474: iload_3
    //   475: invokevirtual setReadTimeout : (I)V
    //   478: aload_1
    //   479: astore_2
    //   480: aload_1
    //   481: astore #6
    //   483: aload_1
    //   484: invokevirtual getResponseCode : ()I
    //   487: istore_3
    //   488: goto -> 551
    //   491: aload #7
    //   493: astore #6
    //   495: aload #7
    //   497: astore #8
    //   499: new java/net/URL
    //   502: dup
    //   503: aload #7
    //   505: ldc_w 'Location'
    //   508: invokevirtual getHeaderField : (Ljava/lang/String;)Ljava/lang/String;
    //   511: invokespecial <init> : (Ljava/lang/String;)V
    //   514: invokevirtual openConnection : ()Ljava/net/URLConnection;
    //   517: checkcast javax/net/ssl/HttpsURLConnection
    //   520: astore_1
    //   521: aload_1
    //   522: astore_2
    //   523: aload_1
    //   524: astore #6
    //   526: aload_1
    //   527: iload_3
    //   528: invokevirtual setConnectTimeout : (I)V
    //   531: aload_1
    //   532: astore_2
    //   533: aload_1
    //   534: astore #6
    //   536: aload_1
    //   537: iload_3
    //   538: invokevirtual setReadTimeout : (I)V
    //   541: aload_1
    //   542: astore_2
    //   543: aload_1
    //   544: astore #6
    //   546: aload_1
    //   547: invokevirtual getResponseCode : ()I
    //   550: istore_3
    //   551: aload_1
    //   552: astore #7
    //   554: goto -> 575
    //   557: astore_0
    //   558: aload_2
    //   559: astore #6
    //   561: goto -> 815
    //   564: astore_1
    //   565: aload #6
    //   567: astore #8
    //   569: goto -> 734
    //   572: iload #4
    //   574: istore_3
    //   575: iload_3
    //   576: sipush #200
    //   579: if_icmpne -> 611
    //   582: aload #7
    //   584: astore #6
    //   586: aload #7
    //   588: astore #8
    //   590: aload #7
    //   592: invokevirtual getInputStream : ()Ljava/io/InputStream;
    //   595: invokestatic a : (Ljava/io/InputStream;)Ljava/lang/String;
    //   598: astore_1
    //   599: aload #7
    //   601: ifnull -> 609
    //   604: aload #7
    //   606: invokevirtual disconnect : ()V
    //   609: aload_1
    //   610: areturn
    //   611: aload #7
    //   613: astore #6
    //   615: aload #7
    //   617: astore #8
    //   619: new java/lang/StringBuilder
    //   622: dup
    //   623: invokespecial <init> : ()V
    //   626: astore_1
    //   627: aload #7
    //   629: astore #6
    //   631: aload #7
    //   633: astore #8
    //   635: aload_1
    //   636: ldc 'url: '
    //   638: invokevirtual append : (Ljava/lang/String;)Ljava/lang/StringBuilder;
    //   641: pop
    //   642: aload #7
    //   644: astore #6
    //   646: aload #7
    //   648: astore #8
    //   650: aload_1
    //   651: aload_0
    //   652: invokevirtual append : (Ljava/lang/String;)Ljava/lang/StringBuilder;
    //   655: pop
    //   656: aload #7
    //   658: astore #6
    //   660: aload #7
    //   662: astore #8
    //   664: aload_1
    //   665: ldc ', responseCode: '
    //   667: invokevirtual append : (Ljava/lang/String;)Ljava/lang/StringBuilder;
    //   670: pop
    //   671: aload #7
    //   673: astore #6
    //   675: aload #7
    //   677: astore #8
    //   679: aload_1
    //   680: iload_3
    //   681: invokevirtual append : (I)Ljava/lang/StringBuilder;
    //   684: pop
    //   685: aload #7
    //   687: astore #6
    //   689: aload #7
    //   691: astore #8
    //   693: aload_1
    //   694: invokevirtual toString : ()Ljava/lang/String;
    //   697: invokestatic c : (Ljava/lang/String;)V
    //   700: aload #7
    //   702: ifnull -> 710
    //   705: aload #7
    //   707: invokevirtual disconnect : ()V
    //   710: ldc ''
    //   712: areturn
    //   713: astore_0
    //   714: aload #7
    //   716: astore #6
    //   718: goto -> 815
    //   721: astore_1
    //   722: aload #7
    //   724: astore #8
    //   726: goto -> 734
    //   729: astore_0
    //   730: goto -> 815
    //   733: astore_1
    //   734: aload #8
    //   736: astore #6
    //   738: new java/lang/StringBuilder
    //   741: dup
    //   742: invokespecial <init> : ()V
    //   745: astore_2
    //   746: aload #8
    //   748: astore #6
    //   750: aload_2
    //   751: ldc 'url: '
    //   753: invokevirtual append : (Ljava/lang/String;)Ljava/lang/StringBuilder;
    //   756: pop
    //   757: aload #8
    //   759: astore #6
    //   761: aload_2
    //   762: aload_0
    //   763: invokevirtual append : (Ljava/lang/String;)Ljava/lang/StringBuilder;
    //   766: pop
    //   767: aload #8
    //   769: astore #6
    //   771: aload_2
    //   772: ldc ', error: '
    //   774: invokevirtual append : (Ljava/lang/String;)Ljava/lang/StringBuilder;
    //   777: pop
    //   778: aload #8
    //   780: astore #6
    //   782: aload_2
    //   783: aload_1
    //   784: invokevirtual toString : ()Ljava/lang/String;
    //   787: invokevirtual append : (Ljava/lang/String;)Ljava/lang/StringBuilder;
    //   790: pop
    //   791: aload #8
    //   793: astore #6
    //   795: aload_2
    //   796: invokevirtual toString : ()Ljava/lang/String;
    //   799: invokestatic c : (Ljava/lang/String;)V
    //   802: aload #8
    //   804: ifnull -> 1522
    //   807: aload #8
    //   809: invokevirtual disconnect : ()V
    //   812: ldc ''
    //   814: areturn
    //   815: aload #6
    //   817: ifnull -> 825
    //   820: aload #6
    //   822: invokevirtual disconnect : ()V
    //   825: aload_0
    //   826: athrow
    //   827: aload #10
    //   829: invokevirtual openConnection : ()Ljava/net/URLConnection;
    //   832: checkcast java/net/HttpURLConnection
    //   835: astore #7
    //   837: aload_2
    //   838: ifnull -> 863
    //   841: getstatic android/os/Build$VERSION.SDK_INT : I
    //   844: bipush #21
    //   846: if_icmplt -> 1525
    //   849: aload_2
    //   850: aload #10
    //   852: invokevirtual openConnection : (Ljava/net/URL;)Ljava/net/URLConnection;
    //   855: checkcast java/net/HttpURLConnection
    //   858: astore #6
    //   860: goto -> 873
    //   863: aload #10
    //   865: invokevirtual openConnection : ()Ljava/net/URLConnection;
    //   868: checkcast java/net/HttpURLConnection
    //   871: astore #6
    //   873: aload #6
    //   875: astore #7
    //   877: aload #7
    //   879: astore #6
    //   881: aload #7
    //   883: astore #8
    //   885: aload #7
    //   887: iload_3
    //   888: invokevirtual setConnectTimeout : (I)V
    //   891: aload #7
    //   893: astore #6
    //   895: aload #7
    //   897: astore #8
    //   899: aload #7
    //   901: iload_3
    //   902: invokevirtual setReadTimeout : (I)V
    //   905: aload #7
    //   907: astore #6
    //   909: aload #7
    //   911: astore #8
    //   913: aload #7
    //   915: iconst_1
    //   916: invokevirtual setDoInput : (Z)V
    //   919: aload #7
    //   921: astore #6
    //   923: aload #7
    //   925: astore #8
    //   927: aload #7
    //   929: iconst_1
    //   930: invokevirtual setDoOutput : (Z)V
    //   933: aload #7
    //   935: astore #6
    //   937: aload #7
    //   939: astore #8
    //   941: aload #7
    //   943: ldc 'POST'
    //   945: invokevirtual setRequestMethod : (Ljava/lang/String;)V
    //   948: aload #7
    //   950: astore #6
    //   952: aload #7
    //   954: astore #8
    //   956: aload #7
    //   958: iconst_0
    //   959: invokevirtual setUseCaches : (Z)V
    //   962: aload #7
    //   964: astore #6
    //   966: aload #7
    //   968: astore #8
    //   970: aload #7
    //   972: invokevirtual connect : ()V
    //   975: aload_1
    //   976: ifnull -> 1040
    //   979: aload #7
    //   981: astore #6
    //   983: aload #7
    //   985: astore #8
    //   987: aload #7
    //   989: invokevirtual getOutputStream : ()Ljava/io/OutputStream;
    //   992: astore #9
    //   994: aload #7
    //   996: astore #6
    //   998: aload #7
    //   1000: astore #8
    //   1002: aload #9
    //   1004: aload_1
    //   1005: invokevirtual toString : ()Ljava/lang/String;
    //   1008: invokevirtual getBytes : ()[B
    //   1011: invokevirtual write : ([B)V
    //   1014: aload #7
    //   1016: astore #6
    //   1018: aload #7
    //   1020: astore #8
    //   1022: aload #9
    //   1024: invokevirtual flush : ()V
    //   1027: aload #7
    //   1029: astore #6
    //   1031: aload #7
    //   1033: astore #8
    //   1035: aload #9
    //   1037: invokevirtual close : ()V
    //   1040: aload #7
    //   1042: astore #6
    //   1044: aload #7
    //   1046: astore #8
    //   1048: aload #7
    //   1050: invokevirtual getResponseCode : ()I
    //   1053: istore #4
    //   1055: iload #4
    //   1057: sipush #302
    //   1060: if_icmpne -> 1228
    //   1063: aload_2
    //   1064: ifnull -> 1147
    //   1067: aload #7
    //   1069: astore #6
    //   1071: aload #7
    //   1073: astore #8
    //   1075: getstatic android/os/Build$VERSION.SDK_INT : I
    //   1078: bipush #21
    //   1080: if_icmplt -> 1228
    //   1083: aload #7
    //   1085: astore #6
    //   1087: aload #7
    //   1089: astore #8
    //   1091: aload_2
    //   1092: new java/net/URL
    //   1095: dup
    //   1096: aload #7
    //   1098: ldc_w 'Location'
    //   1101: invokevirtual getHeaderField : (Ljava/lang/String;)Ljava/lang/String;
    //   1104: invokespecial <init> : (Ljava/lang/String;)V
    //   1107: invokevirtual openConnection : (Ljava/net/URL;)Ljava/net/URLConnection;
    //   1110: checkcast javax/net/ssl/HttpsURLConnection
    //   1113: astore_1
    //   1114: aload_1
    //   1115: astore_2
    //   1116: aload_1
    //   1117: astore #6
    //   1119: aload_1
    //   1120: iload_3
    //   1121: invokevirtual setConnectTimeout : (I)V
    //   1124: aload_1
    //   1125: astore_2
    //   1126: aload_1
    //   1127: astore #6
    //   1129: aload_1
    //   1130: iload_3
    //   1131: invokevirtual setReadTimeout : (I)V
    //   1134: aload_1
    //   1135: astore_2
    //   1136: aload_1
    //   1137: astore #6
    //   1139: aload_1
    //   1140: invokevirtual getResponseCode : ()I
    //   1143: istore_3
    //   1144: goto -> 1207
    //   1147: aload #7
    //   1149: astore #6
    //   1151: aload #7
    //   1153: astore #8
    //   1155: new java/net/URL
    //   1158: dup
    //   1159: aload #7
    //   1161: ldc_w 'Location'
    //   1164: invokevirtual getHeaderField : (Ljava/lang/String;)Ljava/lang/String;
    //   1167: invokespecial <init> : (Ljava/lang/String;)V
    //   1170: invokevirtual openConnection : ()Ljava/net/URLConnection;
    //   1173: checkcast javax/net/ssl/HttpsURLConnection
    //   1176: astore_1
    //   1177: aload_1
    //   1178: astore_2
    //   1179: aload_1
    //   1180: astore #6
    //   1182: aload_1
    //   1183: iload_3
    //   1184: invokevirtual setConnectTimeout : (I)V
    //   1187: aload_1
    //   1188: astore_2
    //   1189: aload_1
    //   1190: astore #6
    //   1192: aload_1
    //   1193: iload_3
    //   1194: invokevirtual setReadTimeout : (I)V
    //   1197: aload_1
    //   1198: astore_2
    //   1199: aload_1
    //   1200: astore #6
    //   1202: aload_1
    //   1203: invokevirtual getResponseCode : ()I
    //   1206: istore_3
    //   1207: aload_1
    //   1208: astore #7
    //   1210: goto -> 1231
    //   1213: astore_0
    //   1214: aload_2
    //   1215: astore #6
    //   1217: goto -> 1471
    //   1220: astore_1
    //   1221: aload #6
    //   1223: astore #8
    //   1225: goto -> 1390
    //   1228: iload #4
    //   1230: istore_3
    //   1231: iload_3
    //   1232: sipush #200
    //   1235: if_icmpne -> 1267
    //   1238: aload #7
    //   1240: astore #6
    //   1242: aload #7
    //   1244: astore #8
    //   1246: aload #7
    //   1248: invokevirtual getInputStream : ()Ljava/io/InputStream;
    //   1251: invokestatic a : (Ljava/io/InputStream;)Ljava/lang/String;
    //   1254: astore_1
    //   1255: aload #7
    //   1257: ifnull -> 1265
    //   1260: aload #7
    //   1262: invokevirtual disconnect : ()V
    //   1265: aload_1
    //   1266: areturn
    //   1267: aload #7
    //   1269: astore #6
    //   1271: aload #7
    //   1273: astore #8
    //   1275: new java/lang/StringBuilder
    //   1278: dup
    //   1279: invokespecial <init> : ()V
    //   1282: astore_1
    //   1283: aload #7
    //   1285: astore #6
    //   1287: aload #7
    //   1289: astore #8
    //   1291: aload_1
    //   1292: ldc 'url: '
    //   1294: invokevirtual append : (Ljava/lang/String;)Ljava/lang/StringBuilder;
    //   1297: pop
    //   1298: aload #7
    //   1300: astore #6
    //   1302: aload #7
    //   1304: astore #8
    //   1306: aload_1
    //   1307: aload_0
    //   1308: invokevirtual append : (Ljava/lang/String;)Ljava/lang/StringBuilder;
    //   1311: pop
    //   1312: aload #7
    //   1314: astore #6
    //   1316: aload #7
    //   1318: astore #8
    //   1320: aload_1
    //   1321: ldc ', responseCode: '
    //   1323: invokevirtual append : (Ljava/lang/String;)Ljava/lang/StringBuilder;
    //   1326: pop
    //   1327: aload #7
    //   1329: astore #6
    //   1331: aload #7
    //   1333: astore #8
    //   1335: aload_1
    //   1336: iload_3
    //   1337: invokevirtual append : (I)Ljava/lang/StringBuilder;
    //   1340: pop
    //   1341: aload #7
    //   1343: astore #6
    //   1345: aload #7
    //   1347: astore #8
    //   1349: aload_1
    //   1350: invokevirtual toString : ()Ljava/lang/String;
    //   1353: invokestatic c : (Ljava/lang/String;)V
    //   1356: aload #7
    //   1358: ifnull -> 1366
    //   1361: aload #7
    //   1363: invokevirtual disconnect : ()V
    //   1366: ldc ''
    //   1368: areturn
    //   1369: astore_0
    //   1370: aload #7
    //   1372: astore #6
    //   1374: goto -> 1471
    //   1377: astore_1
    //   1378: aload #7
    //   1380: astore #8
    //   1382: goto -> 1390
    //   1385: astore_0
    //   1386: goto -> 1471
    //   1389: astore_1
    //   1390: aload #8
    //   1392: astore #6
    //   1394: new java/lang/StringBuilder
    //   1397: dup
    //   1398: invokespecial <init> : ()V
    //   1401: astore_2
    //   1402: aload #8
    //   1404: astore #6
    //   1406: aload_2
    //   1407: ldc 'url: '
    //   1409: invokevirtual append : (Ljava/lang/String;)Ljava/lang/StringBuilder;
    //   1412: pop
    //   1413: aload #8
    //   1415: astore #6
    //   1417: aload_2
    //   1418: aload_0
    //   1419: invokevirtual append : (Ljava/lang/String;)Ljava/lang/StringBuilder;
    //   1422: pop
    //   1423: aload #8
    //   1425: astore #6
    //   1427: aload_2
    //   1428: ldc ', error: '
    //   1430: invokevirtual append : (Ljava/lang/String;)Ljava/lang/StringBuilder;
    //   1433: pop
    //   1434: aload #8
    //   1436: astore #6
    //   1438: aload_2
    //   1439: aload_1
    //   1440: invokevirtual toString : ()Ljava/lang/String;
    //   1443: invokevirtual append : (Ljava/lang/String;)Ljava/lang/StringBuilder;
    //   1446: pop
    //   1447: aload #8
    //   1449: astore #6
    //   1451: aload_2
    //   1452: invokevirtual toString : ()Ljava/lang/String;
    //   1455: invokestatic c : (Ljava/lang/String;)V
    //   1458: aload #8
    //   1460: ifnull -> 1528
    //   1463: aload #8
    //   1465: invokevirtual disconnect : ()V
    //   1468: ldc ''
    //   1470: areturn
    //   1471: aload #6
    //   1473: ifnull -> 1481
    //   1476: aload #6
    //   1478: invokevirtual disconnect : ()V
    //   1481: aload_0
    //   1482: athrow
    //   1483: astore_0
    //   1484: new java/lang/StringBuilder
    //   1487: dup
    //   1488: invokespecial <init> : ()V
    //   1491: astore_1
    //   1492: aload_1
    //   1493: ldc_w 'preGateWay error: '
    //   1496: invokevirtual append : (Ljava/lang/String;)Ljava/lang/StringBuilder;
    //   1499: pop
    //   1500: aload_1
    //   1501: aload_0
    //   1502: invokevirtual toString : ()Ljava/lang/String;
    //   1505: invokevirtual append : (Ljava/lang/String;)Ljava/lang/StringBuilder;
    //   1508: pop
    //   1509: aload_1
    //   1510: invokevirtual toString : ()Ljava/lang/String;
    //   1513: invokestatic c : (Ljava/lang/String;)V
    //   1516: ldc ''
    //   1518: areturn
    //   1519: goto -> 221
    //   1522: ldc ''
    //   1524: areturn
    //   1525: goto -> 877
    //   1528: ldc ''
    //   1530: areturn
    // Exception table:
    //   from	to	target	type
    //   53	68	1483	java/lang/Exception
    //   93	100	733	java/lang/Exception
    //   93	100	729	finally
    //   108	129	733	java/lang/Exception
    //   108	129	729	finally
    //   137	145	733	java/lang/Exception
    //   137	145	729	finally
    //   153	163	733	java/lang/Exception
    //   153	163	729	finally
    //   171	181	733	java/lang/Exception
    //   171	181	729	finally
    //   185	204	721	java/lang/Exception
    //   185	204	713	finally
    //   207	217	721	java/lang/Exception
    //   207	217	713	finally
    //   229	235	733	java/lang/Exception
    //   229	235	729	finally
    //   243	249	733	java/lang/Exception
    //   243	249	729	finally
    //   257	263	733	java/lang/Exception
    //   257	263	729	finally
    //   271	277	733	java/lang/Exception
    //   271	277	729	finally
    //   285	292	733	java/lang/Exception
    //   285	292	729	finally
    //   300	306	733	java/lang/Exception
    //   300	306	729	finally
    //   314	319	733	java/lang/Exception
    //   314	319	729	finally
    //   331	338	733	java/lang/Exception
    //   331	338	729	finally
    //   346	358	733	java/lang/Exception
    //   346	358	729	finally
    //   366	371	733	java/lang/Exception
    //   366	371	729	finally
    //   379	384	733	java/lang/Exception
    //   379	384	729	finally
    //   392	399	733	java/lang/Exception
    //   392	399	729	finally
    //   419	427	733	java/lang/Exception
    //   419	427	729	finally
    //   435	458	733	java/lang/Exception
    //   435	458	729	finally
    //   463	468	564	java/lang/Exception
    //   463	468	557	finally
    //   473	478	564	java/lang/Exception
    //   473	478	557	finally
    //   483	488	564	java/lang/Exception
    //   483	488	557	finally
    //   499	521	733	java/lang/Exception
    //   499	521	729	finally
    //   526	531	564	java/lang/Exception
    //   526	531	557	finally
    //   536	541	564	java/lang/Exception
    //   536	541	557	finally
    //   546	551	564	java/lang/Exception
    //   546	551	557	finally
    //   590	599	733	java/lang/Exception
    //   590	599	729	finally
    //   604	609	1483	java/lang/Exception
    //   619	627	733	java/lang/Exception
    //   619	627	729	finally
    //   635	642	733	java/lang/Exception
    //   635	642	729	finally
    //   650	656	733	java/lang/Exception
    //   650	656	729	finally
    //   664	671	733	java/lang/Exception
    //   664	671	729	finally
    //   679	685	733	java/lang/Exception
    //   679	685	729	finally
    //   693	700	733	java/lang/Exception
    //   693	700	729	finally
    //   705	710	1483	java/lang/Exception
    //   738	746	729	finally
    //   750	757	729	finally
    //   761	767	729	finally
    //   771	778	729	finally
    //   782	791	729	finally
    //   795	802	729	finally
    //   807	812	1483	java/lang/Exception
    //   820	825	1483	java/lang/Exception
    //   825	827	1483	java/lang/Exception
    //   827	837	1389	java/lang/Exception
    //   827	837	1385	finally
    //   841	860	1377	java/lang/Exception
    //   841	860	1369	finally
    //   863	873	1377	java/lang/Exception
    //   863	873	1369	finally
    //   885	891	1389	java/lang/Exception
    //   885	891	1385	finally
    //   899	905	1389	java/lang/Exception
    //   899	905	1385	finally
    //   913	919	1389	java/lang/Exception
    //   913	919	1385	finally
    //   927	933	1389	java/lang/Exception
    //   927	933	1385	finally
    //   941	948	1389	java/lang/Exception
    //   941	948	1385	finally
    //   956	962	1389	java/lang/Exception
    //   956	962	1385	finally
    //   970	975	1389	java/lang/Exception
    //   970	975	1385	finally
    //   987	994	1389	java/lang/Exception
    //   987	994	1385	finally
    //   1002	1014	1389	java/lang/Exception
    //   1002	1014	1385	finally
    //   1022	1027	1389	java/lang/Exception
    //   1022	1027	1385	finally
    //   1035	1040	1389	java/lang/Exception
    //   1035	1040	1385	finally
    //   1048	1055	1389	java/lang/Exception
    //   1048	1055	1385	finally
    //   1075	1083	1389	java/lang/Exception
    //   1075	1083	1385	finally
    //   1091	1114	1389	java/lang/Exception
    //   1091	1114	1385	finally
    //   1119	1124	1220	java/lang/Exception
    //   1119	1124	1213	finally
    //   1129	1134	1220	java/lang/Exception
    //   1129	1134	1213	finally
    //   1139	1144	1220	java/lang/Exception
    //   1139	1144	1213	finally
    //   1155	1177	1389	java/lang/Exception
    //   1155	1177	1385	finally
    //   1182	1187	1220	java/lang/Exception
    //   1182	1187	1213	finally
    //   1192	1197	1220	java/lang/Exception
    //   1192	1197	1213	finally
    //   1202	1207	1220	java/lang/Exception
    //   1202	1207	1213	finally
    //   1246	1255	1389	java/lang/Exception
    //   1246	1255	1385	finally
    //   1260	1265	1483	java/lang/Exception
    //   1275	1283	1389	java/lang/Exception
    //   1275	1283	1385	finally
    //   1291	1298	1389	java/lang/Exception
    //   1291	1298	1385	finally
    //   1306	1312	1389	java/lang/Exception
    //   1306	1312	1385	finally
    //   1320	1327	1389	java/lang/Exception
    //   1320	1327	1385	finally
    //   1335	1341	1389	java/lang/Exception
    //   1335	1341	1385	finally
    //   1349	1356	1389	java/lang/Exception
    //   1349	1356	1385	finally
    //   1361	1366	1483	java/lang/Exception
    //   1394	1402	1385	finally
    //   1406	1413	1385	finally
    //   1417	1423	1385	finally
    //   1427	1434	1385	finally
    //   1438	1447	1385	finally
    //   1451	1458	1385	finally
    //   1463	1468	1483	java/lang/Exception
    //   1476	1481	1483	java/lang/Exception
    //   1481	1483	1483	java/lang/Exception
  }
}


/* Location:              D:\code\BluedHook\classes.dex\com.soft.blued7575468-dex2jar.jar!\com\geetest\onepassv2\g\a.class
 * Java compiler version: 6 (50.0)
 * JD-Core Version:       1.1.3
 */