package com.alipay.security.mobile.module.d;

import java.util.List;

public final class d {
  private static String a = "";
  
  private static String b = "";
  
  private static String c = "";
  
  public static void a(String paramString) {
    // Byte code:
    //   0: ldc com/alipay/security/mobile/module/d/d
    //   2: monitorenter
    //   3: new java/util/ArrayList
    //   6: dup
    //   7: invokespecial <init> : ()V
    //   10: astore_1
    //   11: aload_1
    //   12: aload_0
    //   13: invokeinterface add : (Ljava/lang/Object;)Z
    //   18: pop
    //   19: aload_1
    //   20: invokestatic a : (Ljava/util/List;)V
    //   23: ldc com/alipay/security/mobile/module/d/d
    //   25: monitorexit
    //   26: return
    //   27: astore_0
    //   28: ldc com/alipay/security/mobile/module/d/d
    //   30: monitorexit
    //   31: aload_0
    //   32: athrow
    // Exception table:
    //   from	to	target	type
    //   3	23	27	finally
  }
  
  public static void a(String paramString1, String paramString2, String paramString3) {
    // Byte code:
    //   0: ldc com/alipay/security/mobile/module/d/d
    //   2: monitorenter
    //   3: aload_0
    //   4: putstatic com/alipay/security/mobile/module/d/d.a : Ljava/lang/String;
    //   7: aload_1
    //   8: putstatic com/alipay/security/mobile/module/d/d.b : Ljava/lang/String;
    //   11: aload_2
    //   12: putstatic com/alipay/security/mobile/module/d/d.c : Ljava/lang/String;
    //   15: ldc com/alipay/security/mobile/module/d/d
    //   17: monitorexit
    //   18: return
    //   19: astore_0
    //   20: ldc com/alipay/security/mobile/module/d/d
    //   22: monitorexit
    //   23: aload_0
    //   24: athrow
    // Exception table:
    //   from	to	target	type
    //   3	15	19	finally
  }
  
  public static void a(Throwable paramThrowable) {
    // Byte code:
    //   0: ldc com/alipay/security/mobile/module/d/d
    //   2: monitorenter
    //   3: new java/util/ArrayList
    //   6: dup
    //   7: invokespecial <init> : ()V
    //   10: astore_1
    //   11: aload_0
    //   12: ifnull -> 65
    //   15: new java/io/StringWriter
    //   18: dup
    //   19: invokespecial <init> : ()V
    //   22: astore_2
    //   23: aload_0
    //   24: new java/io/PrintWriter
    //   27: dup
    //   28: aload_2
    //   29: invokespecial <init> : (Ljava/io/Writer;)V
    //   32: invokevirtual printStackTrace : (Ljava/io/PrintWriter;)V
    //   35: aload_2
    //   36: invokevirtual toString : ()Ljava/lang/String;
    //   39: astore_0
    //   40: goto -> 43
    //   43: aload_1
    //   44: aload_0
    //   45: invokeinterface add : (Ljava/lang/Object;)Z
    //   50: pop
    //   51: aload_1
    //   52: invokestatic a : (Ljava/util/List;)V
    //   55: ldc com/alipay/security/mobile/module/d/d
    //   57: monitorexit
    //   58: return
    //   59: astore_0
    //   60: ldc com/alipay/security/mobile/module/d/d
    //   62: monitorexit
    //   63: aload_0
    //   64: athrow
    //   65: ldc ''
    //   67: astore_0
    //   68: goto -> 43
    // Exception table:
    //   from	to	target	type
    //   3	11	59	finally
    //   15	40	59	finally
    //   43	55	59	finally
  }
  
  private static void a(List<String> paramList) {
    // Byte code:
    //   0: ldc com/alipay/security/mobile/module/d/d
    //   2: monitorenter
    //   3: getstatic com/alipay/security/mobile/module/d/d.b : Ljava/lang/String;
    //   6: invokestatic a : (Ljava/lang/String;)Z
    //   9: ifne -> 220
    //   12: getstatic com/alipay/security/mobile/module/d/d.c : Ljava/lang/String;
    //   15: invokestatic a : (Ljava/lang/String;)Z
    //   18: ifeq -> 24
    //   21: goto -> 220
    //   24: new java/lang/StringBuffer
    //   27: dup
    //   28: invokespecial <init> : ()V
    //   31: astore_3
    //   32: aload_3
    //   33: getstatic com/alipay/security/mobile/module/d/d.c : Ljava/lang/String;
    //   36: invokevirtual append : (Ljava/lang/String;)Ljava/lang/StringBuffer;
    //   39: pop
    //   40: aload_0
    //   41: invokeinterface iterator : ()Ljava/util/Iterator;
    //   46: astore_0
    //   47: aload_0
    //   48: invokeinterface hasNext : ()Z
    //   53: ifeq -> 99
    //   56: aload_0
    //   57: invokeinterface next : ()Ljava/lang/Object;
    //   62: checkcast java/lang/String
    //   65: astore #4
    //   67: new java/lang/StringBuilder
    //   70: dup
    //   71: ldc ', '
    //   73: invokespecial <init> : (Ljava/lang/String;)V
    //   76: astore #5
    //   78: aload #5
    //   80: aload #4
    //   82: invokevirtual append : (Ljava/lang/String;)Ljava/lang/StringBuilder;
    //   85: pop
    //   86: aload_3
    //   87: aload #5
    //   89: invokevirtual toString : ()Ljava/lang/String;
    //   92: invokevirtual append : (Ljava/lang/String;)Ljava/lang/StringBuffer;
    //   95: pop
    //   96: goto -> 47
    //   99: aload_3
    //   100: ldc '\\n'
    //   102: invokevirtual append : (Ljava/lang/String;)Ljava/lang/StringBuffer;
    //   105: pop
    //   106: new java/io/File
    //   109: dup
    //   110: getstatic com/alipay/security/mobile/module/d/d.a : Ljava/lang/String;
    //   113: invokespecial <init> : (Ljava/lang/String;)V
    //   116: astore_0
    //   117: aload_0
    //   118: invokevirtual exists : ()Z
    //   121: ifne -> 129
    //   124: aload_0
    //   125: invokevirtual mkdirs : ()Z
    //   128: pop
    //   129: new java/io/File
    //   132: dup
    //   133: getstatic com/alipay/security/mobile/module/d/d.a : Ljava/lang/String;
    //   136: getstatic com/alipay/security/mobile/module/d/d.b : Ljava/lang/String;
    //   139: invokespecial <init> : (Ljava/lang/String;Ljava/lang/String;)V
    //   142: astore_0
    //   143: aload_0
    //   144: invokevirtual exists : ()Z
    //   147: ifne -> 155
    //   150: aload_0
    //   151: invokevirtual createNewFile : ()Z
    //   154: pop
    //   155: aload_0
    //   156: invokevirtual length : ()J
    //   159: lstore_1
    //   160: aload_3
    //   161: invokevirtual length : ()I
    //   164: i2l
    //   165: lload_1
    //   166: ladd
    //   167: ldc2_w 51200
    //   170: lcmp
    //   171: ifgt -> 187
    //   174: new java/io/FileWriter
    //   177: dup
    //   178: aload_0
    //   179: iconst_1
    //   180: invokespecial <init> : (Ljava/io/File;Z)V
    //   183: astore_0
    //   184: goto -> 196
    //   187: new java/io/FileWriter
    //   190: dup
    //   191: aload_0
    //   192: invokespecial <init> : (Ljava/io/File;)V
    //   195: astore_0
    //   196: aload_0
    //   197: aload_3
    //   198: invokevirtual toString : ()Ljava/lang/String;
    //   201: invokevirtual write : (Ljava/lang/String;)V
    //   204: aload_0
    //   205: invokevirtual flush : ()V
    //   208: aload_0
    //   209: invokevirtual close : ()V
    //   212: ldc com/alipay/security/mobile/module/d/d
    //   214: monitorexit
    //   215: return
    //   216: ldc com/alipay/security/mobile/module/d/d
    //   218: monitorexit
    //   219: return
    //   220: ldc com/alipay/security/mobile/module/d/d
    //   222: monitorexit
    //   223: return
    //   224: astore_0
    //   225: ldc com/alipay/security/mobile/module/d/d
    //   227: monitorexit
    //   228: aload_0
    //   229: athrow
    //   230: astore_0
    //   231: goto -> 216
    // Exception table:
    //   from	to	target	type
    //   3	21	224	finally
    //   24	47	224	finally
    //   47	96	224	finally
    //   99	106	224	finally
    //   106	129	230	java/lang/Exception
    //   106	129	224	finally
    //   129	155	230	java/lang/Exception
    //   129	155	224	finally
    //   155	184	230	java/lang/Exception
    //   155	184	224	finally
    //   187	196	230	java/lang/Exception
    //   187	196	224	finally
    //   196	212	230	java/lang/Exception
    //   196	212	224	finally
  }
}


/* Location:              D:\code\BluedHook\classes.dex\com.soft.blued7646532-dex2jar.jar!\com\alipay\security\mobile\module\d\d.class
 * Java compiler version: 6 (50.0)
 * JD-Core Version:       1.1.3
 */