package com.bytedance.sdk.adnet.core;

import android.os.SystemClock;
import com.bytedance.sdk.adnet.d.c;
import com.bytedance.sdk.adnet.face.a;
import java.io.DataInputStream;
import java.io.EOFException;
import java.io.File;
import java.io.FileInputStream;
import java.io.FileOutputStream;
import java.io.FilterInputStream;
import java.io.IOException;
import java.io.InputStream;
import java.io.OutputStream;
import java.util.ArrayList;
import java.util.Collections;
import java.util.Iterator;
import java.util.LinkedHashMap;
import java.util.List;
import java.util.Map;

class f implements a {
  private final Map<String, a> a = new LinkedHashMap<String, a>(16, 0.75F, true);
  
  private long b = 0L;
  
  private final File c;
  
  private final int d;
  
  public f(File paramFile) {
    this(paramFile, 5242880);
  }
  
  public f(File paramFile, int paramInt) {
    this.c = paramFile;
    this.d = paramInt;
  }
  
  static int a(InputStream paramInputStream) throws Throwable {
    int i = c(paramInputStream);
    int j = c(paramInputStream);
    int k = c(paramInputStream);
    return c(paramInputStream) << 24 | i << 0 | 0x0 | j << 8 | k << 16;
  }
  
  static String a(b paramb) throws Throwable {
    return new String(a(paramb, b(paramb)), "UTF-8");
  }
  
  static void a(OutputStream paramOutputStream, int paramInt) throws Throwable {
    paramOutputStream.write(paramInt >> 0 & 0xFF);
    paramOutputStream.write(paramInt >> 8 & 0xFF);
    paramOutputStream.write(paramInt >> 16 & 0xFF);
    paramOutputStream.write(paramInt >> 24 & 0xFF);
  }
  
  static void a(OutputStream paramOutputStream, long paramLong) throws Throwable {
    paramOutputStream.write((byte)(int)(paramLong >>> 0L));
    paramOutputStream.write((byte)(int)(paramLong >>> 8L));
    paramOutputStream.write((byte)(int)(paramLong >>> 16L));
    paramOutputStream.write((byte)(int)(paramLong >>> 24L));
    paramOutputStream.write((byte)(int)(paramLong >>> 32L));
    paramOutputStream.write((byte)(int)(paramLong >>> 40L));
    paramOutputStream.write((byte)(int)(paramLong >>> 48L));
    paramOutputStream.write((byte)(int)(paramLong >>> 56L));
  }
  
  static void a(OutputStream paramOutputStream, String paramString) throws Throwable {
    byte[] arrayOfByte = paramString.getBytes("UTF-8");
    a(paramOutputStream, arrayOfByte.length);
    paramOutputStream.write(arrayOfByte, 0, arrayOfByte.length);
  }
  
  private void a(String paramString, a parama) {
    if (!this.a.containsKey(paramString)) {
      this.b += parama.a;
    } else {
      a a1 = this.a.get(paramString);
      this.b += parama.a - a1.a;
    } 
    this.a.put(paramString, parama);
  }
  
  static void a(List<Header> paramList, OutputStream paramOutputStream) throws Throwable {
    if (paramList != null) {
      a(paramOutputStream, paramList.size());
      for (Header header : paramList) {
        a(paramOutputStream, header.a());
        a(paramOutputStream, header.b());
      } 
    } else {
      a(paramOutputStream, 0);
    } 
  }
  
  static byte[] a(b paramb, long paramLong) throws Throwable {
    long l = paramb.a();
    if (paramLong >= 0L && paramLong <= l) {
      int i = (int)paramLong;
      if (i == paramLong) {
        byte[] arrayOfByte = new byte[i];
        (new DataInputStream(paramb)).readFully(arrayOfByte);
        return arrayOfByte;
      } 
    } 
    StringBuilder stringBuilder = new StringBuilder();
    stringBuilder.append("streamToBytes length=");
    stringBuilder.append(paramLong);
    stringBuilder.append(", maxLength=");
    stringBuilder.append(l);
    throw new IOException(stringBuilder.toString());
  }
  
  static long b(InputStream paramInputStream) throws Throwable {
    return (c(paramInputStream) & 0xFFL) << 0L | 0x0L | (c(paramInputStream) & 0xFFL) << 8L | (c(paramInputStream) & 0xFFL) << 16L | (c(paramInputStream) & 0xFFL) << 24L | (c(paramInputStream) & 0xFFL) << 32L | (c(paramInputStream) & 0xFFL) << 40L | (c(paramInputStream) & 0xFFL) << 48L | (0xFFL & c(paramInputStream)) << 56L;
  }
  
  static List<Header> b(b paramb) throws Throwable {
    int i = a(paramb);
    if (i >= 0) {
      List<?> list;
      if (i == 0) {
        list = Collections.emptyList();
      } else {
        list = new ArrayList();
      } 
      for (int j = 0; j < i; j++)
        list.add(new Header(a(paramb).intern(), a(paramb).intern())); 
      return (List)list;
    } 
    StringBuilder stringBuilder = new StringBuilder();
    stringBuilder.append("readHeaderList size=");
    stringBuilder.append(i);
    throw new IOException(stringBuilder.toString());
  }
  
  private void b() {
    int j;
    if (this.b < this.d)
      return; 
    if (p.a)
      p.a("Pruning old cache entries.", new Object[0]); 
    long l1 = this.b;
    long l2 = SystemClock.elapsedRealtime();
    Iterator<Map.Entry> iterator = this.a.entrySet().iterator();
    int i = 0;
    while (true) {
      j = i;
      if (iterator.hasNext()) {
        a a1 = (a)((Map.Entry)iterator.next()).getValue();
        if (c(a1.b).delete()) {
          this.b -= a1.a;
        } else {
          p.b("Could not delete cache entry for key=%s, filename=%s", new Object[] { a1.b, d(a1.b) });
        } 
        iterator.remove();
        j = i + 1;
        i = j;
        if ((float)this.b < this.d * 0.9F)
          break; 
        continue;
      } 
      break;
    } 
    if (p.a)
      p.a("pruned %d files, %d bytes, %d ms", new Object[] { Integer.valueOf(j), Long.valueOf(this.b - l1), Long.valueOf(SystemClock.elapsedRealtime() - l2) }); 
  }
  
  private static int c(InputStream paramInputStream) throws Throwable {
    int i = paramInputStream.read();
    if (i != -1)
      return i; 
    throw new EOFException();
  }
  
  private String d(String paramString) {
    int i = paramString.length() / 2;
    int j = paramString.substring(0, i).hashCode();
    StringBuilder stringBuilder = new StringBuilder();
    stringBuilder.append(String.valueOf(j));
    stringBuilder.append(String.valueOf(paramString.substring(i).hashCode()));
    return stringBuilder.toString();
  }
  
  private void e(String paramString) {
    a a1 = this.a.remove(paramString);
    if (a1 != null)
      this.b -= a1.a; 
  }
  
  public a.a a(String paramString) {
    // Byte code:
    //   0: aload_0
    //   1: monitorenter
    //   2: aload_1
    //   3: invokestatic isEmpty : (Ljava/lang/CharSequence;)Z
    //   6: istore_2
    //   7: iload_2
    //   8: ifeq -> 15
    //   11: aload_0
    //   12: monitorexit
    //   13: aconst_null
    //   14: areturn
    //   15: aload_0
    //   16: getfield a : Ljava/util/Map;
    //   19: aload_1
    //   20: invokeinterface get : (Ljava/lang/Object;)Ljava/lang/Object;
    //   25: checkcast com/bytedance/sdk/adnet/core/f$a
    //   28: astore #4
    //   30: aload #4
    //   32: ifnonnull -> 39
    //   35: aload_0
    //   36: monitorexit
    //   37: aconst_null
    //   38: areturn
    //   39: aload_0
    //   40: aload_1
    //   41: invokevirtual c : (Ljava/lang/String;)Ljava/io/File;
    //   44: astore #5
    //   46: new com/bytedance/sdk/adnet/core/f$b
    //   49: dup
    //   50: new java/io/BufferedInputStream
    //   53: dup
    //   54: aload_0
    //   55: aload #5
    //   57: invokevirtual a : (Ljava/io/File;)Ljava/io/InputStream;
    //   60: invokespecial <init> : (Ljava/io/InputStream;)V
    //   63: aload #5
    //   65: invokevirtual length : ()J
    //   68: invokespecial <init> : (Ljava/io/InputStream;J)V
    //   71: astore_3
    //   72: aload_3
    //   73: invokestatic a : (Lcom/bytedance/sdk/adnet/core/f$b;)Lcom/bytedance/sdk/adnet/core/f$a;
    //   76: astore #6
    //   78: aload_1
    //   79: aload #6
    //   81: getfield b : Ljava/lang/String;
    //   84: invokestatic equals : (Ljava/lang/CharSequence;Ljava/lang/CharSequence;)Z
    //   87: ifne -> 137
    //   90: ldc_w '%s: key=%s, found=%s'
    //   93: iconst_3
    //   94: anewarray java/lang/Object
    //   97: dup
    //   98: iconst_0
    //   99: aload #5
    //   101: invokevirtual getAbsolutePath : ()Ljava/lang/String;
    //   104: aastore
    //   105: dup
    //   106: iconst_1
    //   107: aload_1
    //   108: aastore
    //   109: dup
    //   110: iconst_2
    //   111: aload #6
    //   113: getfield b : Ljava/lang/String;
    //   116: aastore
    //   117: invokestatic b : (Ljava/lang/String;[Ljava/lang/Object;)V
    //   120: aload_0
    //   121: aload_1
    //   122: invokespecial e : (Ljava/lang/String;)V
    //   125: aload_3
    //   126: invokevirtual close : ()V
    //   129: aload_3
    //   130: invokevirtual close : ()V
    //   133: aload_0
    //   134: monitorexit
    //   135: aconst_null
    //   136: areturn
    //   137: aload #4
    //   139: aload_3
    //   140: aload_3
    //   141: invokevirtual a : ()J
    //   144: invokestatic a : (Lcom/bytedance/sdk/adnet/core/f$b;J)[B
    //   147: invokevirtual a : ([B)Lcom/bytedance/sdk/adnet/face/a$a;
    //   150: astore #4
    //   152: aload_3
    //   153: invokevirtual close : ()V
    //   156: aload_3
    //   157: invokevirtual close : ()V
    //   160: aload_0
    //   161: monitorexit
    //   162: aload #4
    //   164: areturn
    //   165: astore #4
    //   167: aload_3
    //   168: invokevirtual close : ()V
    //   171: aload #4
    //   173: athrow
    //   174: astore #4
    //   176: goto -> 183
    //   179: astore #4
    //   181: aconst_null
    //   182: astore_3
    //   183: ldc_w '%s: %s'
    //   186: iconst_2
    //   187: anewarray java/lang/Object
    //   190: dup
    //   191: iconst_0
    //   192: aload #5
    //   194: invokevirtual getAbsolutePath : ()Ljava/lang/String;
    //   197: aastore
    //   198: dup
    //   199: iconst_1
    //   200: aload #4
    //   202: invokevirtual toString : ()Ljava/lang/String;
    //   205: aastore
    //   206: invokestatic b : (Ljava/lang/String;[Ljava/lang/Object;)V
    //   209: aload_0
    //   210: aload_1
    //   211: invokevirtual b : (Ljava/lang/String;)V
    //   214: aload_3
    //   215: ifnull -> 222
    //   218: aload_3
    //   219: invokevirtual close : ()V
    //   222: aload_0
    //   223: monitorexit
    //   224: aconst_null
    //   225: areturn
    //   226: astore_1
    //   227: aload_3
    //   228: ifnull -> 235
    //   231: aload_3
    //   232: invokevirtual close : ()V
    //   235: aload_1
    //   236: athrow
    //   237: astore_1
    //   238: aload_0
    //   239: monitorexit
    //   240: aload_1
    //   241: athrow
    //   242: astore_1
    //   243: goto -> 133
    //   246: astore_1
    //   247: goto -> 160
    //   250: astore_1
    //   251: goto -> 222
    //   254: astore_3
    //   255: goto -> 235
    // Exception table:
    //   from	to	target	type
    //   2	7	237	finally
    //   15	30	237	finally
    //   39	46	237	finally
    //   46	72	179	finally
    //   72	125	165	finally
    //   125	129	174	finally
    //   129	133	242	finally
    //   137	152	165	finally
    //   152	156	174	finally
    //   156	160	246	finally
    //   167	174	174	finally
    //   183	214	226	finally
    //   218	222	250	finally
    //   231	235	254	finally
    //   235	237	237	finally
  }
  
  InputStream a(File paramFile) throws Throwable {
    return new FileInputStream(paramFile);
  }
  
  public void a() {
    // Byte code:
    //   0: aload_0
    //   1: monitorenter
    //   2: aload_0
    //   3: getfield c : Ljava/io/File;
    //   6: invokevirtual exists : ()Z
    //   9: istore_3
    //   10: iconst_0
    //   11: istore_1
    //   12: iload_3
    //   13: ifne -> 49
    //   16: aload_0
    //   17: getfield c : Ljava/io/File;
    //   20: invokevirtual mkdirs : ()Z
    //   23: ifne -> 46
    //   26: ldc_w 'Unable to create cache dir %s'
    //   29: iconst_1
    //   30: anewarray java/lang/Object
    //   33: dup
    //   34: iconst_0
    //   35: aload_0
    //   36: getfield c : Ljava/io/File;
    //   39: invokevirtual getAbsolutePath : ()Ljava/lang/String;
    //   42: aastore
    //   43: invokestatic c : (Ljava/lang/String;[Ljava/lang/Object;)V
    //   46: aload_0
    //   47: monitorexit
    //   48: return
    //   49: aload_0
    //   50: getfield c : Ljava/io/File;
    //   53: invokevirtual listFiles : ()[Ljava/io/File;
    //   56: astore #6
    //   58: aload #6
    //   60: ifnonnull -> 66
    //   63: aload_0
    //   64: monitorexit
    //   65: return
    //   66: aload #6
    //   68: arraylength
    //   69: istore_2
    //   70: iload_1
    //   71: iload_2
    //   72: if_icmpge -> 158
    //   75: aload #6
    //   77: iload_1
    //   78: aaload
    //   79: astore #7
    //   81: aload #7
    //   83: invokevirtual length : ()J
    //   86: lstore #4
    //   88: new com/bytedance/sdk/adnet/core/f$b
    //   91: dup
    //   92: new java/io/BufferedInputStream
    //   95: dup
    //   96: aload_0
    //   97: aload #7
    //   99: invokevirtual a : (Ljava/io/File;)Ljava/io/InputStream;
    //   102: invokespecial <init> : (Ljava/io/InputStream;)V
    //   105: lload #4
    //   107: invokespecial <init> : (Ljava/io/InputStream;J)V
    //   110: astore #8
    //   112: aload #8
    //   114: invokestatic a : (Lcom/bytedance/sdk/adnet/core/f$b;)Lcom/bytedance/sdk/adnet/core/f$a;
    //   117: astore #9
    //   119: aload #9
    //   121: lload #4
    //   123: putfield a : J
    //   126: aload_0
    //   127: aload #9
    //   129: getfield b : Ljava/lang/String;
    //   132: aload #9
    //   134: invokespecial a : (Ljava/lang/String;Lcom/bytedance/sdk/adnet/core/f$a;)V
    //   137: aload #8
    //   139: invokevirtual close : ()V
    //   142: goto -> 151
    //   145: aload #7
    //   147: invokevirtual delete : ()Z
    //   150: pop
    //   151: iload_1
    //   152: iconst_1
    //   153: iadd
    //   154: istore_1
    //   155: goto -> 70
    //   158: aload_0
    //   159: monitorexit
    //   160: return
    //   161: astore #6
    //   163: aload_0
    //   164: monitorexit
    //   165: aload #6
    //   167: athrow
    //   168: astore #8
    //   170: goto -> 145
    //   173: astore #9
    //   175: goto -> 137
    // Exception table:
    //   from	to	target	type
    //   2	10	161	finally
    //   16	46	161	finally
    //   49	58	161	finally
    //   66	70	161	finally
    //   81	112	168	finally
    //   112	137	173	finally
    //   137	142	168	finally
    //   145	151	161	finally
  }
  
  public void a(String paramString, a.a parama) {
    // Byte code:
    //   0: aload_0
    //   1: monitorenter
    //   2: aload_0
    //   3: getfield b : J
    //   6: aload_2
    //   7: getfield b : [B
    //   10: arraylength
    //   11: i2l
    //   12: ladd
    //   13: aload_0
    //   14: getfield d : I
    //   17: i2l
    //   18: lcmp
    //   19: ifle -> 49
    //   22: aload_2
    //   23: getfield b : [B
    //   26: arraylength
    //   27: i2f
    //   28: fstore_3
    //   29: aload_0
    //   30: getfield d : I
    //   33: istore #4
    //   35: fload_3
    //   36: iload #4
    //   38: i2f
    //   39: ldc 0.9
    //   41: fmul
    //   42: fcmpl
    //   43: ifle -> 49
    //   46: aload_0
    //   47: monitorexit
    //   48: return
    //   49: aload_0
    //   50: aload_1
    //   51: invokevirtual c : (Ljava/lang/String;)Ljava/io/File;
    //   54: astore #6
    //   56: new java/io/BufferedOutputStream
    //   59: dup
    //   60: aload_0
    //   61: aload #6
    //   63: invokevirtual b : (Ljava/io/File;)Ljava/io/OutputStream;
    //   66: invokespecial <init> : (Ljava/io/OutputStream;)V
    //   69: astore #5
    //   71: new com/bytedance/sdk/adnet/core/f$a
    //   74: dup
    //   75: aload_1
    //   76: aload_2
    //   77: invokespecial <init> : (Ljava/lang/String;Lcom/bytedance/sdk/adnet/face/a$a;)V
    //   80: astore #7
    //   82: aload #7
    //   84: aload #5
    //   86: invokevirtual a : (Ljava/io/OutputStream;)Z
    //   89: ifeq -> 130
    //   92: aload #5
    //   94: aload_2
    //   95: getfield b : [B
    //   98: invokevirtual write : ([B)V
    //   101: aload #7
    //   103: aload #6
    //   105: invokevirtual length : ()J
    //   108: putfield a : J
    //   111: aload_0
    //   112: aload_1
    //   113: aload #7
    //   115: invokespecial a : (Ljava/lang/String;Lcom/bytedance/sdk/adnet/core/f$a;)V
    //   118: aload_0
    //   119: invokespecial b : ()V
    //   122: aload #5
    //   124: invokevirtual close : ()V
    //   127: aload_0
    //   128: monitorexit
    //   129: return
    //   130: aload #5
    //   132: invokevirtual close : ()V
    //   135: ldc_w 'Failed to write header for %s'
    //   138: iconst_1
    //   139: anewarray java/lang/Object
    //   142: dup
    //   143: iconst_0
    //   144: aload #6
    //   146: invokevirtual getAbsolutePath : ()Ljava/lang/String;
    //   149: aastore
    //   150: invokestatic b : (Ljava/lang/String;[Ljava/lang/Object;)V
    //   153: new java/io/IOException
    //   156: dup
    //   157: invokespecial <init> : ()V
    //   160: athrow
    //   161: aconst_null
    //   162: astore_1
    //   163: aload_1
    //   164: ifnull -> 171
    //   167: aload_1
    //   168: invokevirtual close : ()V
    //   171: aload #6
    //   173: invokevirtual delete : ()Z
    //   176: ifne -> 197
    //   179: ldc_w 'Could not clean up file %s'
    //   182: iconst_1
    //   183: anewarray java/lang/Object
    //   186: dup
    //   187: iconst_0
    //   188: aload #6
    //   190: invokevirtual getAbsolutePath : ()Ljava/lang/String;
    //   193: aastore
    //   194: invokestatic b : (Ljava/lang/String;[Ljava/lang/Object;)V
    //   197: aload_0
    //   198: monitorexit
    //   199: return
    //   200: astore_1
    //   201: aload_0
    //   202: monitorexit
    //   203: aload_1
    //   204: athrow
    //   205: astore_1
    //   206: goto -> 161
    //   209: astore_1
    //   210: aload #5
    //   212: astore_1
    //   213: goto -> 163
    //   216: astore_1
    //   217: goto -> 127
    //   220: astore_1
    //   221: goto -> 171
    // Exception table:
    //   from	to	target	type
    //   2	35	200	finally
    //   49	56	200	finally
    //   56	71	205	finally
    //   71	122	209	finally
    //   122	127	216	finally
    //   130	161	209	finally
    //   167	171	220	finally
    //   171	197	200	finally
  }
  
  OutputStream b(File paramFile) throws Throwable {
    return new FileOutputStream(paramFile);
  }
  
  public void b(String paramString) {
    // Byte code:
    //   0: aload_0
    //   1: monitorenter
    //   2: aload_0
    //   3: aload_1
    //   4: invokevirtual c : (Ljava/lang/String;)Ljava/io/File;
    //   7: invokevirtual delete : ()Z
    //   10: istore_2
    //   11: aload_0
    //   12: aload_1
    //   13: invokespecial e : (Ljava/lang/String;)V
    //   16: iload_2
    //   17: ifne -> 41
    //   20: ldc 'Could not delete cache entry for key=%s, filename=%s'
    //   22: iconst_2
    //   23: anewarray java/lang/Object
    //   26: dup
    //   27: iconst_0
    //   28: aload_1
    //   29: aastore
    //   30: dup
    //   31: iconst_1
    //   32: aload_0
    //   33: aload_1
    //   34: invokespecial d : (Ljava/lang/String;)Ljava/lang/String;
    //   37: aastore
    //   38: invokestatic b : (Ljava/lang/String;[Ljava/lang/Object;)V
    //   41: aload_0
    //   42: monitorexit
    //   43: return
    //   44: astore_1
    //   45: aload_0
    //   46: monitorexit
    //   47: aload_1
    //   48: athrow
    // Exception table:
    //   from	to	target	type
    //   2	16	44	finally
    //   20	41	44	finally
  }
  
  public File c(String paramString) {
    return new File(this.c, d(paramString));
  }
  
  static class a {
    long a;
    
    final String b;
    
    final String c;
    
    final long d;
    
    final long e;
    
    final long f;
    
    final long g;
    
    final List<Header> h;
    
    a(String param1String, a.a param1a) {
      this(param1String, param1a.c, param1a.d, param1a.e, param1a.f, param1a.g, a(param1a));
    }
    
    private a(String param1String1, String param1String2, long param1Long1, long param1Long2, long param1Long3, long param1Long4, List<Header> param1List) {
      this.b = param1String1;
      param1String1 = param1String2;
      if ("".equals(param1String2))
        param1String1 = null; 
      this.c = param1String1;
      this.d = param1Long1;
      this.e = param1Long2;
      this.f = param1Long3;
      this.g = param1Long4;
      this.h = param1List;
    }
    
    static a a(f.b param1b) throws Throwable {
      if (f.a(param1b) == 538247942)
        return new a(f.a(param1b), f.a(param1b), f.b(param1b), f.b(param1b), f.b(param1b), f.b(param1b), f.b(param1b)); 
      throw new IOException();
    }
    
    private static List<Header> a(a.a param1a) {
      return (param1a.i != null) ? param1a.i : c.b(param1a.h);
    }
    
    a.a a(byte[] param1ArrayOfbyte) {
      a.a a1 = new a.a();
      a1.b = param1ArrayOfbyte;
      a1.c = this.c;
      a1.d = this.d;
      a1.e = this.e;
      a1.f = this.f;
      a1.g = this.g;
      a1.h = c.a(this.h);
      a1.i = Collections.unmodifiableList(this.h);
      return a1;
    }
    
    boolean a(OutputStream param1OutputStream) {
      try {
        String str;
        f.a(param1OutputStream, 538247942);
        f.a(param1OutputStream, this.b);
        if (this.c == null) {
          str = "";
        } else {
          str = this.c;
        } 
        f.a(param1OutputStream, str);
        f.a(param1OutputStream, this.d);
        f.a(param1OutputStream, this.e);
        f.a(param1OutputStream, this.f);
        f.a(param1OutputStream, this.g);
        return true;
      } finally {
        param1OutputStream = null;
        p.b("%s", new Object[] { param1OutputStream.toString() });
      } 
    }
  }
  
  static class b extends FilterInputStream {
    private final long a;
    
    private long b;
    
    b(InputStream param1InputStream, long param1Long) {
      super(param1InputStream);
      this.a = param1Long;
    }
    
    long a() {
      return this.a - this.b;
    }
    
    public int read() throws IOException {
      int i = super.read();
      if (i != -1)
        this.b++; 
      return i;
    }
    
    public int read(byte[] param1ArrayOfbyte, int param1Int1, int param1Int2) throws IOException {
      param1Int1 = super.read(param1ArrayOfbyte, param1Int1, param1Int2);
      if (param1Int1 != -1)
        this.b += param1Int1; 
      return param1Int1;
    }
  }
}


/* Location:              D:\code\BluedHook\classes.dex\com.soft.blued7575468-dex2jar.jar!\com\bytedance\sdk\adnet\core\f.class
 * Java compiler version: 6 (50.0)
 * JD-Core Version:       1.1.3
 */