package com.blued.android.module.media.selector.observer;

import java.util.ArrayList;

@Deprecated
public class PLVideoObserver {
  private static PLVideoObserver a = new PLVideoObserver();
  
  private ArrayList<IPLVideoObserver> b = new ArrayList<IPLVideoObserver>();
  
  public static PLVideoObserver a() {
    return a;
  }
  
  public void a(IPLVideoObserver paramIPLVideoObserver) {
    // Byte code:
    //   0: aload_0
    //   1: monitorenter
    //   2: aload_1
    //   3: ifnull -> 23
    //   6: aload_0
    //   7: getfield b : Ljava/util/ArrayList;
    //   10: aload_1
    //   11: invokevirtual add : (Ljava/lang/Object;)Z
    //   14: pop
    //   15: goto -> 23
    //   18: astore_1
    //   19: aload_0
    //   20: monitorexit
    //   21: aload_1
    //   22: athrow
    //   23: aload_0
    //   24: monitorexit
    //   25: return
    // Exception table:
    //   from	to	target	type
    //   6	15	18	finally
  }
  
  public void b(IPLVideoObserver paramIPLVideoObserver) {
    // Byte code:
    //   0: aload_0
    //   1: monitorenter
    //   2: aload_1
    //   3: ifnull -> 23
    //   6: aload_0
    //   7: getfield b : Ljava/util/ArrayList;
    //   10: aload_1
    //   11: invokevirtual remove : (Ljava/lang/Object;)Z
    //   14: pop
    //   15: goto -> 23
    //   18: astore_1
    //   19: aload_0
    //   20: monitorexit
    //   21: aload_1
    //   22: athrow
    //   23: aload_0
    //   24: monitorexit
    //   25: return
    // Exception table:
    //   from	to	target	type
    //   6	15	18	finally
  }
  
  public static interface IPLVideoObserver {}
}


/* Location:              D:\code\BluedHook\classes.dex\com.soft.blued5032032-dex2jar.jar!\com\blued\android\module\media\selector\observer\PLVideoObserver.class
 * Java compiler version: 6 (50.0)
 * JD-Core Version:       1.1.3
 */